Workbook
Name _DLX10.USE: #REF!
Name _DLX11.USE: acm!$A$2:$E$6
Name _DLX12.USE: cr!$A$2:$E$6
Name _DLX3344.USE: #REF!
Name _DLX399.USE: cbo_debt_lt!$A$2:$H$6
Name _DLX4.USE: ffr!$A$1:$C$5
Name _DLX482.USE: cbo_debt!$A$2:$CS$5
Name _DLX482.USE: cbo_deficit!$A$2:$CS$5
Name _DLX482.USE: cbo_deficit_gdp!$A$2:$CS$5
Name _DLX482.USE: cbo_interest!$A$2:$CS$5
Name _DLX482.USE: cbo_interest_gdp!$A$2:$CS$5
Name _DLX482.USE: cbo_ngdp!$A$2:$CS$5
Name _DLX482.USE: cbo_outlays!$A$2:$CS$5
Name _DLX482.USE: cbo_outlays_gdp!$A$2:$CS$5
Name _DLX482.USE: cbo_primary_deficit!$A$2:$CS$5
Name _DLX482.USE: cbo_primary_deficit_gdp!$A$2:$CS$5
Name _DLX482.USE: cbo_revenues!$A$2:$CS$5
Name _DLX482.USE: cbo_revenues_gdp!$A$2:$CS$5
Name _DLX482.USE: cbo_rgdp!$A$2:$CR$5
Name _DLX482.USE: omb_debt!$A$2:$DL$5
Name _DLX482.USE: omb_debt_gdp!$A$2:$DM$5
Name _DLX482.USE: omb_ngdp!$A$2:$DL$5
Name _DLX482.USE: cbo_debt_gdp!$A$2:$CS$5
Name _DLX55.USE: 'Fixed Assets'!$A$1:$G$4
Name _DLX6.USE: treasuries_zc!$A$2:$G$6
Name _DLX66.USE: 'Capital Share'!$A$1:$E$4
Name _DLX6644.USE: frbus_infl!$A$2:$G$6
Name _DLX7.USE: divyield!$A$2:$H$6
Name _DLX8.USE: dkw!$A$2:$H$6
Name _DLX9.USE: treas_holdings!$A$2:$I$6

Sheet final
A1: date | B1: obs | C1: i5y5y_zc | D1: i10y5y_zc | E1: i5y10y_zc | F1: i10y_zc | G1: i5y3m_zc | H1: i10y3m_zc | I1: debt_y0 | J1: debt_y5 | K1: debt_y10 | L1: deficit_y0 | M1: deficit_y5 | N1: deficit_y10 | O1: pr_deficit_y0 | P1: pr_deficit_y5 | Q1: pr_deficit_y10 | R1: revenues_y0 | S1: revenues_y5 | T1: revenues_y10 | U1: outlays_y0 | V1: outlays_y5 | W1: outlays_y10 | X1: interest_y0 | Y1: interest_y5 | Z1: interest_y10 | AA1: rgdp_y0 | AB1: rgdp_y5 | AC1: rgdp_y10 | AD1: frbus_pi_y10 | AE1: spf_cpi_y5y5 | AF1: spf_cpi_y10 | AG1: fed_gdp | AH1: foreign_gdp | AI1: divyld | AJ1: ffr | AK1: dkw_ifit_y5y5 | AL1: dkw_rshort_y5y5 | AM1: dkw_rtp_y5y5 | AN1: dkw_epi_y5y5 | AO1: dkw_pirp_y5y5 | AP1: acm_ifit_y10 | AQ1: acm_tp_y10 | AR1: acm_rn_y10 | AS1: cr_ishort_y5y5 | AT1: cr_tp_y10 | AU1: cr_ishort_y10
A2: 27760 | B2: 1 | C2: =VLOOKUP(A2,treasuries_zc!$B$7:$J$1000,_xlfn.XMATCH(C$1,treasuries_zc!$B$1:$J$1,1),FALSE) -> 8.0093745 | D2: =VLOOKUP(A2,treasuries_zc!$B$7:$J$1000,_xlfn.XMATCH(D$1,treasuries_zc!$B$1:$J$1,1),FALSE) -> 8.0089578 | E2: =VLOOKUP(A2,treasuries_zc!$B$7:$J$1000,_xlfn.XMATCH(E$1,treasuries_zc!$B$1:$J$1,1),FALSE) -> 8.0091662 | F2: =VLOOKUP(A2,treasuries_zc!$B$7:$J$1000,_xlfn.XMATCH(F$1,treasuries_zc!$B$1:$J$1,1),FALSE) -> 7.6687 | G2: =VLOOKUP(A2,treasuries_zc!$B$7:$J$1000,_xlfn.XMATCH(G$1,treasuries_zc!$B$1:$J$1,1),FALSE) -> 8.0073 | H2: =VLOOKUP(A2,treasuries_zc!$B$7:$J$1000,_xlfn.XMATCH(H$1,treasuries_zc!$B$1:$J$1,1),FALSE) -> 8.0085 | I2: =cbo_debt_gdp!CX7 -> 27.669617 | J2: =cbo_debt_gdp!CZ7 -> 10.731707 | K2: =cbo_debt_gdp!DB7 -> #N/A | L2: =cbo_deficit_gdp!CX7 -> 4.3657817 | M2: =cbo_deficit_gdp!CZ7 -> -2.9918699 | N2: =cbo_deficit_gdp!DB7 -> #N/A | O2: =cbo_primary_deficit_gdp!CX7 -> 2.7728614 | P2: =cbo_primary_deficit_gdp!CZ7 -> -4.2276423 | Q2: =cbo_primary_deficit_gdp!DB7 -> #N/A | R2: =cbo_revenues_gdp!CX7 -> 17.758112 | S2: =cbo_revenues_gdp!CZ7 -> 21.203252 | T2: =cbo_revenues_gdp!DB7 -> #N/A | U2: =cbo_outlays_gdp!CX7 -> 22.123894 | V2: =cbo_outlays_gdp!CZ7 -> 18.211382 | W2: =cbo_outlays_gdp!DB7 -> #N/A | X2: =cbo_interest_gdp!CX7 -> 1.5929204 | Y2: =cbo_interest_gdp!CZ7 -> 1.2357724 | Z2: =cbo_interest_gdp!DB7 -> #N/A | AA2: =cbo_rgdp!CX7 -> 6.7 | AB2: =cbo_rgdp!CZ7 -> 6.6 | AC2: =cbo_rgdp!DB7 -> #N/A | AD2: =IFERROR(IFERROR(VLOOKUP(A2,frbus_infl!$B$7:$H$1000,7,FALSE),VLOOKUP(A2,frbus_infl!$C$7:$H$1000,6,FALSE)),VLOOKUP(A2,frbus_infl!$D$7:$H$1000,5,FALSE)) -> 4.8788333 | AE2: =IFERROR(IFERROR(VLOOKUP(A2,frbus_infl!$B$7:$I$1000,8,FALSE),VLOOKUP(A2,frbus_infl!$C$7:$I$1000,7,FALSE)),VLOOKUP(A2,frbus_infl!$D$7:$I$1000,6,FALSE)) -> #N/A | AF2: =IFERROR(IFERROR(VLOOKUP(A2,frbus_infl!$B$7:$I$1000,5,FALSE),VLOOKUP(A2,frbus_infl!$C$7:$I$1000,4,FALSE)),VLOOKUP(A2,frbus_infl!$D$7:$I$1000,3,FALSE)) -> #N/A | AG2: =IFERROR(IFERROR(VLOOKUP(A2,treas_holdings!$B$7:$I$1000,7,FALSE),VLOOKUP(A2,treas_holdings!$C$7:$I$1000,6,FALSE)),VLOOKUP(A2,treas_holdings!$D$7:$I$1000,5,FALSE)) -> 4.7950014 | AH2: =IFERROR(IFERROR(VLOOKUP(A2,treas_holdings!$B$7:$I$1000,8,FALSE),VLOOKUP(A2,treas_holdings!$C$7:$I$1000,7,FALSE)),VLOOKUP(A2,treas_holdings!$D$7:$I$1000,6,FALSE)) -> 3.4687723 | AI2: =IFERROR(IFERROR(VLOOKUP(A2,divyield!$B$7:$E$1001,4,FALSE),VLOOKUP(A2,divyield!$C$7:$E$1001,3,FALSE)),VLOOKUP(A2,divyield!$D$7:$E$1001,2,FALSE)) -> 3.4960883 | AJ2: =VLOOKUP(A2,ffr!$B$6:$C$1000,2) -> 4.84 | AK2: =VLOOKUP(A2,dkw!$B$7:$H$1001,3,FALSE) -> #N/A | AL2: =VLOOKUP(A2,dkw!$B$7:$H$1001,4,FALSE) -> #N/A | AM2: =VLOOKUP(A2,dkw!$B$7:$H$1001,5,FALSE) -> #N/A | AN2: =VLOOKUP(A2,dkw!$B$7:$H$1001,6,FALSE) -> #N/A | AO2: =VLOOKUP(A2,dkw!$B$7:$H$1001,7,FALSE) -> #N/A | AP2: =VLOOKUP(A2,acm!B$7:E$1001,2,FALSE) -> 7.66327 | AQ2: =VLOOKUP(A2,acm!B$7:E$1001,3,FALSE) -> 2.41473 | AR2: =VLOOKUP(A2,acm!B$7:E$1001,4,FALSE) -> 5.24854 | AS2: =VLOOKUP(A2,cr!B$7:F$1001,5,FALSE) -> #N/A | AT2: =VLOOKUP(A2,cr!B$7:F$1001,4,FALSE) -> #N/A | AU2: =VLOOKUP(A2,cr!B$7:F$1001,2,FALSE) -> #N/A
A3: 28095 | B3: 2 | C3: =VLOOKUP(A3,treasuries_zc!$B$7:$J$1000,_xlfn.XMATCH(C$1,treasuries_zc!$B$1:$J$1,1),FALSE) -> 7.2808838 | D3: =VLOOKUP(A3,treasuries_zc!$B$7:$J$1000,_xlfn.XMATCH(D$1,treasuries_zc!$B$1:$J$1,1),FALSE) -> 7.350582 | E3: =VLOOKUP(A3,treasuries_zc!$B$7:$J$1000,_xlfn.XMATCH(E$1,treasuries_zc!$B$1:$J$1,1),FALSE) -> 7.3157272 | F3: =VLOOKUP(A3,treasuries_zc!$B$7:$J$1000,_xlfn.XMATCH(F$1,treasuries_zc!$B$1:$J$1,1),FALSE) -> 6.7344 | G3: =VLOOKUP(A3,treasuries_zc!$B$7:$J$1000,_xlfn.XMATCH(G$1,treasuries_zc!$B$1:$J$1,1),FALSE) -> 7.134 | H3: =VLOOKUP(A3,treasuries_zc!$B$7:$J$1000,_xlfn.XMATCH(H$1,treasuries_zc!$B$1:$J$1,1),FALSE) -> 7.3424 | I3: =cbo_debt_gdp!CX8 -> 28.75817 | J3: =cbo_debt_gdp!CZ8 -> 19.343066 | K3: =cbo_debt_gdp!DB8 -> #N/A | L3: =cbo_deficit_gdp!CX8 -> 2.7777778 | M3: =cbo_deficit_gdp!CZ8 -> -1.6788321 | N3: =cbo_deficit_gdp!DB8 -> #N/A | O3: =cbo_primary_deficit_gdp!CX8 -> 1.1437908 | P3: =cbo_primary_deficit_gdp!CZ8 -> -3.1386861 | Q3: =cbo_primary_deficit_gdp!DB8 -> #N/A | R3: =cbo_revenues_gdp!CX8 -> 19.771242 | S3: =cbo_revenues_gdp!CZ8 -> 21.678832 | T3: =cbo_revenues_gdp!DB8 -> #N/A | U3: =cbo_outlays_gdp!CX8 -> 22.494553 | V3: =cbo_outlays_gdp!CZ8 -> 20 | W3: =cbo_outlays_gdp!DB8 -> #N/A | X3: =cbo_interest_gdp!CX8 -> 1.6339869 | Y3: =cbo_interest_gdp!CZ8 -> 1.459854 | Z3: =cbo_interest_gdp!DB8 -> #N/A | AA3: =cbo_rgdp!CX8 -> 5.5 | AB3: =cbo_rgdp!CZ8 -> 4.8 | AC3: =cbo_rgdp!DB8 -> #N/A | AD3: =IFERROR(IFERROR(VLOOKUP(A3,frbus_infl!$B$7:$H$1000,7,FALSE),VLOOKUP(A3,frbus_infl!$C$7:$H$1000,6,FALSE)),VLOOKUP(A3,frbus_infl!$D$7:$H$1000,5,FALSE)) -> 4.4988 | AE3: =IFERROR(IFERROR(VLOOKUP(A3,frbus_infl!$B$7:$I$1000,8,FALSE),VLOOKUP(A3,frbus_infl!$C$7:$I$1000,7,FALSE)),VLOOKUP(A3,frbus_infl!$D$7:$I$1000,6,FALSE)) -> #N/A | AF3: =IFERROR(IFERROR(VLOOKUP(A3,frbus_infl!$B$7:$I$1000,5,FALSE),VLOOKUP(A3,frbus_infl!$C$7:$I$1000,4,FALSE)),VLOOKUP(A3,frbus_infl!$D$7:$I$1000,3,FALSE)) -> #N/A | AG3: =IFERROR(IFERROR(VLOOKUP(A3,treas_holdings!$B$7:$I$1000,7,FALSE),VLOOKUP(A3,treas_holdings!$C$7:$I$1000,6,FALSE)),VLOOKUP(A3,treas_holdings!$D$7:$I$1000,5,FALSE)) -> 4.821796 | AH3: =IFERROR(IFERROR(VLOOKUP(A3,treas_holdings!$B$7:$I$1000,8,FALSE),VLOOKUP(A3,treas_holdings!$C$7:$I$1000,7,FALSE)),VLOOKUP(A3,treas_holdings!$D$7:$I$1000,6,FALSE)) -> 3.6475728 | AI3: =IFERROR(IFERROR(VLOOKUP(A3,divyield!$B$7:$E$1001,4,FALSE),VLOOKUP(A3,divyield!$C$7:$E$1001,3,FALSE)),VLOOKUP(A3,divyield!$D$7:$E$1001,2,FALSE)) -> 4.0442406 | AJ3: =VLOOKUP(A3,ffr!$B$6:$C$1000,2) -> 4.17 | AK3: =VLOOKUP(A3,dkw!$B$7:$H$1001,3,FALSE) -> #N/A | AL3: =VLOOKUP(A3,dkw!$B$7:$H$1001,4,FALSE) -> #N/A | AM3: =VLOOKUP(A3,dkw!$B$7:$H$1001,5,FALSE) -> #N/A | AN3: =VLOOKUP(A3,dkw!$B$7:$H$1001,6,FALSE) -> #N/A | AO3: =VLOOKUP(A3,dkw!$B$7:$H$1001,7,FALSE) -> #N/A | AP3: =VLOOKUP(A3,acm!B$7:E$1001,2,FALSE) -> 6.74373 | AQ3: =VLOOKUP(A3,acm!B$7:E$1001,3,FALSE) -> 2.17446 | AR3: =VLOOKUP(A3,acm!B$7:E$1001,4,FALSE) -> 4.56927 | AS3: =VLOOKUP(A3,cr!B$7:F$1001,5,FALSE) -> #N/A | AT3: =VLOOKUP(A3,cr!B$7:F$1001,4,FALSE) -> #N/A | AU3: =VLOOKUP(A3,cr!B$7:F$1001,2,FALSE) -> #N/A
A4: 28460 | B4: 3 | C4: =VLOOKUP(A4,treasuries_zc!$B$7:$J$1000,_xlfn.XMATCH(C$1,treasuries_zc!$B$1:$J$1,1),FALSE) -> 7.9051504 | D4: =VLOOKUP(A4,treasuries_zc!$B$7:$J$1000,_xlfn.XMATCH(D$1,treasuries_zc!$B$1:$J$1,1),FALSE) -> 7.9350938 | E4: =VLOOKUP(A4,treasuries_zc!$B$7:$J$1000,_xlfn.XMATCH(E$1,treasuries_zc!$B$1:$J$1,1),FALSE) -> 7.9201211 | F4: =VLOOKUP(A4,treasuries_zc!$B$7:$J$1000,_xlfn.XMATCH(F$1,treasuries_zc!$B$1:$J$1,1),FALSE) -> 7.6847 | G4: =VLOOKUP(A4,treasuries_zc!$B$7:$J$1000,_xlfn.XMATCH(G$1,treasuries_zc!$B$1:$J$1,1),FALSE) -> 7.8494 | H4: =VLOOKUP(A4,treasuries_zc!$B$7:$J$1000,_xlfn.XMATCH(H$1,treasuries_zc!$B$1:$J$1,1),FALSE) -> 7.9313 | I4: =cbo_debt_gdp!CX9 -> 29.654837 | J4: =cbo_debt_gdp!CZ9 -> 18.544982 | K4: =cbo_debt_gdp!DB9 -> #N/A | L4: =cbo_deficit_gdp!CX9 -> 2.9654837 | M4: =cbo_deficit_gdp!CZ9 -> -2.0136408 | N4: =cbo_deficit_gdp!DB9 -> #N/A | O4: =cbo_primary_deficit_gdp!CX9 -> 1.3612056 | P4: =cbo_primary_deficit_gdp!CZ9 -> -3.37772 | Q4: =cbo_primary_deficit_gdp!DB9 -> #N/A | R4: =cbo_revenues_gdp!CX9 -> 19.299951 | S4: =cbo_revenues_gdp!CZ9 -> 21.695356 | T4: =cbo_revenues_gdp!DB9 -> #N/A | U4: =cbo_outlays_gdp!CX9 -> 22.265435 | V4: =cbo_outlays_gdp!CZ9 -> 19.681715 | W4: =cbo_outlays_gdp!DB9 -> #N/A | X4: =cbo_interest_gdp!CX9 -> 1.6042781 | Y4: =cbo_interest_gdp!CZ9 -> 1.3640792 | Z4: =cbo_interest_gdp!DB9 -> #N/A | AA4: =cbo_rgdp!CX9 -> 5.2 | AB4: =cbo_rgdp!CZ9 -> 4.8 | AC4: =cbo_rgdp!DB9 -> #N/A | AD4: =IFERROR(IFERROR(VLOOKUP(A4,frbus_infl!$B$7:$H$1000,7,FALSE),VLOOKUP(A4,frbus_infl!$C$7:$H$1000,6,FALSE)),VLOOKUP(A4,frbus_infl!$D$7:$H$1000,5,FALSE)) -> 4.8504 | AE4: =IFERROR(IFERROR(VLOOKUP(A4,frbus_infl!$B$7:$I$1000,8,FALSE),VLOOKUP(A4,frbus_infl!$C$7:$I$1000,7,FALSE)),VLOOKUP(A4,frbus_infl!$D$7:$I$1000,6,FALSE)) -> #N/A | AF4: =IFERROR(IFERROR(VLOOKUP(A4,frbus_infl!$B$7:$I$1000,5,FALSE),VLOOKUP(A4,frbus_infl!$C$7:$I$1000,4,FALSE)),VLOOKUP(A4,frbus_infl!$D$7:$I$1000,3,FALSE)) -> #N/A | AG4: =IFERROR(IFERROR(VLOOKUP(A4,treas_holdings!$B$7:$I$1000,7,FALSE),VLOOKUP(A4,treas_holdings!$C$7:$I$1000,6,FALSE)),VLOOKUP(A4,treas_holdings!$D$7:$I$1000,5,FALSE)) -> 4.6628471 | AH4: =IFERROR(IFERROR(VLOOKUP(A4,treas_holdings!$B$7:$I$1000,8,FALSE),VLOOKUP(A4,treas_holdings!$C$7:$I$1000,7,FALSE)),VLOOKUP(A4,treas_holdings!$D$7:$I$1000,6,FALSE)) -> 4.6708867 | AI4: =IFERROR(IFERROR(VLOOKUP(A4,divyield!$B$7:$E$1001,4,FALSE),VLOOKUP(A4,divyield!$C$7:$E$1001,3,FALSE)),VLOOKUP(A4,divyield!$D$7:$E$1001,2,FALSE)) -> 5.2676489 | AJ4: =VLOOKUP(A4,ffr!$B$6:$C$1000,2) -> 6.53 | AK4: =VLOOKUP(A4,dkw!$B$7:$H$1001,3,FALSE) -> #N/A | AL4: =VLOOKUP(A4,dkw!$B$7:$H$1001,4,FALSE) -> #N/A | AM4: =VLOOKUP(A4,dkw!$B$7:$H$1001,5,FALSE) -> #N/A | AN4: =VLOOKUP(A4,dkw!$B$7:$H$1001,6,FALSE) -> #N/A | AO4: =VLOOKUP(A4,dkw!$B$7:$H$1001,7,FALSE) -> #N/A | AP4: =VLOOKUP(A4,acm!B$7:E$1001,2,FALSE) -> 7.69327 | AQ4: =VLOOKUP(A4,acm!B$7:E$1001,3,FALSE) -> 2.01431 | AR4: =VLOOKUP(A4,acm!B$7:E$1001,4,FALSE) -> 5.67896 | AS4: =VLOOKUP(A4,cr!B$7:F$1001,5,FALSE) -> #N/A | AT4: =VLOOKUP(A4,cr!B$7:F$1001,4,FALSE) -> #N/A | AU4: =VLOOKUP(A4,cr!B$7:F$1001,2,FALSE) -> #N/A
A5: 28856 | B5: 4 | C5: =VLOOKUP(A5,treasuries_zc!$B$7:$J$1000,_xlfn.XMATCH(C$1,treasuries_zc!$B$1:$J$1,1),FALSE) -> 8.3691604 | D5: =VLOOKUP(A5,treasuries_zc!$B$7:$J$1000,_xlfn.XMATCH(D$1,treasuries_zc!$B$1:$J$1,1),FALSE) -> 8.3689203 | E5: =VLOOKUP(A5,treasuries_zc!$B$7:$J$1000,_xlfn.XMATCH(E$1,treasuries_zc!$B$1:$J$1,1),FALSE) -> 8.3690404 | F5: =VLOOKUP(A5,treasuries_zc!$B$7:$J$1000,_xlfn.XMATCH(F$1,treasuries_zc!$B$1:$J$1,1),FALSE) -> 8.5668 | G5: =VLOOKUP(A5,treasuries_zc!$B$7:$J$1000,_xlfn.XMATCH(G$1,treasuries_zc!$B$1:$J$1,1),FALSE) -> 8.3689 | H5: =VLOOKUP(A5,treasuries_zc!$B$7:$J$1000,_xlfn.XMATCH(H$1,treasuries_zc!$B$1:$J$1,1),FALSE) -> 8.3687 | I5: =cbo_debt_gdp!CX10 -> 28.173913 | J5: =cbo_debt_gdp!CZ10 -> 15.02444 | K5: =cbo_debt_gdp!DB10 -> #N/A | L5: =cbo_deficit_gdp!CX10 -> 1.7826087 | M5: =cbo_deficit_gdp!CZ10 -> -2.4183175 | N5: =cbo_deficit_gdp!DB10 -> #N/A | O5: =cbo_primary_deficit_gdp!CX10 -> 0.26086957 | P5: =cbo_primary_deficit_gdp!CZ10 -> -3.5194237 | Q5: =cbo_primary_deficit_gdp!DB10 -> #N/A | R5: =cbo_revenues_gdp!CX10 -> 19.695652 | S5: =cbo_revenues_gdp!CZ10 -> 21.842038 | T5: =cbo_revenues_gdp!DB10 -> #N/A | U5: =cbo_outlays_gdp!CX10 -> 21.478261 | V5: =cbo_outlays_gdp!CZ10 -> 19.42372 | W5: =cbo_outlays_gdp!DB10 -> #N/A | X5: =cbo_interest_gdp!CX10 -> 1.5217391 | Y5: =cbo_interest_gdp!CZ10 -> 1.1011063 | Z5: =cbo_interest_gdp!DB10 -> #N/A | AA5: =cbo_rgdp!CX10 -> 3.9 | AB5: =cbo_rgdp!CZ10 -> 4.5 | AC5: =cbo_rgdp!DB10 -> #N/A | AD5: =IFERROR(IFERROR(VLOOKUP(A5,frbus_infl!$B$7:$H$1000,7,FALSE),VLOOKUP(A5,frbus_infl!$C$7:$H$1000,6,FALSE)),VLOOKUP(A5,frbus_infl!$D$7:$H$1000,5,FALSE)) -> 6.1473 | AE5: =IFERROR(IFERROR(VLOOKUP(A5,frbus_infl!$B$7:$I$1000,8,FALSE),VLOOKUP(A5,frbus_infl!$C$7:$I$1000,7,FALSE)),VLOOKUP(A5,frbus_infl!$D$7:$I$1000,6,FALSE)) -> #N/A | AF5: =IFERROR(IFERROR(VLOOKUP(A5,frbus_infl!$B$7:$I$1000,5,FALSE),VLOOKUP(A5,frbus_infl!$C$7:$I$1000,4,FALSE)),VLOOKUP(A5,frbus_infl!$D$7:$I$1000,3,FALSE)) -> #N/A | AG5: =IFERROR(IFERROR(VLOOKUP(A5,treas_holdings!$B$7:$I$1000,7,FALSE),VLOOKUP(A5,treas_holdings!$C$7:$I$1000,6,FALSE)),VLOOKUP(A5,treas_holdings!$D$7:$I$1000,5,FALSE)) -> 4.3243885 | AH5: =IFERROR(IFERROR(VLOOKUP(A5,treas_holdings!$B$7:$I$1000,8,FALSE),VLOOKUP(A5,treas_holdings!$C$7:$I$1000,7,FALSE)),VLOOKUP(A5,treas_holdings!$D$7:$I$1000,6,FALSE)) -> 4.5578643 | AI5: =IFERROR(IFERROR(VLOOKUP(A5,divyield!$B$7:$E$1001,4,FALSE),VLOOKUP(A5,divyield!$C$7:$E$1001,3,FALSE)),VLOOKUP(A5,divyield!$D$7:$E$1001,2,FALSE)) -> 5.5197287 | AJ5: =VLOOKUP(A5,ffr!$B$6:$C$1000,2) -> 10.57 | AK5: =VLOOKUP(A5,dkw!$B$7:$H$1001,3,FALSE) -> #N/A | AL5: =VLOOKUP(A5,dkw!$B$7:$H$1001,4,FALSE) -> #N/A | AM5: =VLOOKUP(A5,dkw!$B$7:$H$1001,5,FALSE) -> #N/A | AN5: =VLOOKUP(A5,dkw!$B$7:$H$1001,6,FALSE) -> #N/A | AO5: =VLOOKUP(A5,dkw!$B$7:$H$1001,7,FALSE) -> #N/A | AP5: =VLOOKUP(A5,acm!B$7:E$1001,2,FALSE) -> 8.59173 | AQ5: =VLOOKUP(A5,acm!B$7:E$1001,3,FALSE) -> 1.53715 | AR5: =VLOOKUP(A5,acm!B$7:E$1001,4,FALSE) -> 7.05458 | AS5: =VLOOKUP(A5,cr!B$7:F$1001,5,FALSE) -> #N/A | AT5: =VLOOKUP(A5,cr!B$7:F$1001,4,FALSE) -> #N/A | AU5: =VLOOKUP(A5,cr!B$7:F$1001,2,FALSE) -> #N/A
A6: 29252 | B6: 5 | C6: =VLOOKUP(A6,treasuries_zc!$B$7:$J$1000,_xlfn.XMATCH(C$1,treasuries_zc!$B$1:$J$1,1),FALSE) -> 11.600305 | D6: =VLOOKUP(A6,treasuries_zc!$B$7:$J$1000,_xlfn.XMATCH(D$1,treasuries_zc!$B$1:$J$1,1),FALSE) -> 11.828698 | E6: =VLOOKUP(A6,treasuries_zc!$B$7:$J$1000,_xlfn.XMATCH(E$1,treasuries_zc!$B$1:$J$1,1),FALSE) -> 11.714443 | F6: =VLOOKUP(A6,treasuries_zc!$B$7:$J$1000,_xlfn.XMATCH(F$1,treasuries_zc!$B$1:$J$1,1),FALSE) -> 12.0101 | G6: =VLOOKUP(A6,treasuries_zc!$B$7:$J$1000,_xlfn.XMATCH(G$1,treasuries_zc!$B$1:$J$1,1),FALSE) -> 11.2688 | H6: =VLOOKUP(A6,treasuries_zc!$B$7:$J$1000,_xlfn.XMATCH(H$1,treasuries_zc!$B$1:$J$1,1),FALSE) -> 11.8002 | I6: =cbo_debt_gdp!CX11 -> 27.306977 | J6: =cbo_debt_gdp!CZ11 -> 15.871658 | K6: =cbo_debt_gdp!DB11 -> #N/A | L6: =cbo_deficit_gdp!CX11 -> 1.7565891 | M6: =cbo_deficit_gdp!CZ11 -> -1.3604278 | N6: =cbo_deficit_gdp!DB11 -> #N/A | O6: =cbo_primary_deficit_gdp!CX11 -> -0.27945736 | P6: =cbo_primary_deficit_gdp!CZ11 -> -2.6528342 | Q6: =cbo_primary_deficit_gdp!DB11 -> #N/A | R6: =cbo_revenues_gdp!CX11 -> 20.6 | S6: =cbo_revenues_gdp!CZ11 -> 21.2 | T6: =cbo_revenues_gdp!DB11 -> #N/A | U6: =cbo_outlays_gdp!CX11 -> 22.3 | V6: =cbo_outlays_gdp!CZ11 -> 19.9 | W6: =cbo_outlays_gdp!DB11 -> #N/A | X6: =cbo_interest_gdp!CX11 -> 2.0360465 | Y6: =cbo_interest_gdp!CZ11 -> 1.2924064 | Z6: =cbo_interest_gdp!DB11 -> #N/A | AA6: =cbo_rgdp!CX11 -> -0.9 | AB6: =cbo_rgdp!CZ11 -> 3.8 | AC6: =cbo_rgdp!DB11 -> #N/A | AD6: =IFERROR(IFERROR(VLOOKUP(A6,frbus_infl!$B$7:$H$1000,7,FALSE),VLOOKUP(A6,frbus_infl!$C$7:$H$1000,6,FALSE)),VLOOKUP(A6,frbus_infl!$D$7:$H$1000,5,FALSE)) -> 6.7167 | AE6: =IFERROR(IFERROR(VLOOKUP(A6,frbus_infl!$B$7:$I$1000,8,FALSE),VLOOKUP(A6,frbus_infl!$C$7:$I$1000,7,FALSE)),VLOOKUP(A6,frbus_infl!$D$7:$I$1000,6,FALSE)) -> #N/A | AF6: =IFERROR(IFERROR(VLOOKUP(A6,frbus_infl!$B$7:$I$1000,5,FALSE),VLOOKUP(A6,frbus_infl!$C$7:$I$1000,4,FALSE)),VLOOKUP(A6,frbus_infl!$D$7:$I$1000,3,FALSE)) -> #N/A | AG6: =IFERROR(IFERROR(VLOOKUP(A6,treas_holdings!$B$7:$I$1000,7,FALSE),VLOOKUP(A6,treas_holdings!$C$7:$I$1000,6,FALSE)),VLOOKUP(A6,treas_holdings!$D$7:$I$1000,5,FALSE)) -> 4.1484694 | AH6: =IFERROR(IFERROR(VLOOKUP(A6,treas_holdings!$B$7:$I$1000,8,FALSE),VLOOKUP(A6,treas_holdings!$C$7:$I$1000,7,FALSE)),VLOOKUP(A6,treas_holdings!$D$7:$I$1000,6,FALSE)) -> 3.4551222 | AI6: =IFERROR(IFERROR(VLOOKUP(A6,divyield!$B$7:$E$1001,4,FALSE),VLOOKUP(A6,divyield!$C$7:$E$1001,3,FALSE)),VLOOKUP(A6,divyield!$D$7:$E$1001,2,FALSE)) -> 5.3379155 | AJ6: =VLOOKUP(A6,ffr!$B$6:$C$1000,2) -> 16.33 | AK6: =VLOOKUP(A6,dkw!$B$7:$H$1001,3,FALSE) -> #N/A | AL6: =VLOOKUP(A6,dkw!$B$7:$H$1001,4,FALSE) -> #N/A | AM6: =VLOOKUP(A6,dkw!$B$7:$H$1001,5,FALSE) -> #N/A | AN6: =VLOOKUP(A6,dkw!$B$7:$H$1001,6,FALSE) -> #N/A | AO6: =VLOOKUP(A6,dkw!$B$7:$H$1001,7,FALSE) -> #N/A | AP6: =VLOOKUP(A6,acm!B$7:E$1001,2,FALSE) -> 12.05624 | AQ6: =VLOOKUP(A6,acm!B$7:E$1001,3,FALSE) -> 2.80265 | AR6: =VLOOKUP(A6,acm!B$7:E$1001,4,FALSE) -> 9.25359 | AS6: =VLOOKUP(A6,cr!B$7:F$1001,5,FALSE) -> #N/A | AT6: =VLOOKUP(A6,cr!B$7:F$1001,4,FALSE) -> #N/A | AU6: =VLOOKUP(A6,cr!B$7:F$1001,2,FALSE) -> #N/A
A7: 29768 | B7: 6 | C7: =VLOOKUP(A7,treasuries_zc!$B$7:$J$1000,_xlfn.XMATCH(C$1,treasuries_zc!$B$1:$J$1,1),FALSE) -> 13.067212 | D7: =VLOOKUP(A7,treasuries_zc!$B$7:$J$1000,_xlfn.XMATCH(D$1,treasuries_zc!$B$1:$J$1,1),FALSE) -> 12.978691 | E7: =VLOOKUP(A7,treasuries_zc!$B$7:$J$1000,_xlfn.XMATCH(E$1,treasuries_zc!$B$1:$J$1,1),FALSE) -> 13.022943 | F7: =VLOOKUP(A7,treasuries_zc!$B$7:$J$1000,_xlfn.XMATCH(F$1,treasuries_zc!$B$1:$J$1,1),FALSE) -> 13.641 | G7: =VLOOKUP(A7,treasuries_zc!$B$7:$J$1000,_xlfn.XMATCH(G$1,treasuries_zc!$B$1:$J$1,1),FALSE) -> 13.2584 | H7: =VLOOKUP(A7,treasuries_zc!$B$7:$J$1000,_xlfn.XMATCH(H$1,treasuries_zc!$B$1:$J$1,1),FALSE) -> 12.9831 | I7: =cbo_debt_gdp!CX12 -> 26.916667 | J7: =cbo_debt_gdp!CZ12 -> 7.1803828 | K7: =cbo_debt_gdp!DB12 -> #N/A | L7: =cbo_deficit_gdp!CX12 -> 1.7 | M7: =cbo_deficit_gdp!CZ12 -> -4.3 | N7: =cbo_deficit_gdp!DB12 -> #N/A | O7: =cbo_primary_deficit_gdp!CX12 -> -0.6375 | P7: =cbo_primary_deficit_gdp!CZ12 -> -5.5138756 | Q7: =cbo_primary_deficit_gdp!DB12 -> #N/A | R7: =cbo_revenues_gdp!CX12 -> 21.4 | S7: =cbo_revenues_gdp!CZ12 -> 23.9 | T7: =cbo_revenues_gdp!DB12 -> #N/A | U7: =cbo_outlays_gdp!CX12 -> 23.1 | V7: =cbo_outlays_gdp!CZ12 -> 19.6 | W7: =cbo_outlays_gdp!DB12 -> #N/A | X7: =cbo_interest_gdp!CX12 -> 2.3 | Y7: =cbo_interest_gdp!CZ12 -> 1.2 | Z7: =cbo_interest_gdp!DB12 -> #N/A | AA7: =cbo_rgdp!CX12 -> 2 | AB7: =cbo_rgdp!CZ12 -> 4.2 | AC7: =cbo_rgdp!DB12 -> #N/A | AD7: =IFERROR(IFERROR(VLOOKUP(A7,frbus_infl!$B$7:$H$1000,7,FALSE),VLOOKUP(A7,frbus_infl!$C$7:$H$1000,6,FALSE)),VLOOKUP(A7,frbus_infl!$D$7:$H$1000,5,FALSE)) -> 7.22 | AE7: =IFERROR(IFERROR(VLOOKUP(A7,frbus_infl!$B$7:$I$1000,8,FALSE),VLOOKUP(A7,frbus_infl!$C$7:$I$1000,7,FALSE)),VLOOKUP(A7,frbus_infl!$D$7:$I$1000,6,FALSE)) -> #N/A | AF7: =IFERROR(IFERROR(VLOOKUP(A7,frbus_infl!$B$7:$I$1000,5,FALSE),VLOOKUP(A7,frbus_infl!$C$7:$I$1000,4,FALSE)),VLOOKUP(A7,frbus_infl!$D$7:$I$1000,3,FALSE)) -> #N/A | AG7: =IFERROR(IFERROR(VLOOKUP(A7,treas_holdings!$B$7:$I$1000,7,FALSE),VLOOKUP(A7,treas_holdings!$C$7:$I$1000,6,FALSE)),VLOOKUP(A7,treas_holdings!$D$7:$I$1000,5,FALSE)) -> 3.8131019 | AH7: =IFERROR(IFERROR(VLOOKUP(A7,treas_holdings!$B$7:$I$1000,8,FALSE),VLOOKUP(A7,treas_holdings!$C$7:$I$1000,7,FALSE)),VLOOKUP(A7,treas_holdings!$D$7:$I$1000,6,FALSE)) -> 3.4314237 | AI7: =IFERROR(IFERROR(VLOOKUP(A7,divyield!$B$7:$E$1001,4,FALSE),VLOOKUP(A7,divyield!$C$7:$E$1001,3,FALSE)),VLOOKUP(A7,divyield!$D$7:$E$1001,2,FALSE)) -> 6.3722535 | AJ7: =VLOOKUP(A7,ffr!$B$6:$C$1000,2) -> 17.46 | AK7: =VLOOKUP(A7,dkw!$B$7:$H$1001,3,FALSE) -> #N/A | AL7: =VLOOKUP(A7,dkw!$B$7:$H$1001,4,FALSE) -> #N/A | AM7: =VLOOKUP(A7,dkw!$B$7:$H$1001,5,FALSE) -> #N/A | AN7: =VLOOKUP(A7,dkw!$B$7:$H$1001,6,FALSE) -> #N/A | AO7: =VLOOKUP(A7,dkw!$B$7:$H$1001,7,FALSE) -> #N/A | AP7: =VLOOKUP(A7,acm!B$7:E$1001,2,FALSE) -> 13.64153 | AQ7: =VLOOKUP(A7,acm!B$7:E$1001,3,FALSE) -> 3.1892 | AR7: =VLOOKUP(A7,acm!B$7:E$1001,4,FALSE) -> 10.45233 | AS7: =VLOOKUP(A7,cr!B$7:F$1001,5,FALSE) -> #N/A | AT7: =VLOOKUP(A7,cr!B$7:F$1001,4,FALSE) -> #N/A | AU7: =VLOOKUP(A7,cr!B$7:F$1001,2,FALSE) -> #N/A
A8: 29983 | B8: 7 | C8: =VLOOKUP(A8,treasuries_zc!$B$7:$J$1000,_xlfn.XMATCH(C$1,treasuries_zc!$B$1:$J$1,1),FALSE) -> 13.398502 | D8: =VLOOKUP(A8,treasuries_zc!$B$7:$J$1000,_xlfn.XMATCH(D$1,treasuries_zc!$B$1:$J$1,1),FALSE) -> 14.173082 | E8: =VLOOKUP(A8,treasuries_zc!$B$7:$J$1000,_xlfn.XMATCH(E$1,treasuries_zc!$B$1:$J$1,1),FALSE) -> 13.785133 | F8: =VLOOKUP(A8,treasuries_zc!$B$7:$J$1000,_xlfn.XMATCH(F$1,treasuries_zc!$B$1:$J$1,1),FALSE) -> 13.4151 | G8: =VLOOKUP(A8,treasuries_zc!$B$7:$J$1000,_xlfn.XMATCH(G$1,treasuries_zc!$B$1:$J$1,1),FALSE) -> 13.0418 | H8: =VLOOKUP(A8,treasuries_zc!$B$7:$J$1000,_xlfn.XMATCH(H$1,treasuries_zc!$B$1:$J$1,1),FALSE) -> 13.8784 | I8: =cbo_debt_gdp!CX13 -> 29.888372 | J8: =cbo_debt_gdp!CZ13 -> 41 | K8: =cbo_debt_gdp!DB13 -> #N/A | L8: =cbo_deficit_gdp!CX13 -> 4.2 | M8: =cbo_deficit_gdp!CZ13 -> 5.4 | N8: =cbo_deficit_gdp!DB13 -> #N/A | O8: =cbo_primary_deficit_gdp!CX13 -> 1.4325581 | P8: =cbo_primary_deficit_gdp!CZ13 -> 2.04 | Q8: =cbo_primary_deficit_gdp!DB13 -> #N/A | R8: =cbo_revenues_gdp!CX13 -> 20.6 | S8: =cbo_revenues_gdp!CZ13 -> 17.7 | T8: =cbo_revenues_gdp!DB13 -> #N/A | U8: =cbo_outlays_gdp!CX13 -> 24.9 | V8: =cbo_outlays_gdp!CZ13 -> 23.1 | W8: =cbo_outlays_gdp!DB13 -> #N/A | X8: =cbo_interest_gdp!CX13 -> 2.8 | Y8: =cbo_interest_gdp!CZ13 -> 3.4 | Z8: =cbo_interest_gdp!DB13 -> #N/A | AA8: =cbo_rgdp!CX13 -> -0.1 | AB8: =cbo_rgdp!CZ13 -> 3.5 | AC8: =cbo_rgdp!DB13 -> #N/A | AD8: =IFERROR(IFERROR(VLOOKUP(A8,frbus_infl!$B$7:$H$1000,7,FALSE),VLOOKUP(A8,frbus_infl!$C$7:$H$1000,6,FALSE)),VLOOKUP(A8,frbus_infl!$D$7:$H$1000,5,FALSE)) -> 6.76 | AE8: =IFERROR(IFERROR(VLOOKUP(A8,frbus_infl!$B$7:$I$1000,8,FALSE),VLOOKUP(A8,frbus_infl!$C$7:$I$1000,7,FALSE)),VLOOKUP(A8,frbus_infl!$D$7:$I$1000,6,FALSE)) -> #N/A | AF8: =IFERROR(IFERROR(VLOOKUP(A8,frbus_infl!$B$7:$I$1000,5,FALSE),VLOOKUP(A8,frbus_infl!$C$7:$I$1000,4,FALSE)),VLOOKUP(A8,frbus_infl!$D$7:$I$1000,3,FALSE)) -> #N/A | AG8: =IFERROR(IFERROR(VLOOKUP(A8,treas_holdings!$B$7:$I$1000,7,FALSE),VLOOKUP(A8,treas_holdings!$C$7:$I$1000,6,FALSE)),VLOOKUP(A8,treas_holdings!$D$7:$I$1000,5,FALSE)) -> 3.7868247 | AH8: =IFERROR(IFERROR(VLOOKUP(A8,treas_holdings!$B$7:$I$1000,8,FALSE),VLOOKUP(A8,treas_holdings!$C$7:$I$1000,7,FALSE)),VLOOKUP(A8,treas_holdings!$D$7:$I$1000,6,FALSE)) -> 3.5328773 | AI8: =IFERROR(IFERROR(VLOOKUP(A8,divyield!$B$7:$E$1001,4,FALSE),VLOOKUP(A8,divyield!$C$7:$E$1001,3,FALSE)),VLOOKUP(A8,divyield!$D$7:$E$1001,2,FALSE)) -> 7.3683108 | AJ8: =VLOOKUP(A8,ffr!$B$6:$C$1000,2) -> 13.74 | AK8: =VLOOKUP(A8,dkw!$B$7:$H$1001,3,FALSE) -> #N/A | AL8: =VLOOKUP(A8,dkw!$B$7:$H$1001,4,FALSE) -> #N/A | AM8: =VLOOKUP(A8,dkw!$B$7:$H$1001,5,FALSE) -> #N/A | AN8: =VLOOKUP(A8,dkw!$B$7:$H$1001,6,FALSE) -> #N/A | AO8: =VLOOKUP(A8,dkw!$B$7:$H$1001,7,FALSE) -> #N/A | AP8: =VLOOKUP(A8,acm!B$7:E$1001,2,FALSE) -> 13.39092 | AQ8: =VLOOKUP(A8,acm!B$7:E$1001,3,FALSE) -> 4.19835 | AR8: =VLOOKUP(A8,acm!B$7:E$1001,4,FALSE) -> 9.19258 | AS8: =VLOOKUP(A8,cr!B$7:F$1001,5,FALSE) -> #N/A | AT8: =VLOOKUP(A8,cr!B$7:F$1001,4,FALSE) -> #N/A | AU8: =VLOOKUP(A8,cr!B$7:F$1001,2,FALSE) -> #N/A
A9: 30348 | B9: 8 | C9: =VLOOKUP(A9,treasuries_zc!$B$7:$J$1000,_xlfn.XMATCH(C$1,treasuries_zc!$B$1:$J$1,1),FALSE) -> 10.668087 | D9: =VLOOKUP(A9,treasuries_zc!$B$7:$J$1000,_xlfn.XMATCH(D$1,treasuries_zc!$B$1:$J$1,1),FALSE) -> 11.3867 | E9: =VLOOKUP(A9,treasuries_zc!$B$7:$J$1000,_xlfn.XMATCH(E$1,treasuries_zc!$B$1:$J$1,1),FALSE) -> 11.026812 | F9: =VLOOKUP(A9,treasuries_zc!$B$7:$J$1000,_xlfn.XMATCH(F$1,treasuries_zc!$B$1:$J$1,1),FALSE) -> 10.3548 | G9: =VLOOKUP(A9,treasuries_zc!$B$7:$J$1000,_xlfn.XMATCH(G$1,treasuries_zc!$B$1:$J$1,1),FALSE) -> 10.7422 | H9: =VLOOKUP(A9,treasuries_zc!$B$7:$J$1000,_xlfn.XMATCH(H$1,treasuries_zc!$B$1:$J$1,1),FALSE) -> 10.7676 | I9: =cbo_debt_gdp!CX14 -> 35.6 | J9: =cbo_debt_gdp!CZ14 -> 49.5 | K9: =cbo_debt_gdp!DB14 -> #N/A | L9: =cbo_deficit_gdp!CX14 -> 6.6 | M9: =cbo_deficit_gdp!CZ14 -> 5.9 | N9: =cbo_deficit_gdp!DB14 -> #N/A | O9: =cbo_primary_deficit_gdp!CX14 -> 3.8657143 | P9: =cbo_primary_deficit_gdp!CZ14 -> 3.1161972 | Q9: =cbo_primary_deficit_gdp!DB14 -> #N/A | R9: =cbo_revenues_gdp!CX14 -> 19 | S9: =cbo_revenues_gdp!CZ14 -> 18.3 | T9: =cbo_revenues_gdp!DB14 -> #N/A | U9: =cbo_outlays_gdp!CX14 -> 25 | V9: =cbo_outlays_gdp!CZ14 -> 23.9 | W9: =cbo_outlays_gdp!DB14 -> #N/A | X9: =cbo_interest_gdp!CX14 -> 2.7 | Y9: =cbo_interest_gdp!CZ14 -> 2.8 | Z9: =cbo_interest_gdp!DB14 -> #N/A | AA9: =cbo_rgdp!CX14 -> 2.1 | AB9: =cbo_rgdp!CZ14 -> 3.5 | AC9: =cbo_rgdp!DB14 -> #N/A | AD9: =IFERROR(IFERROR(VLOOKUP(A9,frbus_infl!$B$7:$H$1000,7,FALSE),VLOOKUP(A9,frbus_infl!$C$7:$H$1000,6,FALSE)),VLOOKUP(A9,frbus_infl!$D$7:$H$1000,5,FALSE)) -> 5.92 | AE9: =IFERROR(IFERROR(VLOOKUP(A9,frbus_infl!$B$7:$I$1000,8,FALSE),VLOOKUP(A9,frbus_infl!$C$7:$I$1000,7,FALSE)),VLOOKUP(A9,frbus_infl!$D$7:$I$1000,6,FALSE)) -> #N/A | AF9: =IFERROR(IFERROR(VLOOKUP(A9,frbus_infl!$B$7:$I$1000,5,FALSE),VLOOKUP(A9,frbus_infl!$C$7:$I$1000,4,FALSE)),VLOOKUP(A9,frbus_infl!$D$7:$I$1000,3,FALSE)) -> 5.3 | AG9: =IFERROR(IFERROR(VLOOKUP(A9,treas_holdings!$B$7:$I$1000,7,FALSE),VLOOKUP(A9,treas_holdings!$C$7:$I$1000,6,FALSE)),VLOOKUP(A9,treas_holdings!$D$7:$I$1000,5,FALSE)) -> 3.9342143 | AH9: =IFERROR(IFERROR(VLOOKUP(A9,treas_holdings!$B$7:$I$1000,8,FALSE),VLOOKUP(A9,treas_holdings!$C$7:$I$1000,7,FALSE)),VLOOKUP(A9,treas_holdings!$D$7:$I$1000,6,FALSE)) -> 3.6834514 | AI9: =IFERROR(IFERROR(VLOOKUP(A9,divyield!$B$7:$E$1001,4,FALSE),VLOOKUP(A9,divyield!$C$7:$E$1001,3,FALSE)),VLOOKUP(A9,divyield!$D$7:$E$1001,2,FALSE)) -> 5.7540656 | AJ9: =VLOOKUP(A9,ffr!$B$6:$C$1000,2) -> 8.53 | AK9: =VLOOKUP(A9,dkw!$B$7:$H$1001,3,FALSE) -> 10.7417 | AL9: =VLOOKUP(A9,dkw!$B$7:$H$1001,4,FALSE) -> 3.2954 | AM9: =VLOOKUP(A9,dkw!$B$7:$H$1001,5,FALSE) -> 2.9208 | AN9: =VLOOKUP(A9,dkw!$B$7:$H$1001,6,FALSE) -> 3.7725 | AO9: =VLOOKUP(A9,dkw!$B$7:$H$1001,7,FALSE) -> 0.753 | AP9: =VLOOKUP(A9,acm!B$7:E$1001,2,FALSE) -> 10.35693 | AQ9: =VLOOKUP(A9,acm!B$7:E$1001,3,FALSE) -> 3.55614 | AR9: =VLOOKUP(A9,acm!B$7:E$1001,4,FALSE) -> 6.80079 | AS9: =VLOOKUP(A9,cr!B$7:F$1001,5,FALSE) -> #N/A | AT9: =VLOOKUP(A9,cr!B$7:F$1001,4,FALSE) -> #N/A | AU9: =VLOOKUP(A9,cr!B$7:F$1001,2,FALSE) -> #N/A
A10: 30713 | B10: 9 | C10: =VLOOKUP(A10,treasuries_zc!$B$7:$J$1000,_xlfn.XMATCH(C$1,treasuries_zc!$B$1:$J$1,1),FALSE) -> 12.137928 | D10: =VLOOKUP(A10,treasuries_zc!$B$7:$J$1000,_xlfn.XMATCH(D$1,treasuries_zc!$B$1:$J$1,1),FALSE) -> 12.00709 | E10: =VLOOKUP(A10,treasuries_zc!$B$7:$J$1000,_xlfn.XMATCH(E$1,treasuries_zc!$B$1:$J$1,1),FALSE) -> 12.07249 | F10: =VLOOKUP(A10,treasuries_zc!$B$7:$J$1000,_xlfn.XMATCH(F$1,treasuries_zc!$B$1:$J$1,1),FALSE) -> 11.8333 | G10: =VLOOKUP(A10,treasuries_zc!$B$7:$J$1000,_xlfn.XMATCH(G$1,treasuries_zc!$B$1:$J$1,1),FALSE) -> 12.2385 | H10: =VLOOKUP(A10,treasuries_zc!$B$7:$J$1000,_xlfn.XMATCH(H$1,treasuries_zc!$B$1:$J$1,1),FALSE) -> 12.0395 | I10: =cbo_debt_gdp!CX15 -> 37.243896 | J10: =cbo_debt_gdp!CZ15 -> 49.377208 | K10: =cbo_debt_gdp!DB15 -> #N/A | L10: =cbo_deficit_gdp!CX15 -> 5.697446 | M10: =cbo_deficit_gdp!CZ15 -> 6.3022867 | N10: =cbo_deficit_gdp!DB15 -> #N/A | O10: =cbo_primary_deficit_gdp!CX15 -> 2.6662925 | P10: =cbo_primary_deficit_gdp!CZ15 -> 2.2308979 | Q10: =cbo_primary_deficit_gdp!DB15 -> #N/A | R10: =cbo_revenues_gdp!CX15 -> 18.607915 | S10: =cbo_revenues_gdp!CZ15 -> 18.888269 | T10: =cbo_revenues_gdp!DB15 -> #N/A | U10: =cbo_outlays_gdp!CX15 -> 24.305361 | V10: =cbo_outlays_gdp!CZ15 -> 25.190556 | W10: =cbo_outlays_gdp!DB15 -> #N/A | X10: =cbo_interest_gdp!CX15 -> 3.0311535 | Y10: =cbo_interest_gdp!CZ15 -> 4.0713887 | Z10: =cbo_interest_gdp!DB15 -> #N/A | AA10: =cbo_rgdp!CX15 -> 5.4 | AB10: =cbo_rgdp!CZ15 -> 3.3 | AC10: =cbo_rgdp!DB15 -> #N/A | AD10: =IFERROR(IFERROR(VLOOKUP(A10,frbus_infl!$B$7:$H$1000,7,FALSE),VLOOKUP(A10,frbus_infl!$C$7:$H$1000,6,FALSE)),VLOOKUP(A10,frbus_infl!$D$7:$H$1000,5,FALSE)) -> 6.18 | AE10: =IFERROR(IFERROR(VLOOKUP(A10,frbus_infl!$B$7:$I$1000,8,FALSE),VLOOKUP(A10,frbus_infl!$C$7:$I$1000,7,FALSE)),VLOOKUP(A10,frbus_infl!$D$7:$I$1000,6,FALSE)) -> #N/A | AF10: =IFERROR(IFERROR(VLOOKUP(A10,frbus_infl!$B$7:$I$1000,5,FALSE),VLOOKUP(A10,frbus_infl!$C$7:$I$1000,4,FALSE)),VLOOKUP(A10,frbus_infl!$D$7:$I$1000,3,FALSE)) -> 5.6 | AG10: =IFERROR(IFERROR(VLOOKUP(A10,treas_holdings!$B$7:$I$1000,7,FALSE),VLOOKUP(A10,treas_holdings!$C$7:$I$1000,6,FALSE)),VLOOKUP(A10,treas_holdings!$D$7:$I$1000,5,FALSE)) -> 3.8590108 | AH10: =IFERROR(IFERROR(VLOOKUP(A10,treas_holdings!$B$7:$I$1000,8,FALSE),VLOOKUP(A10,treas_holdings!$C$7:$I$1000,7,FALSE)),VLOOKUP(A10,treas_holdings!$D$7:$I$1000,6,FALSE)) -> 3.3121466 | AI10: =IFERROR(IFERROR(VLOOKUP(A10,divyield!$B$7:$E$1001,4,FALSE),VLOOKUP(A10,divyield!$C$7:$E$1001,3,FALSE)),VLOOKUP(A10,divyield!$D$7:$E$1001,2,FALSE)) -> 6.1924995 | AJ10: =VLOOKUP(A10,ffr!$B$6:$C$1000,2) -> 9.45 | AK10: =VLOOKUP(A10,dkw!$B$7:$H$1001,3,FALSE) -> 12.1545 | AL10: =VLOOKUP(A10,dkw!$B$7:$H$1001,4,FALSE) -> 3.823 | AM10: =VLOOKUP(A10,dkw!$B$7:$H$1001,5,FALSE) -> 3.4012 | AN10: =VLOOKUP(A10,dkw!$B$7:$H$1001,6,FALSE) -> 4.0289 | AO10: =VLOOKUP(A10,dkw!$B$7:$H$1001,7,FALSE) -> 0.9014 | AP10: =VLOOKUP(A10,acm!B$7:E$1001,2,FALSE) -> 11.84852 | AQ10: =VLOOKUP(A10,acm!B$7:E$1001,3,FALSE) -> 4.26572 | AR10: =VLOOKUP(A10,acm!B$7:E$1001,4,FALSE) -> 7.58279 | AS10: =VLOOKUP(A10,cr!B$7:F$1001,5,FALSE) -> #N/A | AT10: =VLOOKUP(A10,cr!B$7:F$1001,4,FALSE) -> #N/A | AU10: =VLOOKUP(A10,cr!B$7:F$1001,2,FALSE) -> #N/A
A11: 31079 | B11: 10 | C11: =VLOOKUP(A11,treasuries_zc!$B$7:$J$1000,_xlfn.XMATCH(C$1,treasuries_zc!$B$1:$J$1,1),FALSE) -> 12.151557 | D11: =VLOOKUP(A11,treasuries_zc!$B$7:$J$1000,_xlfn.XMATCH(D$1,treasuries_zc!$B$1:$J$1,1),FALSE) -> 12.343607 | E11: =VLOOKUP(A11,treasuries_zc!$B$7:$J$1000,_xlfn.XMATCH(E$1,treasuries_zc!$B$1:$J$1,1),FALSE) -> 12.247541 | F11: =VLOOKUP(A11,treasuries_zc!$B$7:$J$1000,_xlfn.XMATCH(F$1,treasuries_zc!$B$1:$J$1,1),FALSE) -> 11.7913 | G11: =VLOOKUP(A11,treasuries_zc!$B$7:$J$1000,_xlfn.XMATCH(G$1,treasuries_zc!$B$1:$J$1,1),FALSE) -> 12.2626 | H11: =VLOOKUP(A11,treasuries_zc!$B$7:$J$1000,_xlfn.XMATCH(H$1,treasuries_zc!$B$1:$J$1,1),FALSE) -> 12.1218 | I11: =cbo_debt_gdp!CX16 -> 39.584955 | J11: =cbo_debt_gdp!CZ16 -> 49.696753 | K11: =cbo_debt_gdp!DB16 -> #N/A | L11: =cbo_deficit_gdp!CX16 -> 5.5512322 | M11: =cbo_deficit_gdp!CZ16 -> 5.2800571 | N11: =cbo_deficit_gdp!DB16 -> #N/A | O11: =cbo_primary_deficit_gdp!CX16 -> 2.1789883 | P11: =cbo_primary_deficit_gdp!CZ16 -> 1.17731 | Q11: =cbo_primary_deficit_gdp!DB16 -> #N/A | R11: =cbo_revenues_gdp!CX16 -> 19.066148 | S11: =cbo_revenues_gdp!CZ16 -> 19.407777 | T11: =cbo_revenues_gdp!DB16 -> #N/A | U11: =cbo_outlays_gdp!CX16 -> 24.61738 | V11: =cbo_outlays_gdp!CZ16 -> 24.687834 | W11: =cbo_outlays_gdp!DB16 -> #N/A | X11: =cbo_interest_gdp!CX16 -> 3.3722438 | Y11: =cbo_interest_gdp!CZ16 -> 4.1027471 | Z11: =cbo_interest_gdp!DB16 -> #N/A | AA11: =cbo_rgdp!CX16 -> 4.1 | AB11: =cbo_rgdp!CZ16 -> 3.4 | AC11: =cbo_rgdp!DB16 -> #N/A | AD11: =IFERROR(IFERROR(VLOOKUP(A11,frbus_infl!$B$7:$H$1000,7,FALSE),VLOOKUP(A11,frbus_infl!$C$7:$H$1000,6,FALSE)),VLOOKUP(A11,frbus_infl!$D$7:$H$1000,5,FALSE)) -> 4.9533898 | AE11: =IFERROR(IFERROR(VLOOKUP(A11,frbus_infl!$B$7:$I$1000,8,FALSE),VLOOKUP(A11,frbus_infl!$C$7:$I$1000,7,FALSE)),VLOOKUP(A11,frbus_infl!$D$7:$I$1000,6,FALSE)) -> #N/A | AF11: =IFERROR(IFERROR(VLOOKUP(A11,frbus_infl!$B$7:$I$1000,5,FALSE),VLOOKUP(A11,frbus_infl!$C$7:$I$1000,4,FALSE)),VLOOKUP(A11,frbus_infl!$D$7:$I$1000,3,FALSE)) -> 4.35 | AG11: =IFERROR(IFERROR(VLOOKUP(A11,treas_holdings!$B$7:$I$1000,7,FALSE),VLOOKUP(A11,treas_holdings!$C$7:$I$1000,6,FALSE)),VLOOKUP(A11,treas_holdings!$D$7:$I$1000,5,FALSE)) -> 3.8055647 | AH11: =IFERROR(IFERROR(VLOOKUP(A11,treas_holdings!$B$7:$I$1000,8,FALSE),VLOOKUP(A11,treas_holdings!$C$7:$I$1000,7,FALSE)),VLOOKUP(A11,treas_holdings!$D$7:$I$1000,6,FALSE)) -> 3.0965675 | AI11: =IFERROR(IFERROR(VLOOKUP(A11,divyield!$B$7:$E$1001,4,FALSE),VLOOKUP(A11,divyield!$C$7:$E$1001,3,FALSE)),VLOOKUP(A11,divyield!$D$7:$E$1001,2,FALSE)) -> 5.9128204 | AJ11: =VLOOKUP(A11,ffr!$B$6:$C$1000,2) -> 8.74 | AK11: =VLOOKUP(A11,dkw!$B$7:$H$1001,3,FALSE) -> 12.1911 | AL11: =VLOOKUP(A11,dkw!$B$7:$H$1001,4,FALSE) -> 3.7849 | AM11: =VLOOKUP(A11,dkw!$B$7:$H$1001,5,FALSE) -> 3.4662 | AN11: =VLOOKUP(A11,dkw!$B$7:$H$1001,6,FALSE) -> 4.0128 | AO11: =VLOOKUP(A11,dkw!$B$7:$H$1001,7,FALSE) -> 0.9272 | AP11: =VLOOKUP(A11,acm!B$7:E$1001,2,FALSE) -> 11.80212 | AQ11: =VLOOKUP(A11,acm!B$7:E$1001,3,FALSE) -> 4.37507 | AR11: =VLOOKUP(A11,acm!B$7:E$1001,4,FALSE) -> 7.42705 | AS11: =VLOOKUP(A11,cr!B$7:F$1001,5,FALSE) -> #N/A | AT11: =VLOOKUP(A11,cr!B$7:F$1001,4,FALSE) -> #N/A | AU11: =VLOOKUP(A11,cr!B$7:F$1001,2,FALSE) -> #N/A
A12: 31260 | B12: 11 | C12: =VLOOKUP(A12,treasuries_zc!$B$7:$J$1000,_xlfn.XMATCH(C$1,treasuries_zc!$B$1:$J$1,1),FALSE) -> 10.855752 | D12: =VLOOKUP(A12,treasuries_zc!$B$7:$J$1000,_xlfn.XMATCH(D$1,treasuries_zc!$B$1:$J$1,1),FALSE) -> 11.712831 | E12: =VLOOKUP(A12,treasuries_zc!$B$7:$J$1000,_xlfn.XMATCH(E$1,treasuries_zc!$B$1:$J$1,1),FALSE) -> 11.283467 | F12: =VLOOKUP(A12,treasuries_zc!$B$7:$J$1000,_xlfn.XMATCH(F$1,treasuries_zc!$B$1:$J$1,1),FALSE) -> 10.3673 | G12: =VLOOKUP(A12,treasuries_zc!$B$7:$J$1000,_xlfn.XMATCH(G$1,treasuries_zc!$B$1:$J$1,1),FALSE) -> 10.7977 | H12: =VLOOKUP(A12,treasuries_zc!$B$7:$J$1000,_xlfn.XMATCH(H$1,treasuries_zc!$B$1:$J$1,1),FALSE) -> 11.1216 | I12: =cbo_debt_gdp!CX17 -> 39.635417 | J12: =cbo_debt_gdp!CZ17 -> 40.235841 | K12: =cbo_debt_gdp!DB17 -> #N/A | L12: =cbo_deficit_gdp!CX17 -> 5.46875 | M12: =cbo_deficit_gdp!CZ17 -> 2.1440057 | N12: =cbo_deficit_gdp!DB17 -> #N/A | O12: =cbo_primary_deficit_gdp!CX17 -> 2.109375 | P12: =cbo_primary_deficit_gdp!CZ17 -> -1.0362694 | Q12: =cbo_primary_deficit_gdp!DB17 -> #N/A | R12: =cbo_revenues_gdp!CX17 -> 19.192708 | S12: =cbo_revenues_gdp!CZ17 -> 19.546185 | T12: =cbo_revenues_gdp!DB17 -> #N/A | U12: =cbo_outlays_gdp!CX17 -> 24.635417 | V12: =cbo_outlays_gdp!CZ17 -> 21.690191 | W12: =cbo_outlays_gdp!DB17 -> #N/A | X12: =cbo_interest_gdp!CX17 -> 3.359375 | Y12: =cbo_interest_gdp!CZ17 -> 3.1802751 | Z12: =cbo_interest_gdp!DB17 -> #N/A | AA12: =cbo_rgdp!CX17 -> 3.3 | AB12: =cbo_rgdp!CZ17 -> 3.5 | AC12: =cbo_rgdp!DB17 -> #N/A | AD12: =IFERROR(IFERROR(VLOOKUP(A12,frbus_infl!$B$7:$H$1000,7,FALSE),VLOOKUP(A12,frbus_infl!$C$7:$H$1000,6,FALSE)),VLOOKUP(A12,frbus_infl!$D$7:$H$1000,5,FALSE)) -> 5.295 | AE12: =IFERROR(IFERROR(VLOOKUP(A12,frbus_infl!$B$7:$I$1000,8,FALSE),VLOOKUP(A12,frbus_infl!$C$7:$I$1000,7,FALSE)),VLOOKUP(A12,frbus_infl!$D$7:$I$1000,6,FALSE)) -> #N/A | AF12: =IFERROR(IFERROR(VLOOKUP(A12,frbus_infl!$B$7:$I$1000,5,FALSE),VLOOKUP(A12,frbus_infl!$C$7:$I$1000,4,FALSE)),VLOOKUP(A12,frbus_infl!$D$7:$I$1000,3,FALSE)) -> #N/A | AG12: =IFERROR(IFERROR(VLOOKUP(A12,treas_holdings!$B$7:$I$1000,7,FALSE),VLOOKUP(A12,treas_holdings!$C$7:$I$1000,6,FALSE)),VLOOKUP(A12,treas_holdings!$D$7:$I$1000,5,FALSE)) -> 3.868469 | AH12: =IFERROR(IFERROR(VLOOKUP(A12,treas_holdings!$B$7:$I$1000,8,FALSE),VLOOKUP(A12,treas_holdings!$C$7:$I$1000,7,FALSE)),VLOOKUP(A12,treas_holdings!$D$7:$I$1000,6,FALSE)) -> 3.1760509 | AI12: =IFERROR(IFERROR(VLOOKUP(A12,divyield!$B$7:$E$1001,4,FALSE),VLOOKUP(A12,divyield!$C$7:$E$1001,3,FALSE)),VLOOKUP(A12,divyield!$D$7:$E$1001,2,FALSE)) -> 6.21857 | AJ12: =VLOOKUP(A12,ffr!$B$6:$C$1000,2) -> 7.8 | AK12: =VLOOKUP(A12,dkw!$B$7:$H$1001,3,FALSE) -> 10.9306 | AL12: =VLOOKUP(A12,dkw!$B$7:$H$1001,4,FALSE) -> 3.2562 | AM12: =VLOOKUP(A12,dkw!$B$7:$H$1001,5,FALSE) -> 3.0924 | AN12: =VLOOKUP(A12,dkw!$B$7:$H$1001,6,FALSE) -> 3.7618 | AO12: =VLOOKUP(A12,dkw!$B$7:$H$1001,7,FALSE) -> 0.8202 | AP12: =VLOOKUP(A12,acm!B$7:E$1001,2,FALSE) -> 10.35384 | AQ12: =VLOOKUP(A12,acm!B$7:E$1001,3,FALSE) -> 3.91385 | AR12: =VLOOKUP(A12,acm!B$7:E$1001,4,FALSE) -> 6.44 | AS12: =VLOOKUP(A12,cr!B$7:F$1001,5,FALSE) -> #N/A | AT12: =VLOOKUP(A12,cr!B$7:F$1001,4,FALSE) -> #N/A | AU12: =VLOOKUP(A12,cr!B$7:F$1001,2,FALSE) -> #N/A
A13: 31444 | B13: 12 | C13: =VLOOKUP(A13,treasuries_zc!$B$7:$J$1000,_xlfn.XMATCH(C$1,treasuries_zc!$B$1:$J$1,1),FALSE) -> 8.4816266 | D13: =VLOOKUP(A13,treasuries_zc!$B$7:$J$1000,_xlfn.XMATCH(D$1,treasuries_zc!$B$1:$J$1,1),FALSE) -> 8.8632668 | E13: =VLOOKUP(A13,treasuries_zc!$B$7:$J$1000,_xlfn.XMATCH(E$1,treasuries_zc!$B$1:$J$1,1),FALSE) -> 8.6722792 | F13: =VLOOKUP(A13,treasuries_zc!$B$7:$J$1000,_xlfn.XMATCH(F$1,treasuries_zc!$B$1:$J$1,1),FALSE) -> 8.2209 | G13: =VLOOKUP(A13,treasuries_zc!$B$7:$J$1000,_xlfn.XMATCH(G$1,treasuries_zc!$B$1:$J$1,1),FALSE) -> 8.3002 | H13: =VLOOKUP(A13,treasuries_zc!$B$7:$J$1000,_xlfn.XMATCH(H$1,treasuries_zc!$B$1:$J$1,1),FALSE) -> 8.6938 | I13: =cbo_debt_gdp!CX18 -> 41.030534 | J13: =cbo_debt_gdp!CZ18 -> 40.168679 | K13: =cbo_debt_gdp!DB18 -> #N/A | L13: =cbo_deficit_gdp!CX18 -> 4.9618321 | M13: =cbo_deficit_gdp!CZ18 -> 1.7198611 | N13: =cbo_deficit_gdp!DB18 -> #N/A | O13: =cbo_primary_deficit_gdp!CX18 -> 1.6555344 | P13: =cbo_primary_deficit_gdp!CZ18 -> -0.93104019 | Q13: =cbo_primary_deficit_gdp!DB18 -> #N/A | R13: =cbo_revenues_gdp!CX18 -> 18.55916 | S13: =cbo_revenues_gdp!CZ18 -> 18.918472 | T13: =cbo_revenues_gdp!DB18 -> #N/A | U13: =cbo_outlays_gdp!CX18 -> 23.520992 | V13: =cbo_outlays_gdp!CZ18 -> 20.638333 | W13: =cbo_outlays_gdp!DB18 -> #N/A | X13: =cbo_interest_gdp!CX18 -> 3.3062977 | Y13: =cbo_interest_gdp!CZ18 -> 2.6509013 | Z13: =cbo_interest_gdp!DB18 -> #N/A | AA13: =cbo_rgdp!CX18 -> 3 | AB13: =cbo_rgdp!CZ18 -> 3.4 | AC13: =cbo_rgdp!DB18 -> #N/A | AD13: =IFERROR(IFERROR(VLOOKUP(A13,frbus_infl!$B$7:$H$1000,7,FALSE),VLOOKUP(A13,frbus_infl!$C$7:$H$1000,6,FALSE)),VLOOKUP(A13,frbus_infl!$D$7:$H$1000,5,FALSE)) -> 4.8771181 | AE13: =IFERROR(IFERROR(VLOOKUP(A13,frbus_infl!$B$7:$I$1000,8,FALSE),VLOOKUP(A13,frbus_infl!$C$7:$I$1000,7,FALSE)),VLOOKUP(A13,frbus_infl!$D$7:$I$1000,6,FALSE)) -> #N/A | AF13: =IFERROR(IFERROR(VLOOKUP(A13,frbus_infl!$B$7:$I$1000,5,FALSE),VLOOKUP(A13,frbus_infl!$C$7:$I$1000,4,FALSE)),VLOOKUP(A13,frbus_infl!$D$7:$I$1000,3,FALSE)) -> 4 | AG13: =IFERROR(IFERROR(VLOOKUP(A13,treas_holdings!$B$7:$I$1000,7,FALSE),VLOOKUP(A13,treas_holdings!$C$7:$I$1000,6,FALSE)),VLOOKUP(A13,treas_holdings!$D$7:$I$1000,5,FALSE)) -> 3.9180106 | AH13: =IFERROR(IFERROR(VLOOKUP(A13,treas_holdings!$B$7:$I$1000,8,FALSE),VLOOKUP(A13,treas_holdings!$C$7:$I$1000,7,FALSE)),VLOOKUP(A13,treas_holdings!$D$7:$I$1000,6,FALSE)) -> 3.1428381 | AI13: =IFERROR(IFERROR(VLOOKUP(A13,divyield!$B$7:$E$1001,4,FALSE),VLOOKUP(A13,divyield!$C$7:$E$1001,3,FALSE)),VLOOKUP(A13,divyield!$D$7:$E$1001,2,FALSE)) -> 4.6626305 | AJ13: =VLOOKUP(A13,ffr!$B$6:$C$1000,2) -> 7.95 | AK13: =VLOOKUP(A13,dkw!$B$7:$H$1001,3,FALSE) -> 8.4921 | AL13: =VLOOKUP(A13,dkw!$B$7:$H$1001,4,FALSE) -> 2.5938 | AM13: =VLOOKUP(A13,dkw!$B$7:$H$1001,5,FALSE) -> 2.0129 | AN13: =VLOOKUP(A13,dkw!$B$7:$H$1001,6,FALSE) -> 3.4265 | AO13: =VLOOKUP(A13,dkw!$B$7:$H$1001,7,FALSE) -> 0.4589 | AP13: =VLOOKUP(A13,acm!B$7:E$1001,2,FALSE) -> 8.21614 | AQ13: =VLOOKUP(A13,acm!B$7:E$1001,3,FALSE) -> 2.30003 | AR13: =VLOOKUP(A13,acm!B$7:E$1001,4,FALSE) -> 5.9161 | AS13: =VLOOKUP(A13,cr!B$7:F$1001,5,FALSE) -> #N/A | AT13: =VLOOKUP(A13,cr!B$7:F$1001,4,FALSE) -> #N/A | AU13: =VLOOKUP(A13,cr!B$7:F$1001,2,FALSE) -> #N/A
... A96: 45658 | B96: 95 | C96: =VLOOKUP(A96,treasuries_zc!$B$7:$J$1000,_xlfn.XMATCH(C$1,treasuries_zc!$B$1:$J$1,1),FALSE) -> 4.8528212 | D96: =VLOOKUP(A96,treasuries_zc!$B$7:$J$1000,_xlfn.XMATCH(D$1,treasuries_zc!$B$1:$J$1,1),FALSE) -> 5.1319072 | E96: =VLOOKUP(A96,treasuries_zc!$B$7:$J$1000,_xlfn.XMATCH(E$1,treasuries_zc!$B$1:$J$1,1),FALSE) -> 4.9922715 | F96: =VLOOKUP(A96,treasuries_zc!$B$7:$J$1000,_xlfn.XMATCH(F$1,treasuries_zc!$B$1:$J$1,1),FALSE) -> 4.5976 | G96: =VLOOKUP(A96,treasuries_zc!$B$7:$J$1000,_xlfn.XMATCH(G$1,treasuries_zc!$B$1:$J$1,1),FALSE) -> 4.6405 | H96: =VLOOKUP(A96,treasuries_zc!$B$7:$J$1000,_xlfn.XMATCH(H$1,treasuries_zc!$B$1:$J$1,1),FALSE) -> 5.0367 | I96: =cbo_debt_gdp!CX101 -> 99.890496 | J96: =cbo_debt_gdp!CZ101 -> 109.2158 | K96: =cbo_debt_gdp!DB101 -> 118.48143 | L96: =cbo_deficit_gdp!CX101 -> 6.1886116 | M96: =cbo_deficit_gdp!CZ101 -> 5.8800901 | N96: =cbo_deficit_gdp!DB101 -> 5.7606519 | O96: =cbo_primary_deficit_gdp!CX101 -> 3.0295992 | P96: =cbo_primary_deficit_gdp!CZ101 -> 2.231137 | Q96: =cbo_primary_deficit_gdp!DB101 -> 1.7024763 | R96: =cbo_revenues_gdp!CX101 -> 17.132333 | S96: =cbo_revenues_gdp!CZ101 -> 17.994724 | T96: =cbo_revenues_gdp!DB101 -> 18.27886 | U96: =cbo_outlays_gdp!CX101 -> 23.320945 | V96: =cbo_outlays_gdp!CZ101 -> 23.874815 | W96: =cbo_outlays_gdp!DB101 -> 24.041788 | X96: =cbo_interest_gdp!CX101 -> 3.1590125 | Y96: =cbo_interest_gdp!CZ101 -> 3.6489531 | Z96: =cbo_interest_gdp!DB101 -> 4.0581755 | AA96: =cbo_rgdp!CX101 -> 2.234 | AB96: =cbo_rgdp!CZ101 -> 1.817 | AC96: =cbo_rgdp!DB101 -> 1.768 | AD96: =IFERROR(IFERROR(VLOOKUP(A96,frbus_infl!$B$7:$H$1000,7,FALSE),VLOOKUP(A96,frbus_infl!$C$7:$H$1000,6,FALSE)),VLOOKUP(A96,frbus_infl!$D$7:$H$1000,5,FALSE)) -> 2.11 | AE96: =IFERROR(IFERROR(VLOOKUP(A96,frbus_infl!$B$7:$I$1000,8,FALSE),VLOOKUP(A96,frbus_infl!$C$7:$I$1000,7,FALSE)),VLOOKUP(A96,frbus_infl!$D$7:$I$1000,6,FALSE)) -> 2.2000977 | AF96: =IFERROR(IFERROR(VLOOKUP(A96,frbus_infl!$B$7:$I$1000,5,FALSE),VLOOKUP(A96,frbus_infl!$C$7:$I$1000,4,FALSE)),VLOOKUP(A96,frbus_infl!$D$7:$I$1000,3,FALSE)) -> 2.3 | AG96: =IFERROR(IFERROR(VLOOKUP(A96,treas_holdings!$B$7:$I$1000,7,FALSE),VLOOKUP(A96,treas_holdings!$C$7:$I$1000,6,FALSE)),VLOOKUP(A96,treas_holdings!$D$7:$I$1000,5,FALSE)) -> 12.756076 | AH96: =IFERROR(IFERROR(VLOOKUP(A96,treas_holdings!$B$7:$I$1000,8,FALSE),VLOOKUP(A96,treas_holdings!$C$7:$I$1000,7,FALSE)),VLOOKUP(A96,treas_holdings!$D$7:$I$1000,6,FALSE)) -> 13.065784 | AI96: =IFERROR(IFERROR(VLOOKUP(A96,divyield!$B$7:$E$1001,4,FALSE),VLOOKUP(A96,divyield!$C$7:$E$1001,3,FALSE)),VLOOKUP(A96,divyield!$D$7:$E$1001,2,FALSE)) -> 2.4668563 | AJ96: =VLOOKUP(A96,ffr!$B$6:$C$1000,2) -> 4.33 | AK96: =VLOOKUP(A96,dkw!$B$7:$H$1001,3,FALSE) -> 4.8785 | AL96: =VLOOKUP(A96,dkw!$B$7:$H$1001,4,FALSE) -> 1.307 | AM96: =VLOOKUP(A96,dkw!$B$7:$H$1001,5,FALSE) -> 0.7216 | AN96: =VLOOKUP(A96,dkw!$B$7:$H$1001,6,FALSE) -> 2.7974 | AO96: =VLOOKUP(A96,dkw!$B$7:$H$1001,7,FALSE) -> 0.0525 | AP96: =VLOOKUP(A96,acm!B$7:E$1001,2,FALSE) -> 4.5945 | AQ96: =VLOOKUP(A96,acm!B$7:E$1001,3,FALSE) -> 0.50232 | AR96: =VLOOKUP(A96,acm!B$7:E$1001,4,FALSE) -> 4.09218 | AS96: =VLOOKUP(A96,cr!B$7:F$1001,5,FALSE) -> 3.1115327 | AT96: =VLOOKUP(A96,cr!B$7:F$1001,4,FALSE) -> 1.2112 | AU96: =VLOOKUP(A96,cr!B$7:F$1001,2,FALSE) -> 3.3864

Sheet treasuries_zc
B1: date | C1: i15y_zcm | D1: i10y_zcm | E1: i5y_zcm | F1: i5y3m_zcm | G1: i10y3m_zcm | H1: i5y5y_zcm | I1: i10y5y_zcm | J1: i5y10y_zcm | N1: Source
A2: 197501 !M | B2: .excel_first | C2: FYCCZFE@USECON | D2: FYCCZAE@USECON | E2: FYCCZ5E@USECON | F2: FZ3M5YE@USECON | G2: FZ3M10E@USECON | N2: https://www.federalreserve.gov/data/nominal-yield-curve.htm
A3: .DESC | C3: US Treasury Yield: Continuously Compounded Zero-Coupon: 15-Yrs(EOP, %) | D3: US Treasury Yield: Continuously Compounded Zero-Coupon: 10-Yrs(EOP, %) | E3: US Treasury Yield: Continuously Compounded Zero-Coupon: 5-Yrs(EOP, %) | F3: US Treas Yld: Cont Compounded Fwd Rate Beg 5 Yrs Hence: 3-Month(EOP, % p.a.) | G3: US Treas Yld: Cont Compounded Fwd Rate Beg 10 Yrs Hence: 3-Mo (EOP, % p.a.) | N3: Mnemonic: SVENYXX
A4: .DTLM | C4: Dec-02-2025 14:13 | D4: Dec-02-2025 14:13 | E4: Dec-02-2025 14:13 | F4: Dec-02-2025 14:22 | G4: Dec-02-2025 14:22
A5: .SOURCE | C5: FRB | D5: FRB | E5: FRB | F5: HAVER | G5: HAVER
A6: .AGG | C6: End of Period | D6: End of Period | E6: End of Period | F6: End of Period | G6: End of Period
A7: 197501 | B7: 27395 | C7: 7.3326 | D7: 7.2796 | E7: 7.1207 | F7: 7.4385 | G7: 7.4386 | H7: =100*((((1+D7/100)^10)/(1+E7/100)^5)^(1/5)-1) -> 7.4387357 | I7: =100*((((1+C7/100)^15)/(1+D7/100)^10)^(1/5)-1) -> 7.4386786 | J7: =100*((((1+C7/100)^15)/(1+E7/100)^5)^(1/10)-1) -> 7.4387071
A8: 197502 | B8: 27426 | C8: 7.3022 | D8: 7.21 | E8: 6.9345 | F8: 7.4805 | G8: 7.4865 | H8: =100*((((1+D8/100)^10)/(1+E8/100)^5)^(1/5)-1) -> 7.4862098 | I8: =100*((((1+C8/100)^15)/(1+D8/100)^10)^(1/5)-1) -> 7.4868379 | J8: =100*((((1+C8/100)^15)/(1+E8/100)^5)^(1/10)-1) -> 7.4865239
A9: 197503 | B9: 27454 | C9: 7.5035 | D9: 7.444 | E9: 7.2657 | F9: 7.6223 | G9: 7.6224 | H9: =100*((((1+D9/100)^10)/(1+E9/100)^5)^(1/5)-1) -> 7.6225964 | I9: =100*((((1+C9/100)^15)/(1+D9/100)^10)^(1/5)-1) -> 7.6225989 | J9: =100*((((1+C9/100)^15)/(1+E9/100)^5)^(1/10)-1) -> 7.6225976
A10: 197504 | B10: 27485 | C10: 8.0136 | D10: 7.9672 | E10: 7.8282 | F10: 8.1062 | G10: 8.1062 | H10: =100*((((1+D10/100)^10)/(1+E10/100)^5)^(1/5)-1) -> 8.1063792 | I10: =100*((((1+C10/100)^15)/(1+D10/100)^10)^(1/5)-1) -> 8.1064598 | J10: =100*((((1+C10/100)^15)/(1+E10/100)^5)^(1/10)-1) -> 8.1064195
A11: 197505 | B11: 27515 | C11: 7.7659 | D11: 7.686 | E11: 7.4464 | F11: 7.925 | G11: 7.9257 | H11: =100*((((1+D11/100)^10)/(1+E11/100)^5)^(1/5)-1) -> 7.9261343 | I11: =100*((((1+C11/100)^15)/(1+D11/100)^10)^(1/5)-1) -> 7.9258779 | J11: =100*((((1+C11/100)^15)/(1+E11/100)^5)^(1/10)-1) -> 7.9260061
A12: 197506 | B12: 27546 | C12: 7.6313 | D12: 7.6212 | E12: 7.5322 | F12: 7.7809 | G12: 7.6624 | H12: =100*((((1+D12/100)^10)/(1+E12/100)^5)^(1/5)-1) -> 7.7102737 | I12: =100*((((1+C12/100)^15)/(1+D12/100)^10)^(1/5)-1) -> 7.6515028 | J12: =100*((((1+C12/100)^15)/(1+E12/100)^5)^(1/10)-1) -> 7.6808842
A13: 197507 | B13: 27576 | C13: 7.6778 | D13: 7.7142 | E13: 7.7762 | F13: 7.7448 | G13: 7.6095 | H13: =100*((((1+D13/100)^10)/(1+E13/100)^5)^(1/5)-1) -> 7.6522357 | I13: =100*((((1+C13/100)^15)/(1+D13/100)^10)^(1/5)-1) -> 7.6050369 | J13: =100*((((1+C13/100)^15)/(1+E13/100)^5)^(1/10)-1) -> 7.6286337
A14: 197508 | B14: 27607 | C14: 7.8987 | D14: 7.9025 | E14: 7.895 | F14: 7.9519 | G14: 7.8925 | H14: =100*((((1+D14/100)^10)/(1+E14/100)^5)^(1/5)-1) -> 7.9100005 | I14: =100*((((1+C14/100)^15)/(1+D14/100)^10)^(1/5)-1) -> 7.8911004 | J14: =100*((((1+C14/100)^15)/(1+E14/100)^5)^(1/10)-1) -> 7.90055
A15: 197509 | B15: 27638 | C15: 8.1318 | D15: 8.1502 | E15: 8.1755 | F15: 8.1904 | G15: 8.0972 | H15: =100*((((1+D15/100)^10)/(1+E15/100)^5)^(1/5)-1) -> 8.1249059 | I15: =100*((((1+C15/100)^15)/(1+D15/100)^10)^(1/5)-1) -> 8.0950094 | J15: =100*((((1+C15/100)^15)/(1+E15/100)^5)^(1/10)-1) -> 8.1099566
A16: 197510 | B16: 27668 | C16: 7.833 | D16: 7.7593 | E16: 7.5381 | F16: 7.98 | G16: 7.9805 | H16: =100*((((1+D16/100)^10)/(1+E16/100)^5)^(1/5)-1) -> 7.980955 | I16: =100*((((1+C16/100)^15)/(1+D16/100)^10)^(1/5)-1) -> 7.9805513 | J16: =100*((((1+C16/100)^15)/(1+E16/100)^5)^(1/10)-1) -> 7.9807531
A17: 197511 | B17: 27699 | C17: 7.9981 | D17: 7.9271 | E17: 7.7131 | F17: 8.1419 | G17: 8.1401 | H17: =100*((((1+D17/100)^10)/(1+E17/100)^5)^(1/5)-1) -> 8.1415252 | I17: =100*((((1+C17/100)^15)/(1+D17/100)^10)^(1/5)-1) -> 8.1402402 | J17: =100*((((1+C17/100)^15)/(1+E17/100)^5)^(1/10)-1) -> 8.1408827
A18: 197512 | B18: 27729 | C18: 7.742 | D18: 7.6472 | E18: 7.3657 | F18: 7.9177 | G18: 7.9315 | H18: =100*((((1+D18/100)^10)/(1+E18/100)^5)^(1/5)-1) -> 7.9294381 | I18: =100*((((1+C18/100)^15)/(1+D18/100)^10)^(1/5)-1) -> 7.9318505 | J18: =100*((((1+C18/100)^15)/(1+E18/100)^5)^(1/10)-1) -> 7.9306443
... A171: 198809 | B171: 32387 | C171: 9.0343 | D171: 8.8704 | E171: 8.5027 | F171: 8.9435 | G171: 9.4092 | H171: =100*((((1+D171/100)^10)/(1+E171/100)^5)^(1/5)-1) -> 9.2393461 | I171: =100*((((1+C171/100)^15)/(1+D171/100)^10)^(1/5)-1) -> 9.3628406 | J171: =100*((((1+C171/100)^15)/(1+E171/100)^5)^(1/10)-1) -> 9.3010759
A172: 198810 | B172: 32417 | C172: 8.841 | D172: 8.6762 | E172: 8.2532 | F172: 8.7227 | G172: 9.2921 | H172: =100*(((1+D172/100)^10/(1+E172/100)^5)^(1/5)-1) -> 9.1008529 | I172: =100*(((1+C172/100)^15/(1+D172/100)^10)^(1/5)-1) -> 9.1713501 | J172: =100*((((1+C172/100)^15)/(1+E172/100)^5)^(1/10)-1) -> 9.1360958
A173: 198811 | B173: 32448 | C173: 9.0656 | D173: 8.9978 | E173: 8.7723 | F173: 9.0429 | G173: 9.2925 | H173: =100*(((1+D173/100)^10/(1+E173/100)^5)^(1/5)-1) -> 9.2237675 | I173: =100*(((1+C173/100)^15/(1+D173/100)^10)^(1/5)-1) -> 9.2013265 | J173: =100*((((1+C173/100)^15)/(1+E173/100)^5)^(1/10)-1) -> 9.2125464
A174: 198812 | B174: 32478 | C174: 8.9112 | D174: 9.0064 | E174: 9.0037 | F174: 9.0908 | G174: 8.8659 | H174: =100*(((1+D174/100)^10/(1+E174/100)^5)^(1/5)-1) -> 9.0091001 | I174: =100*(((1+C174/100)^15/(1+D174/100)^10)^(1/5)-1) -> 8.7210494 | J174: =100*((((1+C174/100)^15)/(1+E174/100)^5)^(1/10)-1) -> 8.8649794
A175: 198901 | B175: 32509 | C175: 8.7202 | D175: 8.827 | E175: 8.8862 | F175: 8.8538 | G175: 8.6341 | H175: =100*(((1+D175/100)^10/(1+E175/100)^5)^(1/5)-1) -> 8.7678322 | I175: =100*(((1+C175/100)^15/(1+D175/100)^10)^(1/5)-1) -> 8.5069143 | J175: =100*((((1+C175/100)^15)/(1+E175/100)^5)^(1/10)-1) -> 8.6372949
A176: 198902 | B176: 32540 | C176: 9.0182 | D176: 9.1471 | E176: 9.2516 | F176: 9.1566 | G176: 8.8884 | H176: =100*(((1+D176/100)^10/(1+E176/100)^5)^(1/5)-1) -> 9.0427 | I176: =100*(((1+C176/100)^15/(1+D176/100)^10)^(1/5)-1) -> 8.7608565 | J176: =100*((((1+C176/100)^15)/(1+E176/100)^5)^(1/10)-1) -> 8.9016871
A177: 198903 | B177: 32568 | C177: 8.9269 | D177: 9.0739 | E177: 9.3174 | F177: 9.0057 | G177: 8.6881 | H177: =100*(((1+D177/100)^10/(1+E177/100)^5)^(1/5)-1) -> 8.8309424 | I177: =100*(((1+C177/100)^15/(1+D177/100)^10)^(1/5)-1) -> 8.6334941 | J177: =100*((((1+C177/100)^15)/(1+E177/100)^5)^(1/10)-1) -> 8.7321734
A178: 198904 | B178: 32599 | C178: 8.8299 | D178: 8.9012 | E178: 8.919 | F178: 8.8929 | G178: 8.8071 | H178: =100*(((1+D178/100)^10/(1+E178/100)^5)^(1/5)-1) -> 8.8834029 | I178: =100*(((1+C178/100)^15/(1+D178/100)^10)^(1/5)-1) -> 8.68744 | J178: =100*((((1+C178/100)^15)/(1+E178/100)^5)^(1/10)-1) -> 8.7853773
A179: 198905 | B179: 32629 | C179: 8.4762 | D179: 8.5151 | E179: 8.5565 | F179: 8.499 | G179: 8.4346 | H179: =100*(((1+D179/100)^10/(1+E179/100)^5)^(1/5)-1) -> 8.4737158 | I179: =100*(((1+C179/100)^15/(1+D179/100)^10)^(1/5)-1) -> 8.3984418 | J179: =100*((((1+C179/100)^15)/(1+E179/100)^5)^(1/10)-1) -> 8.4360723
A180: 198906 | B180: 32660 | C180: 8.0516 | D180: 8.0823 | E180: 7.9783 | F180: 8.1601 | G180: 8.1241 | H180: =100*(((1+D180/100)^10/(1+E180/100)^5)^(1/5)-1) -> 8.1864002 | I180: =100*(((1+C180/100)^15/(1+D180/100)^10)^(1/5)-1) -> 7.9902262 | J180: =100*((((1+C180/100)^15)/(1+E180/100)^5)^(1/10)-1) -> 8.0882687
A181: 198907 | B181: 32690 | C181: 7.9014 | D181: 7.7831 | E181: 7.5167 | F181: 7.8407 | G181: 8.1675 | H181: =100*(((1+D181/100)^10/(1+E181/100)^5)^(1/5)-1) -> 8.0501601 | I181: =100*(((1+C181/100)^15/(1+D181/100)^10)^(1/5)-1) -> 8.1383897 | J181: =100*((((1+C181/100)^15)/(1+E181/100)^5)^(1/10)-1) -> 8.0942659
A182: 198908 | B182: 32721 | C182: 8.1611 | D182: 8.1871 | E182: 8.1794 | F182: 8.1978 | G182: 8.1615 | H182: =100*(((1+D182/100)^10/(1+E182/100)^5)^(1/5)-1) -> 8.1948005 | I182: =100*(((1+C182/100)^15/(1+D182/100)^10)^(1/5)-1) -> 8.1091187 | J182: =100*((((1+C182/100)^15)/(1+E182/100)^5)^(1/10)-1) -> 8.1519512
A183: 198909 | B183: 32752 | C183: 8.2042 | D183: 8.2513 | E183: 8.2656 | F183: 8.2792 | G183: 8.1712 | H183: =100*(((1+D183/100)^10/(1+E183/100)^5)^(1/5)-1) -> 8.2370019 | I183: =100*(((1+C183/100)^15/(1+D183/100)^10)^(1/5)-1) -> 8.1100615 | J183: =100*((((1+C183/100)^15)/(1+E183/100)^5)^(1/10)-1) -> 8.1735131
... A617: 202511 | B617: 45962 | C617: 4.5139 | D617: 4.0983 | E617: 3.5787 | F617: 4.0508 | G617: 5.1194 | H617: =100*(((1+D617/100)^10/(1+E617/100)^5)^(1/5)-1) -> 4.6205066 | I617: =100*(((1+C617/100)^15/(1+D617/100)^10)^(1/5)-1) -> 5.3500843 | J617: =100*((((1+C617/100)^15)/(1+E617/100)^5)^(1/10)-1) -> 4.9846617

Sheet cbo_debt
C1: 1976A | D1: 1976B | E1: 1977A | F1: 1979A | G1: 1980A | H1: 1981A | I1: 1982A | J1: 1983A | K1: 1984A | L1: 1985A | M1: 1985B | N1: 1986A | O1: 1986B | P1: 1987A | Q1: 1987B | R1: 1988A | S1: 1988B | T1: 1989A | U1: 1989B | V1: 1990A | W1: 1990B | X1: 1991A | Y1: 1991B | Z1: 1992A | AA1: 1992B | AB1: 1993A | AC1: 1993B | AD1: 1994A | AE1: 1994B | AF1: 1995A | AG1: 1995B | AH1: 1995C | AI1: 1996A | AJ1: 1997A | AK1: 1997B | AL1: 1998A | AM1: 1998B | AN1: 1999A | AO1: 1999B | AP1: 2000A | AQ1: 2000B | AR1: 2001A | AS1: 2001B | AT1: 2002A | AU1: 2002B | AV1: 2003A | AW1: 2003B | AX1: 2004A | AY1: 2004B | AZ1: 2005A | BA1: 2005B | BB1: 2006A | BC1: 2006B | BD1: 2007A | BE1: 2007B | BF1: 2008A | BG1: 2008B | BH1: 2009A | BI1: 2009B | BJ1: 2009C | BK1: 2010A | BL1: 2010B | BM1: 2011A | BN1: 2011B | BO1: 2012A | BP1: 2012B | BQ1: 2012C | BR1: 2013A | BS1: 2013B | BT1: 2014A | BU1: 2014B | BV1: 2014C | BW1: 2015A | BX1: 2015B | BY1: 2015C | BZ1: 2016A | CA1: 2016B | CB1: 2016C | CC1: 2017A | CD1: 2017B | CE1: 2018A | CF1: 2019A | CG1: 2019B | CH1: 2019C | CI1: 2020A | CJ1: 2020B | CK1: 2020C | CL1: 2021A | CM1: 2021B | CN1: 2022A | CO1: 2023A | CP1: 2023B | CQ1: 2024A | CR1: 2024B | CS1: 2025A
A2: 1975 2035 !A | B2: .excel_first | AU2: CADAL02B@GOVFIN | AW2: CADAL03B@GOVFIN | AX2: CADAL04A@GOVFIN | AY2: CADAL04B@GOVFIN | AZ2: CADAL05A@GOVFIN | BA2: CADAL05B@GOVFIN | BB2: CADAL06A@GOVFIN | BC2: CADAL06B@GOVFIN | BD2: CADAL07A@GOVFIN | BE2: CADAL07B@GOVFIN | BF2: CADAL08A@GOVFIN | BG2: CADAL08B@GOVFIN | BH2: CADAL09A@GOVFIN | BJ2: CADAL09B@GOVFIN | BK2: CADAL10A@GOVFIN | BL2: CADAL10B@GOVFIN | BM2: CADAL11A@GOVFIN | BN2: CADAL11B@GOVFIN | BO2: CADAL12A@GOVFIN | BP2: CADAL12B@GOVFIN | BQ2: CADAL12C@GOVFIN | BR2: CADAL13A@GOVFIN | BS2: CADAL13B@GOVFIN | BT2: CADAL14A@GOVFIN | BU2: CADAL14B@GOVFIN | BV2: CADAL14C@GOVFIN | BW2: CADAL15A@GOVFIN | BX2: CADAL15B@GOVFIN | BY2: CADAL15C@GOVFIN | BZ2: CADAL16A@GOVFIN | CA2: CADAL16B@GOVFIN | CB2: CADAL16C@GOVFIN | CC2: CADAL17A@GOVFIN | CD2: CADAL17B@GOVFIN | CE2: CADAL18A@GOVFIN | CF2: CADAL19A@GOVFIN | CG2: CADAL19B@GOVFIN | CH2: CADAL19C@GOVFIN | CI2: CADAL20A@GOVFIN | CJ2: CADAL20B@GOVFIN | CK2: CADAL20C@GOVFIN | CL2: CADAL21A@GOVFIN | CM2: CADAL21B@GOVFIN | CN2: CADAL22A@GOVFIN | CO2: CADAL23A@GOVFIN | CP2: CADAL23B@GOVFIN | CQ2: CADAL24A@GOVFIN | CR2: CADAL24B@GOVFIN | CS2: PDPABUD@GOVFIN
A3: .DESC | C3: Imputed | D3: Imputed | E3: Imputed | F3: Imputed | G3: Imputed | H3: Imputed | I3: Imputed | AU3: CBO Baseline Budget, August 2002: Debt Held by the Public (FY, Bil.$) | AW3: CBO Baseline Budget, August 2003: Debt Held by the Public (FY, Bil.$) | AX3: CBO Baseline Budget, January 2004: Debt Held by the Public (FY, Bil.$) | AY3: CBO Baseline Budget, September 2004: Debt Held by the Public (FY, Bil.$) | AZ3: CBO Baseline Budget, January 2005: Debt Held by the Public (FY, Bil.$) | BA3: CBO Baseline Budget, August 2005: Debt Held by the Public (FY, Bil.$) | BB3: CBO Baseline Budget, January 2006: Debt Held by the Public (FY, Bil.$) | BC3: CBO Baseline Budget, August 2006: Debt Held by the Public (FY, Bil.$) | BD3: CBO Baseline Budget, January 2007: Debt Held by the Public (FY, Bil.$) | BE3: CBO Baseline Budget, August 2007: Debt Held by the Public (FY, Bil.$) | BF3: CBO Baseline Budget, January 2008: Debt Held by the Public (FY, Bil.$) | BG3: CBO Baseline Budget, August 2008: Debt Held by the Public (FY, Bil.$) | BH3: CBO Baseline Budget, January 2009: Debt Held by the Public (FY, Bil.$) | BJ3: CBO Baseline Budget, August 2009: Debt Held by the Public (FY, Bil.$) | BK3: CBO Baseline Budget, January 2010: Debt Held by the Public (FY, Bil.$) | BL3: CBO Baseline Budget, August 2010: Debt Held by the Public (FY, Bil.$) | BM3: CBO Baseline Budget, January 2011: Debt Held by the Public (FY, Bil.$) | BN3: CBO Baseline Budget, August 2011: Debt Held by the Public (FY, Bil.$) | BO3: CBO Baseline Budget, January 2012: Debt Held by the Public (FY, Bil.$) | BP3: CBO Baseline Budget, March 2012: Debt Held by the Public (FY, Bil.$) | BQ3: CBO Baseline Budget, August 2012: Debt Held by the Public (FY, Bil.$) | BR3: CBO Baseline Budget, February 2013: Debt Held by the Public (FY, Bil.$) | BS3: CBO Baseline Budget, May 2013: Debt Held by the Public (FY, Bil.$) | BT3: CBO Baseline Budget, February 2014: Debt Held by the Public (FY, Bil.$) | BU3: CBO Baseline Budget, April 2014: Debt Held by the Public (FY, Bil.$) | BV3: CBO Baseline Budget, August 2014: Debt Held by the Public (FY, Bil.$) | BW3: CBO Baseline Budget, January 2015: Debt Held by the Public (FY, Bil.$) | BX3: CBO Baseline Budget, March 2015: Debt Held by the Public (FY, Bil.$) | BY3: CBO Baseline Budget, August 2015: Debt Held by the Public (FY, Bil.$) | BZ3: CBO Baseline Budget, January 2016: Debt Held by the Public (FY, Bil.$) | CA3: CBO Baseline Budget, March 2016: Debt Held by the Public (FY, Bil.$) | CB3: CBO Baseline Budget, August 2016: Debt Held by the Public (FY, Bil.$) | CC3: CBO Baseline Budget, January 2017: Debt Held by the Public (FY, Bil. US$) | CD3: CBO Baseline Budget, June 2017: Debt Held by the Public (FY, Bil. US$) | CE3: CBO Baseline Budget, April 2018: Debt Held by the Public (FY, Bil. US$) | CF3: CBO Baseline Budget, January 2019: Debt Held by the Public (FY, Bil. US$) | CG3: CBO Baseline Budget, May 2019: Debt Held by the Public (FY, Bil. US$) | CH3: CBO Baseline Budget, August 2019: Debt Held by the Public (FY, Bil. US$) | CI3: CBO Baseline Budget, Jan 2020: Debt Held by the Public (FY, Bil. US$) | CJ3: CBO Baseline Budget, March 2020: Debt Held by the Public (FY, Bil. US$) | CK3: CBO Baseline Budget, Sept 2020: Debt Held by the Public (FY, Bil. US$) | CL3: CBO Baseline Budget, Feb 2021: Debt Held by the Public (FY, Bil. US$) | CM3: CBO Baseline Budget, Jul 2021: Debt Held by the Public (FY, Bil. US$) | CN3: CBO Baseline Budget, May 2022: Debt Held by the Public (FY, Bil. US$) | CO3: CBO Baseline Budget, Feb 2023: Debt Held by the Public (FY, Bil. US$) | CP3: CBO Baseline Budget, May 2023: Debt Held by the Public (FY, Bil. US$) | CQ3: CBO Baseline Budget, Feb 2024: Debt Held by the Public (FY, Bil. US$) | CR3: CBO Baseline Budget, Jun 2024: Debt Held by the Public (FY, Bil. US$) | CS3: CBO Baseline Budget Projections, Debt Held by the Public (Fiscal Yr, Bil.$)
A4: .DTLM | C4: 27760 | D4: 28095 | E4: 28460 | F4: 28856 | G4: 29252 | H4: 29768 | I4: 29983 | J4: 30348 | K4: 30713 | L4: 31079 | M4: 31260 | N4: 31444 | O4: 31625 | P4: 31778 | Q4: 31990 | R4: 32174 | S4: 32356 | T4: 32509 | U4: 32721 | V4: 32874 | W4: 33055 | X4: 33239 | Y4: 33451 | Z4: 33604 | AA4: 33817 | AB4: 33970 | AC4: 34213 | AD4: 34335 | AE4: 34547 | AF4: 34700 | AG4: 34912 | AH4: 35034 | AI4: 35186 | AJ4: 35431 | AK4: 35674 | AL4: 35796 | AM4: 36008 | AN4: 36161 | AO4: 36342 | AP4: 36526 | AQ4: 36708 | AR4: 36892 | AS4: 37104 | AT4: 37257 | AU4: Mar-05-2015 13:55 | AV4: 37622 | AW4: Mar-05-2015 13:55 | AX4: Mar-05-2015 13:55 | AY4: Mar-05-2015 13:55 | AZ4: Mar-05-2015 13:55 | BA4: Mar-05-2015 13:55 | BB4: Mar-05-2015 13:55 | BC4: Mar-05-2015 13:55 | BD4: Mar-05-2015 13:55 | BE4: Mar-05-2015 13:55 | BF4: Mar-05-2015 13:55 | BG4: Mar-05-2015 13:55 | BH4: Mar-05-2015 13:55 | BI4: 39873 | BJ4: Mar-05-2015 13:55 | BK4: Mar-05-2015 13:55 | BL4: Mar-05-2015 13:55 | BM4: Mar-05-2015 13:55 | BN4: Mar-05-2015 13:55 | BO4: Mar-05-2015 13:55 | BP4: Mar-05-2015 13:55 | BQ4: Mar-05-2015 13:55 | BR4: Mar-05-2015 13:55 | BS4: Mar-05-2015 13:55 | BT4: Mar-05-2015 13:55 | BU4: Mar-05-2015 13:55 | BV4: Mar-05-2015 13:55 | BW4: Mar-10-2015 11:25 | BX4: Aug-13-2015 16:23 | BY4: Jan-19-2016 10:25 | BZ4: Mar-29-2016 14:03 | CA4: Sep-08-2016 12:44 | CB4: Jan-24-2017 10:46 | CC4: Jan-05-2018 16:11 | CD4: Apr-19-2018 10:36 | CE4: Nov-01-2018 09:23 | CF4: Jan-30-2019 09:30 | CG4: May-02-2019 13:12 | CH4: Aug-21-2019 10:39 | CI4: Sep-02-2020 16:58 | CJ4: Sep-02-2020 17:01 | CK4: Sep-02-2020 17:01 | CL4: Feb-22-2023 16:31 | CM4: Feb-22-2023 16:31 | CN4: Feb-22-2023 16:31 | CO4: Aug-03-2023 09:59 | CP4: Feb-08-2024 13:22 | CQ4: Jun-20-2024 11:29 | CR4: Jan-27-2025 08:42 | CS4: Jan-17-2025 12:31
A5: .SOURCE | C5: 27760 | D5: 28095 | E5: 28460 | F5: 28856 | G5: 29252 | H5: 29768 | I5: 29983 | J5: 30348 | K5: 30713 | L5: 31079 | M5: 31260 | N5: 31444 | O5: 31625 | P5: 31778 | Q5: 31990 | R5: 32174 | S5: 32356 | T5: 32509 | U5: 32721 | V5: 32874 | W5: 33055 | X5: 33239 | Y5: 33451 | Z5: 33604 | AA5: 33817 | AB5: 33970 | AC5: 34213 | AD5: 34335 | AE5: 34547 | AF5: 34700 | AG5: 34912 | AH5: 35034 | AI5: 35186 | AJ5: 35431 | AK5: 35674 | AL5: 35796 | AM5: 36008 | AN5: 36161 | AO5: 36342 | AP5: 36526 | AQ5: 36708 | AR5: 365610 | AS5: 37104 | AT5: 37257 | AU5: CBO | AV5: 37622 | AW5: CBO | AX5: CBO | AY5: CBO | AZ5: CBO | BA5: CBO | BB5: CBO | BC5: CBO | BD5: CBO | BE5: CBO | BF5: CBO | BG5: CBO | BH5: CBO | BI5: 39873 | BJ5: CBO | BK5: CBO | BL5: CBO | BM5: CBO | BN5: CBO | BO5: CBO | BP5: CBO | BQ5: CBO | BR5: CBO | BS5: CBO | BT5: CBO | BU5: CBO | BV5: CBO | BW5: CBO | BX5: CBO | BY5: CBO | BZ5: CBO | CA5: CBO | CB5: CBO | CC5: CBO | CD5: CBO | CE5: CBO | CF5: CBO | CG5: CBO | CH5: CBO | CI5: CBO | CJ5: CBO | CK5: CBO | CL5: CBO | CM5: CBO | CN5: CBO | CO5: CBO | CP5: CBO | CQ5: CBO | CR5: CBO | CS5: CBO
A6: 1975 | B6: 27395 | C6: #N/A | D6: #N/A | E6: #N/A | F6: #N/A | G6: #N/A | H6: #N/A | I6: #N/A | J6: #N/A | K6: #N/A | L6: #N/A | M6: #N/A | N6: #N/A | O6: #N/A | P6: #N/A | Q6: #N/A | R6: #N/A | S6: #N/A | T6: #N/A | U6: #N/A | V6: #N/A | W6: #N/A | X6: #N/A | Y6: #N/A | Z6: #N/A | AA6: #N/A | AB6: #N/A | AC6: #N/A | AD6: #N/A | AE6: #N/A | AF6: #N/A | AG6: #N/A | AH6: #N/A | AI6: #N/A | AJ6: #N/A | AK6: #N/A | AL6: #N/A | AM6: #N/A | AN6: #N/A | AO6: #N/A | AP6: #N/A | AQ6: #N/A | AR6: #N/A | AS6: #N/A | AT6: #N/A | AU6: #N/A | AV6: #N/A | AW6: #N/A | AX6: #N/A | AY6: #N/A | AZ6: #N/A | BA6: #N/A | BB6: #N/A | BC6: #N/A | BD6: #N/A | BE6: #N/A | BF6: #N/A | BG6: #N/A | BH6: #N/A | BI6: #N/A | BJ6: #N/A | BK6: #N/A | BL6: #N/A | BM6: #N/A | BN6: #N/A | BO6: #N/A | BP6: #N/A | BQ6: #N/A | BR6: #N/A | BS6: #N/A | BT6: #N/A | BU6: #N/A | BV6: #N/A | BW6: #N/A | BX6: #N/A | BY6: #N/A | BZ6: #N/A | CA6: #N/A | CB6: #N/A | CC6: #N/A | CD6: #N/A | CE6: #N/A | CF6: #N/A | CG6: #N/A | CH6: #N/A | CI6: #N/A | CJ6: #N/A | CK6: #N/A | CL6: #N/A | CM6: #N/A | CN6: #N/A | CO6: #N/A | CP6: #N/A | CQ6: #N/A | CR6: #N/A | CS6: 395
A7: 1976 | B7: 27760 | C7: =$CS$6-SUM(cbo_deficit!C$7:'cbo_deficit'!C7) -> 469 | D7: #N/A | E7: #N/A | F7: #N/A | G7: #N/A | H7: #N/A | I7: #N/A | J7: #N/A | K7: #N/A | L7: #N/A | M7: #N/A | N7: #N/A | O7: #N/A | P7: #N/A | Q7: #N/A | R7: #N/A | S7: #N/A | T7: #N/A | U7: #N/A | V7: #N/A | W7: #N/A | X7: #N/A | Y7: #N/A | Z7: #N/A | AA7: #N/A | AB7: #N/A | AC7: #N/A | AD7: #N/A | AE7: #N/A | AF7: #N/A | AG7: #N/A | AH7: #N/A | AI7: #N/A | AJ7: #N/A | AK7: #N/A | AL7: #N/A | AM7: #N/A | AN7: #N/A | AO7: #N/A | AP7: #N/A | AQ7: #N/A | AR7: #N/A | AS7: #N/A | AT7: #N/A | AU7: #N/A | AV7: #N/A | AW7: #N/A | AX7: #N/A | AY7: #N/A | AZ7: #N/A | BA7: #N/A | BB7: #N/A | BC7: #N/A | BD7: #N/A | BE7: #N/A | BF7: #N/A | BG7: #N/A | BH7: #N/A | BI7: #N/A | BJ7: #N/A | BK7: #N/A | BL7: #N/A | BM7: #N/A | BN7: #N/A | BO7: #N/A | BP7: #N/A | BQ7: #N/A | BR7: #N/A | BS7: #N/A | BT7: #N/A | BU7: #N/A | BV7: #N/A | BW7: #N/A | BX7: #N/A | BY7: #N/A | BZ7: #N/A | CA7: #N/A | CB7: #N/A | CC7: #N/A | CD7: #N/A | CE7: #N/A | CF7: #N/A | CG7: #N/A | CH7: #N/A | CI7: #N/A | CJ7: #N/A | CK7: #N/A | CL7: #N/A | CM7: #N/A | CN7: #N/A | CO7: #N/A | CP7: #N/A | CQ7: #N/A | CR7: #N/A | CS7: 477
A8: 1977 | B8: 28126 | C8: =$CS$6-SUM(cbo_deficit!C$7:'cbo_deficit'!C8) -> 506 | D8: =$CS$7-SUM(cbo_deficit!D$8:'cbo_deficit'!D8) -> 528 | E8: #N/A | F8: #N/A | G8: #N/A | H8: #N/A | I8: #N/A | J8: #N/A | K8: #N/A | L8: #N/A | M8: #N/A | N8: #N/A | O8: #N/A | P8: #N/A | Q8: #N/A | R8: #N/A | S8: #N/A | T8: #N/A | U8: #N/A | V8: #N/A | W8: #N/A | X8: #N/A | Y8: #N/A | Z8: #N/A | AA8: #N/A | AB8: #N/A | AC8: #N/A | AD8: #N/A | AE8: #N/A | AF8: #N/A | AG8: #N/A | AH8: #N/A | AI8: #N/A | AJ8: #N/A | AK8: #N/A | AL8: #N/A | AM8: #N/A | AN8: #N/A | AO8: #N/A | AP8: #N/A | AQ8: #N/A | AR8: #N/A | AS8: #N/A | AT8: #N/A | AU8: #N/A | AV8: #N/A | AW8: #N/A | AX8: #N/A | AY8: #N/A | AZ8: #N/A | BA8: #N/A | BB8: #N/A | BC8: #N/A | BD8: #N/A | BE8: #N/A | BF8: #N/A | BG8: #N/A | BH8: #N/A | BI8: #N/A | BJ8: #N/A | BK8: #N/A | BL8: #N/A | BM8: #N/A | BN8: #N/A | BO8: #N/A | BP8: #N/A | BQ8: #N/A | BR8: #N/A | BS8: #N/A | BT8: #N/A | BU8: #N/A | BV8: #N/A | BW8: #N/A | BX8: #N/A | BY8: #N/A | BZ8: #N/A | CA8: #N/A | CB8: #N/A | CC8: #N/A | CD8: #N/A | CE8: #N/A | CF8: #N/A | CG8: #N/A | CH8: #N/A | CI8: #N/A | CJ8: #N/A | CK8: #N/A | CL8: #N/A | CM8: #N/A | CN8: #N/A | CO8: #N/A | CP8: #N/A | CQ8: #N/A | CR8: #N/A | CS8: 549
A9: 1978 | B9: 28491 | C9: =$CS$6-SUM(cbo_deficit!C$7:'cbo_deficit'!C9) -> 509 | D9: =$CS$7-SUM(cbo_deficit!D$8:'cbo_deficit'!D9) -> 572 | E9: =$CS$8-SUM(cbo_deficit!E$9:'cbo_deficit'!E9) -> 610 | F9: #N/A | G9: #N/A | H9: #N/A | I9: #N/A | J9: #N/A | K9: #N/A | L9: #N/A | M9: #N/A | N9: #N/A | O9: #N/A | P9: #N/A | Q9: #N/A | R9: #N/A | S9: #N/A | T9: #N/A | U9: #N/A | V9: #N/A | W9: #N/A | X9: #N/A | Y9: #N/A | Z9: #N/A | AA9: #N/A | AB9: #N/A | AC9: #N/A | AD9: #N/A | AE9: #N/A | AF9: #N/A | AG9: #N/A | AH9: #N/A | AI9: #N/A | AJ9: #N/A | AK9: #N/A | AL9: #N/A | AM9: #N/A | AN9: #N/A | AO9: #N/A | AP9: #N/A | AQ9: #N/A | AR9: #N/A | AS9: #N/A | AT9: #N/A | AU9: #N/A | AV9: #N/A | AW9: #N/A | AX9: #N/A | AY9: #N/A | AZ9: #N/A | BA9: #N/A | BB9: #N/A | BC9: #N/A | BD9: #N/A | BE9: #N/A | BF9: #N/A | BG9: #N/A | BH9: #N/A | BI9: #N/A | BJ9: #N/A | BK9: #N/A | BL9: #N/A | BM9: #N/A | BN9: #N/A | BO9: #N/A | BP9: #N/A | BQ9: #N/A | BR9: #N/A | BS9: #N/A | BT9: #N/A | BU9: #N/A | BV9: #N/A | BW9: #N/A | BX9: #N/A | BY9: #N/A | BZ9: #N/A | CA9: #N/A | CB9: #N/A | CC9: #N/A | CD9: #N/A | CE9: #N/A | CF9: #N/A | CG9: #N/A | CH9: #N/A | CI9: #N/A | CJ9: #N/A | CK9: #N/A | CL9: #N/A | CM9: #N/A | CN9: #N/A | CO9: #N/A | CP9: #N/A | CQ9: #N/A | CR9: #N/A | CS9: 607
A10: 1979 | B10: 28856 | C10: =$CS$6-SUM(cbo_deficit!C$7:'cbo_deficit'!C10) -> 480 | D10: =$CS$7-SUM(cbo_deficit!D$8:'cbo_deficit'!D10) -> 588 | E10: =$CS$8-SUM(cbo_deficit!E$9:'cbo_deficit'!E10) -> 648 | F10: =$CS$9-SUM(cbo_deficit!F$10:'cbo_deficit'!F10) -> 648 | G10: #N/A | H10: #N/A | I10: #N/A | J10: #N/A | K10: #N/A | L10: #N/A | M10: #N/A | N10: #N/A | O10: #N/A | P10: #N/A | Q10: #N/A | R10: #N/A | S10: #N/A | T10: #N/A | U10: #N/A | V10: #N/A | W10: #N/A | X10: #N/A | Y10: #N/A | Z10: #N/A | AA10: #N/A | AB10: #N/A | AC10: #N/A | AD10: #N/A | AE10: #N/A | AF10: #N/A | AG10: #N/A | AH10: #N/A | AI10: #N/A | AJ10: #N/A | AK10: #N/A | AL10: #N/A | AM10: #N/A | AN10: #N/A | AO10: #N/A | AP10: #N/A | AQ10: #N/A | AR10: #N/A | AS10: #N/A | AT10: #N/A | AU10: #N/A | AV10: #N/A | AW10: #N/A | AX10: #N/A | AY10: #N/A | AZ10: #N/A | BA10: #N/A | BB10: #N/A | BC10: #N/A | BD10: #N/A | BE10: #N/A | BF10: #N/A | BG10: #N/A | BH10: #N/A | BI10: #N/A | BJ10: #N/A | BK10: #N/A | BL10: #N/A | BM10: #N/A | BN10: #N/A | BO10: #N/A | BP10: #N/A | BQ10: #N/A | BR10: #N/A | BS10: #N/A | BT10: #N/A | BU10: #N/A | BV10: #N/A | BW10: #N/A | BX10: #N/A | BY10: #N/A | BZ10: #N/A | CA10: #N/A | CB10: #N/A | CC10: #N/A | CD10: #N/A | CE10: #N/A | CF10: #N/A | CG10: #N/A | CH10: #N/A | CI10: #N/A | CJ10: #N/A | CK10: #N/A | CL10: #N/A | CM10: #N/A | CN10: #N/A | CO10: #N/A | CP10: #N/A | CQ10: #N/A | CR10: #N/A | CS10: 640
A11: 1980 | B11: 29221 | C11: =$CS$6-SUM(cbo_deficit!C$7:'cbo_deficit'!C11) -> 422 | D11: =$CS$7-SUM(cbo_deficit!D$8:'cbo_deficit'!D11) -> 576 | E11: =$CS$8-SUM(cbo_deficit!E$9:'cbo_deficit'!E11) -> 658 | F11: =$CS$9-SUM(cbo_deficit!F$10:'cbo_deficit'!F11) -> 697 | G11: =$CS$10-SUM(cbo_deficit!G$11:'cbo_deficit'!G11) -> 684 | H11: #N/A | I11: #N/A | J11: #N/A | K11: #N/A | L11: #N/A | M11: #N/A | N11: #N/A | O11: #N/A | P11: #N/A | Q11: #N/A | R11: #N/A | S11: #N/A | T11: #N/A | U11: #N/A | V11: #N/A | W11: #N/A | X11: #N/A | Y11: #N/A | Z11: #N/A | AA11: #N/A | AB11: #N/A | AC11: #N/A | AD11: #N/A | AE11: #N/A | AF11: #N/A | AG11: #N/A | AH11: #N/A | AI11: #N/A | AJ11: #N/A | AK11: #N/A | AL11: #N/A | AM11: #N/A | AN11: #N/A | AO11: #N/A | AP11: #N/A | AQ11: #N/A | AR11: #N/A | AS11: #N/A | AT11: #N/A | AU11: #N/A | AV11: #N/A | AW11: #N/A | AX11: #N/A | AY11: #N/A | AZ11: #N/A | BA11: #N/A | BB11: #N/A | BC11: #N/A | BD11: #N/A | BE11: #N/A | BF11: #N/A | BG11: #N/A | BH11: #N/A | BI11: #N/A | BJ11: #N/A | BK11: #N/A | BL11: #N/A | BM11: #N/A | BN11: #N/A | BO11: #N/A | BP11: #N/A | BQ11: #N/A | BR11: #N/A | BS11: #N/A | BT11: #N/A | BU11: #N/A | BV11: #N/A | BW11: #N/A | BX11: #N/A | BY11: #N/A | BZ11: #N/A | CA11: #N/A | CB11: #N/A | CC11: #N/A | CD11: #N/A | CE11: #N/A | CF11: #N/A | CG11: #N/A | CH11: #N/A | CI11: #N/A | CJ11: #N/A | CK11: #N/A | CL11: #N/A | CM11: #N/A | CN11: #N/A | CO11: #N/A | CP11: #N/A | CQ11: #N/A | CR11: #N/A | CS11: 712
A12: 1981 | B12: 29587 | C12: =$CS$6-SUM(cbo_deficit!C$7:'cbo_deficit'!C12) -> 330 | D12: =$CS$7-SUM(cbo_deficit!D$8:'cbo_deficit'!D12) -> 530 | E12: =$CS$8-SUM(cbo_deficit!E$9:'cbo_deficit'!E12) -> 633 | F12: =$CS$9-SUM(cbo_deficit!F$10:'cbo_deficit'!F12) -> 727 | G12: =$CS$10-SUM(cbo_deficit!G$11:'cbo_deficit'!G12) -> 731 | H12: =$CS$11-SUM(cbo_deficit!H$12:'cbo_deficit'!H12) -> 760 | I12: #N/A | J12: #N/A | K12: #N/A | L12: #N/A | M12: #N/A | N12: #N/A | O12: #N/A | P12: #N/A | Q12: #N/A | R12: #N/A | S12: #N/A | T12: #N/A | U12: #N/A | V12: #N/A | W12: #N/A | X12: #N/A | Y12: #N/A | Z12: #N/A | AA12: #N/A | AB12: #N/A | AC12: #N/A | AD12: #N/A | AE12: #N/A | AF12: #N/A | AG12: #N/A | AH12: #N/A | AI12: #N/A | AJ12: #N/A | AK12: #N/A | AL12: #N/A | AM12: #N/A | AN12: #N/A | AO12: #N/A | AP12: #N/A | AQ12: #N/A | AR12: #N/A | AS12: #N/A | AT12: #N/A | AU12: #N/A | AV12: #N/A | AW12: #N/A | AX12: #N/A | AY12: #N/A | AZ12: #N/A | BA12: #N/A | BB12: #N/A | BC12: #N/A | BD12: #N/A | BE12: #N/A | BF12: #N/A | BG12: #N/A | BH12: #N/A | BI12: #N/A | BJ12: #N/A | BK12: #N/A | BL12: #N/A | BM12: #N/A | BN12: #N/A | BO12: #N/A | BP12: #N/A | BQ12: #N/A | BR12: #N/A | BS12: #N/A | BT12: #N/A | BU12: #N/A | BV12: #N/A | BW12: #N/A | BX12: #N/A | BY12: #N/A | BZ12: #N/A | CA12: #N/A | CB12: #N/A | CC12: #N/A | CD12: #N/A | CE12: #N/A | CF12: #N/A | CG12: #N/A | CH12: #N/A | CI12: #N/A | CJ12: #N/A | CK12: #N/A | CL12: #N/A | CM12: #N/A | CN12: #N/A | CO12: #N/A | CP12: #N/A | CQ12: #N/A | CR12: #N/A | CS12: 789
A13: 1982 | B13: 29952 | C13: #N/A | D13: =$CS$7-SUM(cbo_deficit!D$8:'cbo_deficit'!D13) -> 448 | E13: =$CS$8-SUM(cbo_deficit!E$9:'cbo_deficit'!E13) -> 571 | F13: =$CS$9-SUM(cbo_deficit!F$10:'cbo_deficit'!F13) -> 721 | G13: =$CS$10-SUM(cbo_deficit!G$11:'cbo_deficit'!G13) -> 763 | H13: =$CS$11-SUM(cbo_deficit!H$12:'cbo_deficit'!H13) -> 790 | I13: =$CS$12-SUM(cbo_deficit!I$13:'cbo_deficit'!I13) -> 918 | J13: #N/A | K13: #N/A | L13: #N/A | M13: #N/A | N13: #N/A | O13: #N/A | P13: #N/A | Q13: #N/A | R13: #N/A | S13: #N/A | T13: #N/A | U13: #N/A | V13: #N/A | W13: #N/A | X13: #N/A | Y13: #N/A | Z13: #N/A | AA13: #N/A | AB13: #N/A | AC13: #N/A | AD13: #N/A | AE13: #N/A | AF13: #N/A | AG13: #N/A | AH13: #N/A | AI13: #N/A | AJ13: #N/A | AK13: #N/A | AL13: #N/A | AM13: #N/A | AN13: #N/A | AO13: #N/A | AP13: #N/A | AQ13: #N/A | AR13: #N/A | AS13: #N/A | AT13: #N/A | AU13: #N/A | AV13: #N/A | AW13: #N/A | AX13: #N/A | AY13: #N/A | AZ13: #N/A | BA13: #N/A | BB13: #N/A | BC13: #N/A | BD13: #N/A | BE13: #N/A | BF13: #N/A | BG13: #N/A | BH13: #N/A | BI13: #N/A | BJ13: #N/A | BK13: #N/A | BL13: #N/A | BM13: #N/A | BN13: #N/A | BO13: #N/A | BP13: #N/A | BQ13: #N/A | BR13: #N/A | BS13: #N/A | BT13: #N/A | BU13: #N/A | BV13: #N/A | BW13: #N/A | BX13: #N/A | BY13: #N/A | BZ13: #N/A | CA13: #N/A | CB13: #N/A | CC13: #N/A | CD13: #N/A | CE13: #N/A | CF13: #N/A | CG13: #N/A | CH13: #N/A | CI13: #N/A | CJ13: #N/A | CK13: #N/A | CL13: #N/A | CM13: #N/A | CN13: #N/A | CO13: #N/A | CP13: #N/A | CQ13: #N/A | CR13: #N/A | CS13: 925
A14: 1983 | B14: 30317 | C14: #N/A | D14: #N/A | E14: =$CS$8-SUM(cbo_deficit!E$9:'cbo_deficit'!E14) -> 475 | F14: =$CS$9-SUM(cbo_deficit!F$10:'cbo_deficit'!F14) -> 678 | G14: =$CS$10-SUM(cbo_deficit!G$11:'cbo_deficit'!G14) -> 778 | H14: =$CS$11-SUM(cbo_deficit!H$12:'cbo_deficit'!H14) -> 772 | I14: =$CS$12-SUM(cbo_deficit!I$13:'cbo_deficit'!I14) -> 1094 | J14: 1128 | K14: #N/A | L14: #N/A | M14: #N/A | N14: #N/A | O14: #N/A | P14: #N/A | Q14: #N/A | R14: #N/A | S14: #N/A | T14: #N/A | U14: #N/A | V14: #N/A | W14: #N/A | X14: #N/A | Y14: #N/A | Z14: #N/A | AA14: #N/A | AB14: #N/A | AC14: #N/A | AD14: #N/A | AE14: #N/A | AF14: #N/A | AG14: #N/A | AH14: #N/A | AI14: #N/A | AJ14: #N/A | AK14: #N/A | AL14: #N/A | AM14: #N/A | AN14: #N/A | AO14: #N/A | AP14: #N/A | AQ14: #N/A | AR14: #N/A | AS14: #N/A | AT14: #N/A | AU14: #N/A | AV14: #N/A | AW14: #N/A | AX14: #N/A | AY14: #N/A | AZ14: #N/A | BA14: #N/A | BB14: #N/A | BC14: #N/A | BD14: #N/A | BE14: #N/A | BF14: #N/A | BG14: #N/A | BH14: #N/A | BI14: #N/A | BJ14: #N/A | BK14: #N/A | BL14: #N/A | BM14: #N/A | BN14: #N/A | BO14: #N/A | BP14: #N/A | BQ14: #N/A | BR14: #N/A | BS14: #N/A | BT14: #N/A | BU14: #N/A | BV14: #N/A | BW14: #N/A | BX14: #N/A | BY14: #N/A | BZ14: #N/A | CA14: #N/A | CB14: #N/A | CC14: #N/A | CD14: #N/A | CE14: #N/A | CF14: #N/A | CG14: #N/A | CH14: #N/A | CI14: #N/A | CJ14: #N/A | CK14: #N/A | CL14: #N/A | CM14: #N/A | CN14: #N/A | CO14: #N/A | CP14: #N/A | CQ14: #N/A | CR14: #N/A | CS14: 1137
A15: 1984 | B15: 30682 | C15: #N/A | D15: #N/A | E15: #N/A | F15: =$CS$9-SUM(cbo_deficit!F$10:'cbo_deficit'!F15) -> 584 | G15: =$CS$10-SUM(cbo_deficit!G$11:'cbo_deficit'!G15) -> 760 | H15: =$CS$11-SUM(cbo_deficit!H$12:'cbo_deficit'!H15) -> 696 | I15: =$CS$12-SUM(cbo_deficit!I$13:'cbo_deficit'!I15) -> 1300 | J15: 1340 | K15: 1327 | L15: #N/A | M15: #N/A | N15: #N/A | O15: #N/A | P15: #N/A | Q15: #N/A | R15: #N/A | S15: #N/A | T15: #N/A | U15: #N/A | V15: #N/A | W15: #N/A | X15: #N/A | Y15: #N/A | Z15: #N/A | AA15: #N/A | AB15: #N/A | AC15: #N/A | AD15: #N/A | AE15: #N/A | AF15: #N/A | AG15: #N/A | AH15: #N/A | AI15: #N/A | AJ15: #N/A | AK15: #N/A | AL15: #N/A | AM15: #N/A | AN15: #N/A | AO15: #N/A | AP15: #N/A | AQ15: #N/A | AR15: #N/A | AS15: #N/A | AT15: #N/A | AU15: #N/A | AV15: #N/A | AW15: #N/A | AX15: #N/A | AY15: #N/A | AZ15: #N/A | BA15: #N/A | BB15: #N/A | BC15: #N/A | BD15: #N/A | BE15: #N/A | BF15: #N/A | BG15: #N/A | BH15: #N/A | BI15: #N/A | BJ15: #N/A | BK15: #N/A | BL15: #N/A | BM15: #N/A | BN15: #N/A | BO15: #N/A | BP15: #N/A | BQ15: #N/A | BR15: #N/A | BS15: #N/A | BT15: #N/A | BU15: #N/A | BV15: #N/A | BW15: #N/A | BX15: #N/A | BY15: #N/A | BZ15: #N/A | CA15: #N/A | CB15: #N/A | CC15: #N/A | CD15: #N/A | CE15: #N/A | CF15: #N/A | CG15: #N/A | CH15: #N/A | CI15: #N/A | CJ15: #N/A | CK15: #N/A | CL15: #N/A | CM15: #N/A | CN15: #N/A | CO15: #N/A | CP15: #N/A | CQ15: #N/A | CR15: #N/A | CS15: 1307
A16: 1985 | B16: 31048 | C16: #N/A | D16: #N/A | E16: #N/A | F16: #N/A | G16: =$CS$10-SUM(cbo_deficit!G$11:'cbo_deficit'!G16) -> 700 | H16: =$CS$11-SUM(cbo_deficit!H$12:'cbo_deficit'!H16) -> 558 | I16: =$CS$12-SUM(cbo_deficit!I$13:'cbo_deficit'!I16) -> 1526 | J16: 1571 | K16: 1534 | L16: 1526 | M16: 1522 | N16: #N/A | O16: #N/A | P16: #N/A | Q16: #N/A | R16: #N/A | S16: #N/A | T16: #N/A | U16: #N/A | V16: #N/A | W16: #N/A | X16: #N/A | Y16: #N/A | Z16: #N/A | AA16: #N/A | AB16: #N/A | AC16: #N/A | AD16: #N/A | AE16: #N/A | AF16: #N/A | AG16: #N/A | AH16: #N/A | AI16: #N/A | AJ16: #N/A | AK16: #N/A | AL16: #N/A | AM16: #N/A | AN16: #N/A | AO16: #N/A | AP16: #N/A | AQ16: #N/A | AR16: #N/A | AS16: #N/A | AT16: #N/A | AU16: #N/A | AV16: #N/A | AW16: #N/A | AX16: #N/A | AY16: #N/A | AZ16: #N/A | BA16: #N/A | BB16: #N/A | BC16: #N/A | BD16: #N/A | BE16: #N/A | BF16: #N/A | BG16: #N/A | BH16: #N/A | BI16: #N/A | BJ16: #N/A | BK16: #N/A | BL16: #N/A | BM16: #N/A | BN16: #N/A | BO16: #N/A | BP16: #N/A | BQ16: #N/A | BR16: #N/A | BS16: #N/A | BT16: #N/A | BU16: #N/A | BV16: #N/A | BW16: #N/A | BX16: #N/A | BY16: #N/A | BZ16: #N/A | CA16: #N/A | CB16: #N/A | CC16: #N/A | CD16: #N/A | CE16: #N/A | CF16: #N/A | CG16: #N/A | CH16: #N/A | CI16: #N/A | CJ16: #N/A | CK16: #N/A | CL16: #N/A | CM16: #N/A | CN16: #N/A | CO16: #N/A | CP16: #N/A | CQ16: #N/A | CR16: #N/A | CS16: 1507
A17: 1986 | B17: 31413 | C17: #N/A | D17: #N/A | E17: #N/A | F17: #N/A | G17: #N/A | H17: =$CS$11-SUM(cbo_deficit!H$12:'cbo_deficit'!H17) -> 349 | I17: =$CS$12-SUM(cbo_deficit!I$13:'cbo_deficit'!I17) -> 1780 | J17: 1820 | K17: 1763 | L17: 1740 | M17: 1701 | N17: 1720 | O17: 1739 | P17: #N/A | Q17: #N/A | R17: #N/A | S17: #N/A | T17: #N/A | U17: #N/A | V17: #N/A | W17: #N/A | X17: #N/A | Y17: #N/A | Z17: #N/A | AA17: #N/A | AB17: #N/A | AC17: #N/A | AD17: #N/A | AE17: #N/A | AF17: #N/A | AG17: #N/A | AH17: #N/A | AI17: #N/A | AJ17: #N/A | AK17: #N/A | AL17: #N/A | AM17: #N/A | AN17: #N/A | AO17: #N/A | AP17: #N/A | AQ17: #N/A | AR17: #N/A | AS17: #N/A | AT17: #N/A | AU17: #N/A | AV17: #N/A | AW17: #N/A | AX17: #N/A | AY17: #N/A | AZ17: #N/A | BA17: #N/A | BB17: #N/A | BC17: #N/A | BD17: #N/A | BE17: #N/A | BF17: #N/A | BG17: #N/A | BH17: #N/A | BI17: #N/A | BJ17: #N/A | BK17: #N/A | BL17: #N/A | BM17: #N/A | BN17: #N/A | BO17: #N/A | BP17: #N/A | BQ17: #N/A | BR17: #N/A | BS17: #N/A | BT17: #N/A | BU17: #N/A | BV17: #N/A | BW17: #N/A | BX17: #N/A | BY17: #N/A | BZ17: #N/A | CA17: #N/A | CB17: #N/A | CC17: #N/A | CD17: #N/A | CE17: #N/A | CF17: #N/A | CG17: #N/A | CH17: #N/A | CI17: #N/A | CJ17: #N/A | CK17: #N/A | CL17: #N/A | CM17: #N/A | CN17: #N/A | CO17: #N/A | CP17: #N/A | CQ17: #N/A | CR17: #N/A | CS17: 1741
A18: 1987 | B18: 31778 | C18: #N/A | D18: #N/A | E18: #N/A | F18: #N/A | G18: #N/A | H18: #N/A | I18: =$CS$12-SUM(cbo_deficit!I$13:'cbo_deficit'!I18) -> 2050 | J18: 2087 | K18: 2024 | L18: 1972 | M18: 1861 | N18: 1900 | O18: 1924 | P18: 1910 | Q18: 1901 | R18: #N/A | S18: #N/A | T18: #N/A | U18: #N/A | V18: #N/A | W18: #N/A | X18: #N/A | Y18: #N/A | Z18: #N/A | AA18: #N/A | AB18: #N/A | AC18: #N/A | AD18: #N/A | AE18: #N/A | AF18: #N/A | AG18: #N/A | AH18: #N/A | AI18: #N/A | AJ18: #N/A | AK18: #N/A | AL18: #N/A | AM18: #N/A | AN18: #N/A | AO18: #N/A | AP18: #N/A | AQ18: #N/A | AR18: #N/A | AS18: #N/A | AT18: #N/A | AU18: #N/A | AV18: #N/A | AW18: #N/A | AX18: #N/A | AY18: #N/A | AZ18: #N/A | BA18: #N/A | BB18: #N/A | BC18: #N/A | BD18: #N/A | BE18: #N/A | BF18: #N/A | BG18: #N/A | BH18: #N/A | BI18: #N/A | BJ18: #N/A | BK18: #N/A | BL18: #N/A | BM18: #N/A | BN18: #N/A | BO18: #N/A | BP18: #N/A | BQ18: #N/A | BR18: #N/A | BS18: #N/A | BT18: #N/A | BU18: #N/A | BV18: #N/A | BW18: #N/A | BX18: #N/A | BY18: #N/A | BZ18: #N/A | CA18: #N/A | CB18: #N/A | CC18: #N/A | CD18: #N/A | CE18: #N/A | CF18: #N/A | CG18: #N/A | CH18: #N/A | CI18: #N/A | CJ18: #N/A | CK18: #N/A | CL18: #N/A | CM18: #N/A | CN18: #N/A | CO18: #N/A | CP18: #N/A | CQ18: #N/A | CR18: #N/A | CS18: 1890
A19: 1988 | B19: 32143 | C19: #N/A | D19: #N/A | E19: #N/A | F19: #N/A | G19: #N/A | H19: #N/A | I19: #N/A | J19: 2372 | K19: 2318 | L19: 2220 | M19: 2002 | N19: 2064 | O19: 2071 | P19: 2077 | Q19: 2077 | R19: 2041 | S19: 2031 | T19: #N/A | U19: #N/A | V19: #N/A | W19: #N/A | X19: #N/A | Y19: #N/A | Z19: #N/A | AA19: #N/A | AB19: #N/A | AC19: #N/A | AD19: #N/A | AE19: #N/A | AF19: #N/A | AG19: #N/A | AH19: #N/A | AI19: #N/A | AJ19: #N/A | AK19: #N/A | AL19: #N/A | AM19: #N/A | AN19: #N/A | AO19: #N/A | AP19: #N/A | AQ19: #N/A | AR19: #N/A | AS19: #N/A | AT19: #N/A | AU19: #N/A | AV19: #N/A | AW19: #N/A | AX19: #N/A | AY19: #N/A | AZ19: #N/A | BA19: #N/A | BB19: #N/A | BC19: #N/A | BD19: #N/A | BE19: #N/A | BF19: #N/A | BG19: #N/A | BH19: #N/A | BI19: #N/A | BJ19: #N/A | BK19: #N/A | BL19: #N/A | BM19: #N/A | BN19: #N/A | BO19: #N/A | BP19: #N/A | BQ19: #N/A | BR19: #N/A | BS19: #N/A | BT19: #N/A | BU19: #N/A | BV19: #N/A | BW19: #N/A | BX19: #N/A | BY19: #N/A | BZ19: #N/A | CA19: #N/A | CB19: #N/A | CC19: #N/A | CD19: #N/A | CE19: #N/A | CF19: #N/A | CG19: #N/A | CH19: #N/A | CI19: #N/A | CJ19: #N/A | CK19: #N/A | CL19: #N/A | CM19: #N/A | CN19: #N/A | CO19: #N/A | CP19: #N/A | CQ19: #N/A | CR19: #N/A | CS19: 2052
A20: 1989 | B20: 32509 | C20: #N/A | D20: #N/A | E20: #N/A | F20: #N/A | G20: #N/A | H20: #N/A | I20: #N/A | J20: #N/A | K20: 2656 | L20: 2490 | M20: 2133 | N20: 2207 | O20: 2195 | P20: 2236 | Q20: 2266 | R20: 2216 | S20: 2178 | T20: 2190 | U20: 2196 | V20: #N/A | W20: #N/A | X20: #N/A | Y20: #N/A | Z20: #N/A | AA20: #N/A | AB20: #N/A | AC20: #N/A | AD20: #N/A | AE20: #N/A | AF20: #N/A | AG20: #N/A | AH20: #N/A | AI20: #N/A | AJ20: #N/A | AK20: #N/A | AL20: #N/A | AM20: #N/A | AN20: #N/A | AO20: #N/A | AP20: #N/A | AQ20: #N/A | AR20: #N/A | AS20: #N/A | AT20: #N/A | AU20: #N/A | AV20: #N/A | AW20: #N/A | AX20: #N/A | AY20: #N/A | AZ20: #N/A | BA20: #N/A | BB20: #N/A | BC20: #N/A | BD20: #N/A | BE20: #N/A | BF20: #N/A | BG20: #N/A | BH20: #N/A | BI20: #N/A | BJ20: #N/A | BK20: #N/A | BL20: #N/A | BM20: #N/A | BN20: #N/A | BO20: #N/A | BP20: #N/A | BQ20: #N/A | BR20: #N/A | BS20: #N/A | BT20: #N/A | BU20: #N/A | BV20: #N/A | BW20: #N/A | BX20: #N/A | BY20: #N/A | BZ20: #N/A | CA20: #N/A | CB20: #N/A | CC20: #N/A | CD20: #N/A | CE20: #N/A | CF20: #N/A | CG20: #N/A | CH20: #N/A | CI20: #N/A | CJ20: #N/A | CK20: #N/A | CL20: #N/A | CM20: #N/A | CN20: #N/A | CO20: #N/A | CP20: #N/A | CQ20: #N/A | CR20: #N/A | CS20: 2191
A21: 1990 | B21: 32874 | C21: #N/A | D21: #N/A | E21: #N/A | F21: #N/A | G21: #N/A | H21: #N/A | I21: #N/A | J21: #N/A | K21: #N/A | L21: 2786 | M21: 2252 | N21: 2326 | O21: 2290 | P21: 2367 | Q21: 2440 | R21: 2382 | S21: 2313 | T21: 2331 | U21: 2338 | V21: 2324 | W21: 2378 | X21: #N/A | Y21: #N/A | Z21: #N/A | AA21: #N/A | AB21: #N/A | AC21: #N/A | AD21: #N/A | AE21: #N/A | AF21: #N/A | AG21: #N/A | AH21: #N/A | AI21: #N/A | AJ21: #N/A | AK21: #N/A | AL21: #N/A | AM21: #N/A | AN21: #N/A | AO21: #N/A | AP21: #N/A | AQ21: #N/A | AR21: #N/A | AS21: #N/A | AT21: #N/A | AU21: #N/A | AV21: #N/A | AW21: #N/A | AX21: #N/A | AY21: #N/A | AZ21: #N/A | BA21: #N/A | BB21: #N/A | BC21: #N/A | BD21: #N/A | BE21: #N/A | BF21: #N/A | BG21: #N/A | BH21: #N/A | BI21: #N/A | BJ21: #N/A | BK21: #N/A | BL21: #N/A | BM21: #N/A | BN21: #N/A | BO21: #N/A | BP21: #N/A | BQ21: #N/A | BR21: #N/A | BS21: #N/A | BT21: #N/A | BU21: #N/A | BV21: #N/A | BW21: #N/A | BX21: #N/A | BY21: #N/A | BZ21: #N/A | CA21: #N/A | CB21: #N/A | CC21: #N/A | CD21: #N/A | CE21: #N/A | CF21: #N/A | CG21: #N/A | CH21: #N/A | CI21: #N/A | CJ21: #N/A | CK21: #N/A | CL21: #N/A | CM21: #N/A | CN21: #N/A | CO21: #N/A | CP21: #N/A | CQ21: #N/A | CR21: #N/A | CS21: 2412
A22: 1991 | B22: 33239 | C22: #N/A | D22: #N/A | E22: #N/A | F22: #N/A | G22: #N/A | H22: #N/A | I22: #N/A | J22: #N/A | K22: #N/A | L22: #N/A | M22: #N/A | N22: 2429 | O22: 2358 | P22: 2473 | Q22: 2601 | R22: 2537 | S22: 2441 | T22: 2469 | U22: 2481 | V22: 2460 | W22: 2607 | X22: 2693 | Y22: 2684 | Z22: #N/A | AA22: #N/A | AB22: #N/A | AC22: #N/A | AD22: #N/A | AE22: #N/A | AF22: #N/A | AG22: #N/A | AH22: #N/A | AI22: #N/A | AJ22: #N/A | AK22: #N/A | AL22: #N/A | AM22: #N/A | AN22: #N/A | AO22: #N/A | AP22: #N/A | AQ22: #N/A | AR22: #N/A | AS22: #N/A | AT22: #N/A | AU22: #N/A | AV22: #N/A | AW22: #N/A | AX22: #N/A | AY22: #N/A | AZ22: #N/A | BA22: #N/A | BB22: #N/A | BC22: #N/A | BD22: #N/A | BE22: #N/A | BF22: #N/A | BG22: #N/A | BH22: #N/A | BI22: #N/A | BJ22: #N/A | BK22: #N/A | BL22: #N/A | BM22: #N/A | BN22: #N/A | BO22: #N/A | BP22: #N/A | BQ22: #N/A | BR22: #N/A | BS22: #N/A | BT22: #N/A | BU22: #N/A | BV22: #N/A | BW22: #N/A | BX22: #N/A | BY22: #N/A | BZ22: #N/A | CA22: #N/A | CB22: #N/A | CC22: #N/A | CD22: #N/A | CE22: #N/A | CF22: #N/A | CG22: #N/A | CH22: #N/A | CI22: #N/A | CJ22: #N/A | CK22: #N/A | CL22: #N/A | CM22: #N/A | CN22: #N/A | CO22: #N/A | CP22: #N/A | CQ22: #N/A | CR22: #N/A | CS22: 2689
A23: 1992 | B23: 33604 | C23: #N/A | D23: #N/A | E23: #N/A | F23: #N/A | G23: #N/A | H23: #N/A | I23: #N/A | J23: #N/A | K23: #N/A | L23: #N/A | M23: #N/A | N23: #N/A | O23: #N/A | P23: 2556 | Q23: 2750 | R23: 2687 | S23: 2566 | T23: 2603 | U23: 2621 | V23: 2593 | W23: 2844 | X23: 2973 | Y23: 3040 | Z23: 3033 | AA23: 3000 | AB23: #N/A | AC23: #N/A | AD23: #N/A | AE23: #N/A | AF23: #N/A | AG23: #N/A | AH23: #N/A | AI23: #N/A | AJ23: #N/A | AK23: #N/A | AL23: #N/A | AM23: #N/A | AN23: #N/A | AO23: #N/A | AP23: #N/A | AQ23: #N/A | AR23: #N/A | AS23: #N/A | AT23: #N/A | AU23: #N/A | AV23: #N/A | AW23: #N/A | AX23: #N/A | AY23: #N/A | AZ23: #N/A | BA23: #N/A | BB23: #N/A | BC23: #N/A | BD23: #N/A | BE23: #N/A | BF23: #N/A | BG23: #N/A | BH23: #N/A | BI23: #N/A | BJ23: #N/A | BK23: #N/A | BL23: #N/A | BM23: #N/A | BN23: #N/A | BO23: #N/A | BP23: #N/A | BQ23: #N/A | BR23: #N/A | BS23: #N/A | BT23: #N/A | BU23: #N/A | BV23: #N/A | BW23: #N/A | BX23: #N/A | BY23: #N/A | BZ23: #N/A | CA23: #N/A | CB23: #N/A | CC23: #N/A | CD23: #N/A | CE23: #N/A | CF23: #N/A | CG23: #N/A | CH23: #N/A | CI23: #N/A | CJ23: #N/A | CK23: #N/A | CL23: #N/A | CM23: #N/A | CN23: #N/A | CO23: #N/A | CP23: #N/A | CQ23: #N/A | CR23: #N/A | CS23: 3000
A24: 1993 | B24: 33970 | C24: #N/A | D24: #N/A | E24: #N/A | F24: #N/A | G24: #N/A | H24: #N/A | I24: #N/A | J24: #N/A | K24: #N/A | L24: #N/A | M24: #N/A | N24: #N/A | O24: #N/A | P24: #N/A | Q24: #N/A | R24: 2820 | S24: 2686 | T24: 2732 | U24: 2762 | V24: 2734 | W24: 3038 | X24: 3185 | Y24: 3315 | Z24: 3360 | AA24: 3326 | AB24: 3290 | AC24: 3249 | AD24: #N/A | AE24: #N/A | AF24: #N/A | AG24: #N/A | AH24: #N/A | AI24: #N/A | AJ24: #N/A | AK24: #N/A | AL24: #N/A | AM24: #N/A | AN24: #N/A | AO24: #N/A | AP24: #N/A | AQ24: #N/A | AR24: #N/A | AS24: #N/A | AT24: #N/A | AU24: #N/A | AV24: #N/A | AW24: #N/A | AX24: #N/A | AY24: #N/A | AZ24: #N/A | BA24: #N/A | BB24: #N/A | BC24: #N/A | BD24: #N/A | BE24: #N/A | BF24: #N/A | BG24: #N/A | BH24: #N/A | BI24: #N/A | BJ24: #N/A | BK24: #N/A | BL24: #N/A | BM24: #N/A | BN24: #N/A | BO24: #N/A | BP24: #N/A | BQ24: #N/A | BR24: #N/A | BS24: #N/A | BT24: #N/A | BU24: #N/A | BV24: #N/A | BW24: #N/A | BX24: #N/A | BY24: #N/A | BZ24: #N/A | CA24: #N/A | CB24: #N/A | CC24: #N/A | CD24: #N/A | CE24: #N/A | CF24: #N/A | CG24: #N/A | CH24: #N/A | CI24: #N/A | CJ24: #N/A | CK24: #N/A | CL24: #N/A | CM24: #N/A | CN24: #N/A | CO24: #N/A | CP24: #N/A | CQ24: #N/A | CR24: #N/A | CS24: 3248
A25: 1994 | B25: 34335 | C25: #N/A | D25: #N/A | E25: #N/A | F25: #N/A | G25: #N/A | H25: #N/A | I25: #N/A | J25: #N/A | K25: #N/A | L25: #N/A | M25: #N/A | N25: #N/A | O25: #N/A | P25: #N/A | Q25: #N/A | R25: #N/A | S25: 2806 | T25: 2853 | U25: 2890 | V25: 2862 | W25: 3183 | X25: 3346 | Y25: 3548 | Z25: 3624 | AA25: 3597 | AB25: 3585 | AC25: 3507 | AD25: 3462 | AE25: 3440 | AF25: #N/A | AG25: #N/A | AH25: #N/A | AI25: #N/A | AJ25: #N/A | AK25: #N/A | AL25: #N/A | AM25: #N/A | AN25: #N/A | AO25: #N/A | AP25: #N/A | AQ25: #N/A | AR25: #N/A | AS25: #N/A | AT25: #N/A | AU25: #N/A | AV25: #N/A | AW25: #N/A | AX25: #N/A | AY25: #N/A | AZ25: #N/A | BA25: #N/A | BB25: #N/A | BC25: #N/A | BD25: #N/A | BE25: #N/A | BF25: #N/A | BG25: #N/A | BH25: #N/A | BI25: #N/A | BJ25: #N/A | BK25: #N/A | BL25: #N/A | BM25: #N/A | BN25: #N/A | BO25: #N/A | BP25: #N/A | BQ25: #N/A | BR25: #N/A | BS25: #N/A | BT25: #N/A | BU25: #N/A | BV25: #N/A | BW25: #N/A | BX25: #N/A | BY25: #N/A | BZ25: #N/A | CA25: #N/A | CB25: #N/A | CC25: #N/A | CD25: #N/A | CE25: #N/A | CF25: #N/A | CG25: #N/A | CH25: #N/A | CI25: #N/A | CJ25: #N/A | CK25: #N/A | CL25: #N/A | CM25: #N/A | CN25: #N/A | CO25: #N/A | CP25: #N/A | CQ25: #N/A | CR25: #N/A | CS25: 3433
A26: 1995 | B26: 34700 | C26: #N/A | D26: #N/A | E26: #N/A | F26: #N/A | G26: #N/A | H26: #N/A | I26: #N/A | J26: #N/A | K26: #N/A | L26: #N/A | M26: #N/A | N26: #N/A | O26: #N/A | P26: #N/A | Q26: #N/A | R26: #N/A | S26: #N/A | T26: #N/A | U26: #N/A | V26: 2979 | W26: 3321 | X26: 3405 | Y26: 3708 | Z26: 3824 | AA26: 3847 | AB26: 3874 | AC26: 3713 | AD26: 3642 | AE26: 3611 | AF26: 3617 | AG26: 3605 | AH26: #N/A | AI26: #N/A | AJ26: #N/A | AK26: #N/A | AL26: #N/A | AM26: #N/A | AN26: #N/A | AO26: #N/A | AP26: #N/A | AQ26: #N/A | AR26: #N/A | AS26: #N/A | AT26: #N/A | AU26: #N/A | AV26: #N/A | AW26: #N/A | AX26: #N/A | AY26: #N/A | AZ26: #N/A | BA26: #N/A | BB26: #N/A | BC26: #N/A | BD26: #N/A | BE26: #N/A | BF26: #N/A | BG26: #N/A | BH26: #N/A | BI26: #N/A | BJ26: #N/A | BK26: #N/A | BL26: #N/A | BM26: #N/A | BN26: #N/A | BO26: #N/A | BP26: #N/A | BQ26: #N/A | BR26: #N/A | BS26: #N/A | BT26: #N/A | BU26: #N/A | BV26: #N/A | BW26: #N/A | BX26: #N/A | BY26: #N/A | BZ26: #N/A | CA26: #N/A | CB26: #N/A | CC26: #N/A | CD26: #N/A | CE26: #N/A | CF26: #N/A | CG26: #N/A | CH26: #N/A | CI26: #N/A | CJ26: #N/A | CK26: #N/A | CL26: #N/A | CM26: #N/A | CN26: #N/A | CO26: #N/A | CP26: #N/A | CQ26: #N/A | CR26: #N/A | CS26: 3604
A27: 1996 | B27: 35065 | C27: #N/A | D27: #N/A | E27: #N/A | F27: #N/A | G27: #N/A | H27: #N/A | I27: #N/A | J27: #N/A | K27: #N/A | L27: #N/A | M27: #N/A | N27: #N/A | O27: #N/A | P27: #N/A | Q27: #N/A | R27: #N/A | S27: #N/A | T27: #N/A | U27: #N/A | V27: #N/A | W27: #N/A | X27: 3465 | Y27: 3867 | Z27: 4010 | AA27: 4107 | AB27: 4169 | AC27: 3919 | AD27: 3822 | AE27: 3801 | AF27: 3838 | AG27: 3809 | AH27: 3791 | AI27: 3770 | AJ27: #N/A | AK27: #N/A | AL27: #N/A | AM27: #N/A | AN27: #N/A | AO27: #N/A | AP27: #N/A | AQ27: #N/A | AR27: #N/A | AS27: #N/A | AT27: #N/A | AU27: #N/A | AV27: #N/A | AW27: #N/A | AX27: #N/A | AY27: #N/A | AZ27: #N/A | BA27: #N/A | BB27: #N/A | BC27: #N/A | BD27: #N/A | BE27: #N/A | BF27: #N/A | BG27: #N/A | BH27: #N/A | BI27: #N/A | BJ27: #N/A | BK27: #N/A | BL27: #N/A | BM27: #N/A | BN27: #N/A | BO27: #N/A | BP27: #N/A | BQ27: #N/A | BR27: #N/A | BS27: #N/A | BT27: #N/A | BU27: #N/A | BV27: #N/A | BW27: #N/A | BX27: #N/A | BY27: #N/A | BZ27: #N/A | CA27: #N/A | CB27: #N/A | CC27: #N/A | CD27: #N/A | CE27: #N/A | CF27: #N/A | CG27: #N/A | CH27: #N/A | CI27: #N/A | CJ27: #N/A | CK27: #N/A | CL27: #N/A | CM27: #N/A | CN27: #N/A | CO27: #N/A | CP27: #N/A | CQ27: #N/A | CR27: #N/A | CS27: 3734
A28: 1997 | B28: 35431 | C28: #N/A | D28: #N/A | E28: #N/A | F28: #N/A | G28: #N/A | H28: #N/A | I28: #N/A | J28: #N/A | K28: #N/A | L28: #N/A | M28: #N/A | N28: #N/A | O28: #N/A | P28: #N/A | Q28: #N/A | R28: #N/A | S28: #N/A | T28: #N/A | U28: #N/A | V28: #N/A | W28: #N/A | X28: #N/A | Y28: #N/A | Z28: 4244 | AA28: 4403 | AB28: 4496 | AC28: 4137 | AD28: 4021 | AE28: 4011 | AF28: 4077 | AG28: 4044 | AH28: 3987 | AI28: 3967 | AJ28: 3869 | AK28: 3784 | AL28: #N/A | AM28: #N/A | AN28: #N/A | AO28: #N/A | AP28: #N/A | AQ28: #N/A | AR28: #N/A | AS28: #N/A | AT28: #N/A | AU28: #N/A | AV28: #N/A | AW28: #N/A | AX28: #N/A | AY28: #N/A | AZ28: #N/A | BA28: #N/A | BB28: #N/A | BC28: #N/A | BD28: #N/A | BE28: #N/A | BF28: #N/A | BG28: #N/A | BH28: #N/A | BI28: #N/A | BJ28: #N/A | BK28: #N/A | BL28: #N/A | BM28: #N/A | BN28: #N/A | BO28: #N/A | BP28: #N/A | BQ28: #N/A | BR28: #N/A | BS28: #N/A | BT28: #N/A | BU28: #N/A | BV28: #N/A | BW28: #N/A | BX28: #N/A | BY28: #N/A | BZ28: #N/A | CA28: #N/A | CB28: #N/A | CC28: #N/A | CD28: #N/A | CE28: #N/A | CF28: #N/A | CG28: #N/A | CH28: #N/A | CI28: #N/A | CJ28: #N/A | CK28: #N/A | CL28: #N/A | CM28: #N/A | CN28: #N/A | CO28: #N/A | CP28: #N/A | CQ28: #N/A | CR28: #N/A | CS28: 3772
A29: 1998 | B29: 35796 | C29: #N/A | D29: #N/A | E29: #N/A | F29: #N/A | G29: #N/A | H29: #N/A | I29: #N/A | J29: #N/A | K29: #N/A | L29: #N/A | M29: #N/A | N29: #N/A | O29: #N/A | P29: #N/A | Q29: #N/A | R29: #N/A | S29: #N/A | T29: #N/A | U29: #N/A | V29: #N/A | W29: #N/A | X29: #N/A | Y29: #N/A | Z29: #N/A | AA29: #N/A | AB29: 4863 | AC29: 4357 | AD29: 4218 | AE29: 4226 | AF29: 4317 | AG29: 4289 | AH29: 4184 | AI29: 4181 | AJ29: 4009 | AK29: 3859 | AL29: 3790 | AM29: 3717 | AN29: #N/A | AO29: #N/A | AP29: #N/A | AQ29: #N/A | AR29: #N/A | AS29: #N/A | AT29: #N/A | AU29: #N/A | AV29: #N/A | AW29: #N/A | AX29: #N/A | AY29: #N/A | AZ29: #N/A | BA29: #N/A | BB29: #N/A | BC29: #N/A | BD29: #N/A | BE29: #N/A | BF29: #N/A | BG29: #N/A | BH29: #N/A | BI29: #N/A | BJ29: #N/A | BK29: #N/A | BL29: #N/A | BM29: #N/A | BN29: #N/A | BO29: #N/A | BP29: #N/A | BQ29: #N/A | BR29: #N/A | BS29: #N/A | BT29: #N/A | BU29: #N/A | BV29: #N/A | BW29: #N/A | BX29: #N/A | BY29: #N/A | BZ29: #N/A | CA29: #N/A | CB29: #N/A | CC29: #N/A | CD29: #N/A | CE29: #N/A | CF29: #N/A | CG29: #N/A | CH29: #N/A | CI29: #N/A | CJ29: #N/A | CK29: #N/A | CL29: #N/A | CM29: #N/A | CN29: #N/A | CO29: #N/A | CP29: #N/A | CQ29: #N/A | CR29: #N/A | CS29: 3721
A30: 1999 | B30: 36161 | C30: #N/A | D30: #N/A | E30: #N/A | F30: #N/A | G30: #N/A | H30: #N/A | I30: #N/A | J30: #N/A | K30: #N/A | L30: #N/A | M30: #N/A | N30: #N/A | O30: #N/A | P30: #N/A | Q30: #N/A | R30: #N/A | S30: #N/A | T30: #N/A | U30: #N/A | V30: #N/A | W30: #N/A | X30: #N/A | Y30: #N/A | Z30: #N/A | AA30: #N/A | AB30: 5275 | AC30: 4601 | AD30: 4441 | AE30: 4476 | AF30: 4589 | AG30: 4568 | AH30: 4395 | AI30: 4422 | AJ30: 4173 | AK30: 3926 | AL30: 3806 | AM30: 3655 | AN30: 3630 | AO30: 3618 | AP30: #N/A | AQ30: #N/A | AR30: #N/A | AS30: #N/A | AT30: #N/A | AU30: #N/A | AV30: #N/A | AW30: #N/A | AX30: #N/A | AY30: #N/A | AZ30: #N/A | BA30: #N/A | BB30: #N/A | BC30: #N/A | BD30: #N/A | BE30: #N/A | BF30: #N/A | BG30: #N/A | BH30: #N/A | BI30: #N/A | BJ30: #N/A | BK30: #N/A | BL30: #N/A | BM30: #N/A | BN30: #N/A | BO30: #N/A | BP30: #N/A | BQ30: #N/A | BR30: #N/A | BS30: #N/A | BT30: #N/A | BU30: #N/A | BV30: #N/A | BW30: #N/A | BX30: #N/A | BY30: #N/A | BZ30: #N/A | CA30: #N/A | CB30: #N/A | CC30: #N/A | CD30: #N/A | CE30: #N/A | CF30: #N/A | CG30: #N/A | CH30: #N/A | CI30: #N/A | CJ30: #N/A | CK30: #N/A | CL30: #N/A | CM30: #N/A | CN30: #N/A | CO30: #N/A | CP30: #N/A | CQ30: #N/A | CR30: #N/A | CS30: 3632
A31: 2000 | B31: 36526 | C31: #N/A | D31: #N/A | E31: #N/A | F31: #N/A | G31: #N/A | H31: #N/A | I31: #N/A | J31: #N/A | K31: #N/A | L31: #N/A | M31: #N/A | N31: #N/A | O31: #N/A | P31: #N/A | Q31: #N/A | R31: #N/A | S31: #N/A | T31: #N/A | U31: #N/A | V31: #N/A | W31: #N/A | X31: #N/A | Y31: #N/A | Z31: #N/A | AA31: #N/A | AB31: 5739 | AC31: 4873 | AD31: 4686 | AE31: 4753 | AF31: 4891 | AG31: 4873 | AH31: 4614 | AI31: 4687 | AJ31: 4358 | AK31: 3988 | AL31: 3821 | AM31: 3589 | AN31: 3515 | AO31: 3473 | AP31: 3455 | AQ31: 3409 | AR31: #N/A | AS31: #N/A | AT31: #N/A | AU31: #N/A | AV31: #N/A | AW31: #N/A | AX31: #N/A | AY31: #N/A | AZ31: #N/A | BA31: #N/A | BB31: #N/A | BC31: #N/A | BD31: #N/A | BE31: #N/A | BF31: #N/A | BG31: #N/A | BH31: #N/A | BI31: #N/A | BJ31: #N/A | BK31: #N/A | BL31: #N/A | BM31: #N/A | BN31: #N/A | BO31: #N/A | BP31: #N/A | BQ31: #N/A | BR31: #N/A | BS31: #N/A | BT31: #N/A | BU31: #N/A | BV31: #N/A | BW31: #N/A | BX31: #N/A | BY31: #N/A | BZ31: #N/A | CA31: #N/A | CB31: #N/A | CC31: #N/A | CD31: #N/A | CE31: #N/A | CF31: #N/A | CG31: #N/A | CH31: #N/A | CI31: #N/A | CJ31: #N/A | CK31: #N/A | CL31: #N/A | CM31: #N/A | CN31: #N/A | CO31: #N/A | CP31: #N/A | CQ31: #N/A | CR31: #N/A | CS31: 3410
A32: 2001 | B32: 36892 | C32: #N/A | D32: #N/A | E32: #N/A | F32: #N/A | G32: #N/A | H32: #N/A | I32: #N/A | J32: #N/A | K32: #N/A | L32: #N/A | M32: #N/A | N32: #N/A | O32: #N/A | P32: #N/A | Q32: #N/A | R32: #N/A | S32: #N/A | T32: #N/A | U32: #N/A | V32: #N/A | W32: #N/A | X32: #N/A | Y32: #N/A | Z32: #N/A | AA32: #N/A | AB32: 6261 | AC32: 5176 | AD32: 4961 | AE32: 5059 | AF32: #N/A | AG32: 5199 | AH32: 4841 | AI32: 4966 | AJ32: 4539 | AK32: 4039 | AL32: 3821 | AM32: 3518 | AN32: 3378 | AO32: 3297 | AP32: 3292 | AQ32: 3158 | AR32: 3148 | AS32: 3294 | AT32: #N/A | AU32: 3320 | AV32: #N/A | AW32: #N/A | AX32: #N/A | AY32: #N/A | AZ32: #N/A | BA32: #N/A | BB32: #N/A | BC32: #N/A | BD32: #N/A | BE32: #N/A | BF32: #N/A | BG32: #N/A | BH32: #N/A | BI32: #N/A | BJ32: #N/A | BK32: #N/A | BL32: #N/A | BM32: #N/A | BN32: #N/A | BO32: #N/A | BP32: #N/A | BQ32: #N/A | BR32: #N/A | BS32: #N/A | BT32: #N/A | BU32: #N/A | BV32: #N/A | BW32: #N/A | BX32: #N/A | BY32: #N/A | BZ32: #N/A | CA32: #N/A | CB32: #N/A | CC32: #N/A | CD32: #N/A | CE32: #N/A | CF32: #N/A | CG32: #N/A | CH32: #N/A | CI32: #N/A | CJ32: #N/A | CK32: #N/A | CL32: #N/A | CM32: #N/A | CN32: #N/A | CO32: #N/A | CP32: #N/A | CQ32: #N/A | CR32: #N/A | CS32: 3320
A33: 2002 | B33: 37257 | C33: #N/A | D33: #N/A | E33: #N/A | F33: #N/A | G33: #N/A | H33: #N/A | I33: #N/A | J33: #N/A | K33: #N/A | L33: #N/A | M33: #N/A | N33: #N/A | O33: #N/A | P33: #N/A | Q33: #N/A | R33: #N/A | S33: #N/A | T33: #N/A | U33: #N/A | V33: #N/A | W33: #N/A | X33: #N/A | Y33: #N/A | Z33: #N/A | AA33: #N/A | AB33: 6850 | AC33: 5517 | AD33: 5268 | AE33: 5397 | AF33: #N/A | AG33: 5557 | AH33: 5085 | AI33: 5268 | AJ33: 4740 | AK33: 4021 | AL33: 3765 | AM33: 3395 | AN33: 3183 | AO33: 3066 | AP33: 3097 | AQ33: 2854 | AR33: 2848 | AS33: 3138 | AT33: 3380 | AU33: 3504 | AV33: 3540 | AW33: 3540 | AX33: #N/A | AY33: #N/A | AZ33: #N/A | BA33: #N/A | BB33: #N/A | BC33: #N/A | BD33: #N/A | BE33: #N/A | BF33: #N/A | BG33: #N/A | BH33: #N/A | BI33: #N/A | BJ33: #N/A | BK33: #N/A | BL33: #N/A | BM33: #N/A | BN33: #N/A | BO33: #N/A | BP33: #N/A | BQ33: #N/A | BR33: #N/A | BS33: #N/A | BT33: #N/A | BU33: #N/A | BV33: #N/A | BW33: #N/A | BX33: #N/A | BY33: #N/A | BZ33: #N/A | CA33: #N/A | CB33: #N/A | CC33: #N/A | CD33: #N/A | CE33: #N/A | CF33: #N/A | CG33: #N/A | CH33: #N/A | CI33: #N/A | CJ33: #N/A | CK33: #N/A | CL33: #N/A | CM33: #N/A | CN33: #N/A | CO33: #N/A | CP33: #N/A | CQ33: #N/A | CR33: #N/A | CS33: 3540
A34: 2003 | B34: 37622 | C34: #N/A | D34: #N/A | E34: #N/A | F34: #N/A | G34: #N/A | H34: #N/A | I34: #N/A | J34: #N/A | K34: #N/A | L34: #N/A | M34: #N/A | N34: #N/A | O34: #N/A | P34: #N/A | Q34: #N/A | R34: #N/A | S34: #N/A | T34: #N/A | U34: #N/A | V34: #N/A | W34: #N/A | X34: #N/A | Y34: #N/A | Z34: #N/A | AA34: #N/A | AB34: 7512 | AC34: 5896 | AD34: 5611 | AE34: 5771 | AF34: #N/A | AG34: 5949 | AH34: 5345 | AI34: 5593 | AJ34: 4954 | AK34: 4020 | AL34: 3725 | AM34: 3275 | AN34: 2989 | AO34: 2835 | AP34: 2884 | AQ34: 2522 | AR34: 2509 | AS34: 2983 | AT34: 3410 | AU34: 3676 | AV34: 3766 | AW34: 3986 | AX34: 3914 | AY34: 3914 | AZ34: #N/A | BA34: #N/A | BB34: #N/A | BC34: #N/A | BD34: #N/A | BE34: #N/A | BF34: #N/A | BG34: #N/A | BH34: #N/A | BI34: #N/A | BJ34: #N/A | BK34: #N/A | BL34: #N/A | BM34: #N/A | BN34: #N/A | BO34: #N/A | BP34: #N/A | BQ34: #N/A | BR34: #N/A | BS34: #N/A | BT34: #N/A | BU34: #N/A | BV34: #N/A | BW34: #N/A | BX34: #N/A | BY34: #N/A | BZ34: #N/A | CA34: #N/A | CB34: #N/A | CC34: #N/A | CD34: #N/A | CE34: #N/A | CF34: #N/A | CG34: #N/A | CH34: #N/A | CI34: #N/A | CJ34: #N/A | CK34: #N/A | CL34: #N/A | CM34: #N/A | CN34: #N/A | CO34: #N/A | CP34: #N/A | CQ34: #N/A | CR34: #N/A | CS34: 3913
A35: 2004 | B35: 37987 | C35: #N/A | D35: #N/A | E35: #N/A | F35: #N/A | G35: #N/A | H35: #N/A | I35: #N/A | J35: #N/A | K35: #N/A | L35: #N/A | M35: #N/A | N35: #N/A | O35: #N/A | P35: #N/A | Q35: #N/A | R35: #N/A | S35: #N/A | T35: #N/A | U35: #N/A | V35: #N/A | W35: #N/A | X35: #N/A | Y35: #N/A | Z35: #N/A | AA35: #N/A | AB35: #N/A | AC35: #N/A | AD35: 5995 | AE35: 6188 | AF35: #N/A | AG35: 6380 | AH35: 5627 | AI35: 5947 | AJ35: 5184 | AK35: 4003 | AL35: 3668 | AM35: 3136 | AN35: 2770 | AO35: 2584 | AP35: 2651 | AQ35: 2165 | AR35: 2131 | AS35: 2797 | AT35: 3373 | AU35: 3805 | AV35: 3927 | AW35: 4443 | AX35: 4393 | AY35: 4334 | AZ35: 4296 | BA35: 4296 | BB35: #N/A | BC35: #N/A | BD35: #N/A | BE35: #N/A | BF35: #N/A | BG35: #N/A | BH35: #N/A | BI35: #N/A | BJ35: #N/A | BK35: #N/A | BL35: #N/A | BM35: #N/A | BN35: #N/A | BO35: #N/A | BP35: #N/A | BQ35: #N/A | BR35: #N/A | BS35: #N/A | BT35: #N/A | BU35: #N/A | BV35: #N/A | BW35: #N/A | BX35: #N/A | BY35: #N/A | BZ35: #N/A | CA35: #N/A | CB35: #N/A | CC35: #N/A | CD35: #N/A | CE35: #N/A | CF35: #N/A | CG35: #N/A | CH35: #N/A | CI35: #N/A | CJ35: #N/A | CK35: #N/A | CL35: #N/A | CM35: #N/A | CN35: #N/A | CO35: #N/A | CP35: #N/A | CQ35: #N/A | CR35: #N/A | CS35: 4296
A36: 2005 | B36: 38353 | C36: #N/A | D36: #N/A | E36: #N/A | F36: #N/A | G36: #N/A | H36: #N/A | I36: #N/A | J36: #N/A | K36: #N/A | L36: #N/A | M36: #N/A | N36: #N/A | O36: #N/A | P36: #N/A | Q36: #N/A | R36: #N/A | S36: #N/A | T36: #N/A | U36: #N/A | V36: #N/A | W36: #N/A | X36: #N/A | Y36: #N/A | Z36: #N/A | AA36: #N/A | AB36: #N/A | AC36: #N/A | AD36: #N/A | AE36: #N/A | AF36: #N/A | AG36: 6860 | AH36: 5936 | AI36: 6333 | AJ36: 5448 | AK36: 3978 | AL36: 3606 | AM36: 2981 | AN36: 2529 | AO36: 2312 | AP36: 2394 | AQ36: 1774 | AR36: 1714 | AS36: 2572 | AT36: 3288 | AU36: 3862 | AV36: 4013 | AW36: 4790 | AX36: 4771 | AY36: 4694 | AZ36: 4665 | BA36: 4621 | BB36: 4592 | BC36: 4592 | BD36: #N/A | BE36: #N/A | BF36: #N/A | BG36: #N/A | BH36: #N/A | BI36: #N/A | BJ36: #N/A | BK36: #N/A | BL36: #N/A | BM36: #N/A | BN36: #N/A | BO36: #N/A | BP36: #N/A | BQ36: #N/A | BR36: #N/A | BS36: #N/A | BT36: #N/A | BU36: #N/A | BV36: #N/A | BW36: #N/A | BX36: #N/A | BY36: #N/A | BZ36: #N/A | CA36: #N/A | CB36: #N/A | CC36: #N/A | CD36: #N/A | CE36: #N/A | CF36: #N/A | CG36: #N/A | CH36: #N/A | CI36: #N/A | CJ36: #N/A | CK36: #N/A | CL36: #N/A | CM36: #N/A | CN36: #N/A | CO36: #N/A | CP36: #N/A | CQ36: #N/A | CR36: #N/A | CS36: 4592
A37: 2006 | B37: 38718 | C37: #N/A | D37: #N/A | E37: #N/A | F37: #N/A | G37: #N/A | H37: #N/A | I37: #N/A | J37: #N/A | K37: #N/A | L37: #N/A | M37: #N/A | N37: #N/A | O37: #N/A | P37: #N/A | Q37: #N/A | R37: #N/A | S37: #N/A | T37: #N/A | U37: #N/A | V37: #N/A | W37: #N/A | X37: #N/A | Y37: #N/A | Z37: #N/A | AA37: #N/A | AB37: #N/A | AC37: #N/A | AD37: #N/A | AE37: #N/A | AF37: #N/A | AG37: #N/A | AH37: #N/A | AI37: 6746 | AJ37: 5723 | AK37: 3916 | AL37: 3503 | AM37: 2779 | AN37: 2237 | AO37: 1992 | AP37: 2080 | AQ37: 1315 | AR37: 1251 | AS37: 2300 | AT37: 3177 | AU37: 3865 | AV37: 4045 | AW37: 5027 | AX37: 5055 | AY37: 5009 | AZ37: 4971 | BA37: 4943 | BB37: 4925 | BC37: 4851 | BD37: 4829 | BE37: 4829 | BF37: #N/A | BG37: #N/A | BH37: #N/A | BI37: #N/A | BJ37: #N/A | BK37: #N/A | BL37: #N/A | BM37: #N/A | BN37: #N/A | BO37: #N/A | BP37: #N/A | BQ37: #N/A | BR37: #N/A | BS37: #N/A | BT37: #N/A | BU37: #N/A | BV37: #N/A | BW37: #N/A | BX37: #N/A | BY37: #N/A | BZ37: #N/A | CA37: #N/A | CB37: #N/A | CC37: #N/A | CD37: #N/A | CE37: #N/A | CF37: #N/A | CG37: #N/A | CH37: #N/A | CI37: #N/A | CJ37: #N/A | CK37: #N/A | CL37: #N/A | CM37: #N/A | CN37: #N/A | CO37: #N/A | CP37: #N/A | CQ37: #N/A | CR37: #N/A | CS37: 4829
A38: 2007 | B38: 39083 | C38: #N/A | D38: #N/A | E38: #N/A | F38: #N/A | G38: #N/A | H38: #N/A | I38: #N/A | J38: #N/A | K38: #N/A | L38: #N/A | M38: #N/A | N38: #N/A | O38: #N/A | P38: #N/A | Q38: #N/A | R38: #N/A | S38: #N/A | T38: #N/A | U38: #N/A | V38: #N/A | W38: #N/A | X38: #N/A | Y38: #N/A | Z38: #N/A | AA38: #N/A | AB38: #N/A | AC38: #N/A | AD38: #N/A | AE38: #N/A | AF38: #N/A | AG38: #N/A | AH38: #N/A | AI38: #N/A | AJ38: 6011 | AK38: 3842 | AL38: 3386 | AM38: 2557 | AN38: 1917 | AO38: 1640 | AP38: 1721 | AQ38: 1081 | AR38: 1128 | AS38: 1976 | AT38: 3027 | AU38: 3829 | AV38: 4034 | AW38: 5242 | AX38: 5338 | AY38: 5329 | AZ38: 5246 | BA38: 5281 | BB38: 5204 | BC38: 5149 | BD38: 4995 | BE38: 4993 | BF38: 5035 | BG38: 5035 | BH38: #N/A | BI38: #N/A | BJ38: #N/A | BK38: #N/A | BL38: #N/A | BM38: #N/A | BN38: #N/A | BO38: #N/A | BP38: #N/A | BQ38: #N/A | BR38: #N/A | BS38: #N/A | BT38: #N/A | BU38: #N/A | BV38: #N/A | BW38: #N/A | BX38: #N/A | BY38: #N/A | BZ38: #N/A | CA38: #N/A | CB38: #N/A | CC38: #N/A | CD38: #N/A | CE38: #N/A | CF38: #N/A | CG38: #N/A | CH38: #N/A | CI38: #N/A | CJ38: #N/A | CK38: #N/A | CL38: #N/A | CM38: #N/A | CN38: #N/A | CO38: #N/A | CP38: #N/A | CQ38: #N/A | CR38: #N/A | CS38: 5035
A39: 2008 | B39: 39448 | C39: #N/A | D39: #N/A | E39: #N/A | F39: #N/A | G39: #N/A | H39: #N/A | I39: #N/A | J39: #N/A | K39: #N/A | L39: #N/A | M39: #N/A | N39: #N/A | O39: #N/A | P39: #N/A | Q39: #N/A | R39: #N/A | S39: #N/A | T39: #N/A | U39: #N/A | V39: #N/A | W39: #N/A | X39: #N/A | Y39: #N/A | Z39: #N/A | AA39: #N/A | AB39: #N/A | AC39: #N/A | AD39: #N/A | AE39: #N/A | AF39: #N/A | AG39: #N/A | AH39: #N/A | AI39: #N/A | AJ39: #N/A | AK39: #N/A | AL39: 3259 | AM39: 2320 | AN39: 1574 | AO39: 1267 | AP39: 1330 | AQ39: 989 | AR39: 1039 | AS39: 1601 | AT39: 2840 | AU39: 3757 | AV39: 3983 | AW39: 5450 | AX39: 5630 | AY39: 5660 | AZ39: 5494 | BA39: 5630 | BB39: 5477 | BC39: 5434 | BD39: 5104 | BE39: 5163 | BF39: 5232 | BG39: 5425 | BH39: 5803 | BI39: 5803 | BJ39: 5803 | BK39: #N/A | BL39: #N/A | BM39: #N/A | BN39: #N/A | BO39: #N/A | BP39: #N/A | BQ39: #N/A | BR39: #N/A | BS39: #N/A | BT39: #N/A | BU39: #N/A | BV39: #N/A | BW39: #N/A | BX39: #N/A | BY39: #N/A | BZ39: #N/A | CA39: #N/A | CB39: #N/A | CC39: #N/A | CD39: #N/A | CE39: #N/A | CF39: #N/A | CG39: #N/A | CH39: #N/A | CI39: #N/A | CJ39: #N/A | CK39: #N/A | CL39: #N/A | CM39: #N/A | CN39: #N/A | CO39: #N/A | CP39: #N/A | CQ39: #N/A | CR39: #N/A | CS39: 5803
A40: 2009 | B40: 39814 | C40: #N/A | D40: #N/A | E40: #N/A | F40: #N/A | G40: #N/A | H40: #N/A | I40: #N/A | J40: #N/A | K40: #N/A | L40: #N/A | M40: #N/A | N40: #N/A | O40: #N/A | P40: #N/A | Q40: #N/A | R40: #N/A | S40: #N/A | T40: #N/A | U40: #N/A | V40: #N/A | W40: #N/A | X40: #N/A | Y40: #N/A | Z40: #N/A | AA40: #N/A | AB40: #N/A | AC40: #N/A | AD40: #N/A | AE40: #N/A | AF40: #N/A | AG40: #N/A | AH40: #N/A | AI40: #N/A | AJ40: #N/A | AK40: #N/A | AL40: #N/A | AM40: #N/A | AN40: 1206 | AO40: 865 | AP40: 1016 | AQ40: 887 | AR40: 939 | AS40: 1165 | AT40: 2605 | AU40: 3639 | AV40: 3894 | AW40: 5631 | AX40: 5912 | AY40: 5984 | AZ40: 5716 | BA40: 5964 | BB40: 5732 | BC40: 5750 | BD40: 5232 | BE40: 5392 | BF40: 5443 | BG40: 5870 | BH40: 7193 | BI40: 7703 | BJ40: 7612 | BK40: 7544 | BL40: 7545 | BM40: #N/A | BN40: #N/A | BO40: #N/A | BP40: #N/A | BQ40: #N/A | BR40: #N/A | BS40: #N/A | BT40: #N/A | BU40: #N/A | BV40: #N/A | BW40: #N/A | BX40: #N/A | BY40: #N/A | BZ40: #N/A | CA40: #N/A | CB40: #N/A | CC40: #N/A | CD40: #N/A | CE40: #N/A | CF40: #N/A | CG40: #N/A | CH40: #N/A | CI40: #N/A | CJ40: #N/A | CK40: #N/A | CL40: #N/A | CM40: #N/A | CN40: #N/A | CO40: #N/A | CP40: #N/A | CQ40: #N/A | CR40: #N/A | CS40: 7545
A41: 2010 | B41: 40179 | C41: #N/A | D41: #N/A | E41: #N/A | F41: #N/A | G41: #N/A | H41: #N/A | I41: #N/A | J41: #N/A | K41: #N/A | L41: #N/A | M41: #N/A | N41: #N/A | O41: #N/A | P41: #N/A | Q41: #N/A | R41: #N/A | S41: #N/A | T41: #N/A | U41: #N/A | V41: #N/A | W41: #N/A | X41: #N/A | Y41: #N/A | Z41: #N/A | AA41: #N/A | AB41: #N/A | AC41: #N/A | AD41: #N/A | AE41: #N/A | AF41: #N/A | AG41: #N/A | AH41: #N/A | AI41: #N/A | AJ41: #N/A | AK41: #N/A | AL41: #N/A | AM41: #N/A | AN41: #N/A | AO41: #N/A | AP41: 941 | AQ41: 830 | AR41: 878 | AS41: 930 | AT41: 2325 | AU41: 3476 | AV41: 3766 | AW41: 5784 | AX41: 6185 | AY41: 6295 | AZ41: 5919 | BA41: 6292 | BB41: 5967 | BC41: 6088 | BD41: 5380 | BE41: 5661 | BF41: 5698 | BG41: 6319 | BH41: 7829 | BI41: 8658 | BJ41: 8868 | BK41: 8797 | BL41: 9031 | BM41: 9018 | BN41: 9019 | BO41: #N/A | BP41: #N/A | BQ41: #N/A | BR41: #N/A | BS41: #N/A | BT41: #N/A | BU41: #N/A | BV41: #N/A | BW41: #N/A | BX41: #N/A | BY41: #N/A | BZ41: #N/A | CA41: #N/A | CB41: #N/A | CC41: #N/A | CD41: #N/A | CE41: #N/A | CF41: #N/A | CG41: #N/A | CH41: #N/A | CI41: #N/A | CJ41: #N/A | CK41: #N/A | CL41: #N/A | CM41: #N/A | CN41: #N/A | CO41: #N/A | CP41: #N/A | CQ41: #N/A | CR41: #N/A | CS41: 9019
A42: 2011 | B42: 40544 | C42: #N/A | D42: #N/A | E42: #N/A | F42: #N/A | G42: #N/A | H42: #N/A | I42: #N/A | J42: #N/A | K42: #N/A | L42: #N/A | M42: #N/A | N42: #N/A | O42: #N/A | P42: #N/A | Q42: #N/A | R42: #N/A | S42: #N/A | T42: #N/A | U42: #N/A | V42: #N/A | W42: #N/A | X42: #N/A | Y42: #N/A | Z42: #N/A | AA42: #N/A | AB42: #N/A | AC42: #N/A | AD42: #N/A | AE42: #N/A | AF42: #N/A | AG42: #N/A | AH42: #N/A | AI42: #N/A | AJ42: #N/A | AK42: #N/A | AL42: #N/A | AM42: #N/A | AN42: #N/A | AO42: #N/A | AP42: #N/A | AQ42: #N/A | AR42: 818 | AS42: 876 | AT42: 1900 | AU42: 3167 | AV42: 3501 | AW42: 5800 | AX42: 6356 | AY42: 6506 | AZ42: 6012 | BA42: 6520 | BB42: 6092 | BC42: 6324 | BD42: 5403 | BE42: 5807 | BF42: 5827 | BG42: 6662 | BH42: 8238 | BI42: 9340 | BJ42: 9782 | BK42: 9785 | BL42: 10007 | BM42: 10430 | BN42: 10164 | BO42: 10128 | BP42: 10128 | BQ42: 10128 | BR42: #N/A | BS42: #N/A | BT42: #N/A | BU42: #N/A | BV42: #N/A | BW42: #N/A | BX42: #N/A | BY42: #N/A | BZ42: #N/A | CA42: #N/A | CB42: #N/A | CC42: #N/A | CD42: #N/A | CE42: #N/A | CF42: #N/A | CG42: #N/A | CH42: #N/A | CI42: #N/A | CJ42: #N/A | CK42: #N/A | CL42: #N/A | CM42: #N/A | CN42: #N/A | CO42: #N/A | CP42: #N/A | CQ42: #N/A | CR42: #N/A | CS42: 10128
A43: 2012 | B43: 40909 | C43: #N/A | D43: #N/A | E43: #N/A | F43: #N/A | G43: #N/A | H43: #N/A | I43: #N/A | J43: #N/A | K43: #N/A | L43: #N/A | M43: #N/A | N43: #N/A | O43: #N/A | P43: #N/A | Q43: #N/A | R43: #N/A | S43: #N/A | T43: #N/A | U43: #N/A | V43: #N/A | W43: #N/A | X43: #N/A | Y43: #N/A | Z43: #N/A | AA43: #N/A | AB43: #N/A | AC43: #N/A | AD43: #N/A | AE43: #N/A | AF43: #N/A | AG43: #N/A | AH43: #N/A | AI43: #N/A | AJ43: #N/A | AK43: #N/A | AL43: #N/A | AM43: #N/A | AN43: #N/A | AO43: #N/A | AP43: #N/A | AQ43: #N/A | AR43: #N/A | AS43: #N/A | AT43: 1273 | AU43: 2658 | AV43: 3062 | AW43: 5645 | AX43: 6388 | AY43: 6588 | AZ43: 5955 | BA43: 6605 | BB43: 6064 | BC43: 6387 | BD43: 5242 | BE43: 5756 | BF43: 5751 | BG43: 6805 | BH43: 8475 | BI43: 9712 | BJ43: 10382 | BK43: 10479 | BL43: 10790 | BM43: 11598 | BN43: 11153 | BO43: 11242 | BP43: 11347 | BQ43: 11318 | BR43: 11280 | BS43: 11281 | BT43: #N/A | BU43: #N/A | BV43: #N/A | BW43: #N/A | BX43: #N/A | BY43: #N/A | BZ43: #N/A | CA43: #N/A | CB43: #N/A | CC43: #N/A | CD43: #N/A | CE43: #N/A | CF43: #N/A | CG43: #N/A | CH43: #N/A | CI43: #N/A | CJ43: #N/A | CK43: #N/A | CL43: #N/A | CM43: #N/A | CN43: #N/A | CO43: #N/A | CP43: #N/A | CQ43: #N/A | CR43: #N/A | CS43: 11281
A44: 2013 | B44: 41275 | C44: #N/A | D44: #N/A | E44: #N/A | F44: #N/A | G44: #N/A | H44: #N/A | I44: #N/A | J44: #N/A | K44: #N/A | L44: #N/A | M44: #N/A | N44: #N/A | O44: #N/A | P44: #N/A | Q44: #N/A | R44: #N/A | S44: #N/A | T44: #N/A | U44: #N/A | V44: #N/A | W44: #N/A | X44: #N/A | Y44: #N/A | Z44: #N/A | AA44: #N/A | AB44: #N/A | AC44: #N/A | AD44: #N/A | AE44: #N/A | AF44: #N/A | AG44: #N/A | AH44: #N/A | AI44: #N/A | AJ44: #N/A | AK44: #N/A | AL44: #N/A | AM44: #N/A | AN44: #N/A | AO44: #N/A | AP44: #N/A | AQ44: #N/A | AR44: #N/A | AS44: #N/A | AT44: #N/A | AU44: #N/A | AV44: 2565 | AW44: 5438 | AX44: 6409 | AY44: 6675 | AZ44: 5884 | BA44: 6691 | BB44: 6032 | BC44: 6469 | BD44: 5089 | BE44: 5730 | BF44: 5701 | BG44: 6968 | BH44: 8516 | BI44: 10016 | BJ44: 10870 | BK44: 11056 | BL44: 11422 | BM44: 12386 | BN44: 11773 | BO44: 11945 | BP44: 12068 | BQ44: 12064 | BR44: 12229 | BS44: 12036 | BT44: 11982 | BU44: 11983 | BV44: 11983 | BW44: #N/A | BX44: #N/A | BY44: #N/A | BZ44: #N/A | CA44: #N/A | CB44: #N/A | CC44: #N/A | CD44: #N/A | CE44: #N/A | CF44: #N/A | CG44: #N/A | CH44: #N/A | CI44: #N/A | CJ44: #N/A | CK44: #N/A | CL44: #N/A | CM44: #N/A | CN44: #N/A | CO44: #N/A | CP44: #N/A | CQ44: #N/A | CR44: #N/A | CS44: 11983
A45: 2014 | B45: 41640 | C45: #N/A | D45: #N/A | E45: #N/A | F45: #N/A | G45: #N/A | H45: #N/A | I45: #N/A | J45: #N/A | K45: #N/A | L45: #N/A | M45: #N/A | N45: #N/A | O45: #N/A | P45: #N/A | Q45: #N/A | R45: #N/A | S45: #N/A | T45: #N/A | U45: #N/A | V45: #N/A | W45: #N/A | X45: #N/A | Y45: #N/A | Z45: #N/A | AA45: #N/A | AB45: #N/A | AC45: #N/A | AD45: #N/A | AE45: #N/A | AF45: #N/A | AG45: #N/A | AH45: #N/A | AI45: #N/A | AJ45: #N/A | AK45: #N/A | AL45: #N/A | AM45: #N/A | AN45: #N/A | AO45: #N/A | AP45: #N/A | AQ45: #N/A | AR45: #N/A | AS45: #N/A | AT45: #N/A | AU45: #N/A | AV45: #N/A | AW45: #N/A | AX45: 6399 | AY45: 6753 | AZ45: 5784 | BA45: 6762 | BB45: 5981 | BC45: 6539 | BD45: 4912 | BE45: 5674 | BF45: 5613 | BG45: 7155 | BH45: 8734 | BI45: 10372 | BJ45: 11439 | BK45: 11556 | BL45: 11950 | BM45: 12996 | BN45: 12148 | BO45: 12401 | BP45: 12556 | BQ45: 12545 | BR45: 12937 | BS45: 12685 | BT45: 12717 | BU45: 12740 | BV45: 12797 | BW45: 12780 | BX45: 12780 | BY45: 12780 | BZ45: #N/A | CA45: #N/A | CB45: #N/A | CC45: #N/A | CD45: #N/A | CE45: #N/A | CF45: #N/A | CG45: #N/A | CH45: #N/A | CI45: #N/A | CJ45: #N/A | CK45: #N/A | CL45: #N/A | CM45: #N/A | CN45: #N/A | CO45: #N/A | CP45: #N/A | CQ45: #N/A | CR45: #N/A | CS45: 12780
A46: 2015 | B46: 42005 | C46: #N/A | D46: #N/A | E46: #N/A | F46: #N/A | G46: #N/A | H46: #N/A | I46: #N/A | J46: #N/A | K46: #N/A | L46: #N/A | M46: #N/A | N46: #N/A | O46: #N/A | P46: #N/A | Q46: #N/A | R46: #N/A | S46: #N/A | T46: #N/A | U46: #N/A | V46: #N/A | W46: #N/A | X46: #N/A | Y46: #N/A | Z46: #N/A | AA46: #N/A | AB46: #N/A | AC46: #N/A | AD46: #N/A | AE46: #N/A | AF46: #N/A | AG46: #N/A | AH46: #N/A | AI46: #N/A | AJ46: #N/A | AK46: #N/A | AL46: #N/A | AM46: #N/A | AN46: #N/A | AO46: #N/A | AP46: #N/A | AQ46: #N/A | AR46: #N/A | AS46: #N/A | AT46: #N/A | AU46: #N/A | AV46: #N/A | AW46: #N/A | AX46: #N/A | AY46: #N/A | AZ46: 5658 | BA46: 6820 | BB46: 5912 | BC46: 6600 | BD46: 4709 | BE46: 5595 | BF46: 5503 | BG46: 7331 | BH46: 8925 | BI46: 10684 | BJ46: 11986 | BK46: 12055 | BL46: 12544 | BM46: 13625 | BN46: 12463 | BO46: 12783 | BP46: 12909 | BQ46: 12861 | BR46: 13462 | BS46: 13156 | BT46: 13263 | BU46: 13285 | BV46: 13305 | BW46: 13366 | BX46: 13366 | BY46: 13175 | BZ46: 13117 | CA46: 13117 | CB46: 13117 | CC46: #N/A | CD46: #N/A | CE46: #N/A | CF46: #N/A | CG46: #N/A | CH46: #N/A | CI46: #N/A | CJ46: #N/A | CK46: #N/A | CL46: #N/A | CM46: #N/A | CN46: #N/A | CO46: #N/A | CP46: #N/A | CQ46: #N/A | CR46: #N/A | CS46: 13117
A47: 2016 | B47: 42370 | C47: #N/A | D47: #N/A | E47: #N/A | F47: #N/A | G47: #N/A | H47: #N/A | I47: #N/A | J47: #N/A | K47: #N/A | L47: #N/A | M47: #N/A | N47: #N/A | O47: #N/A | P47: #N/A | Q47: #N/A | R47: #N/A | S47: #N/A | T47: #N/A | U47: #N/A | V47: #N/A | W47: #N/A | X47: #N/A | Y47: #N/A | Z47: #N/A | AA47: #N/A | AB47: #N/A | AC47: #N/A | AD47: #N/A | AE47: #N/A | AF47: #N/A | AG47: #N/A | AH47: #N/A | AI47: #N/A | AJ47: #N/A | AK47: #N/A | AL47: #N/A | AM47: #N/A | AN47: #N/A | AO47: #N/A | AP47: #N/A | AQ47: #N/A | AR47: #N/A | AS47: #N/A | AT47: #N/A | AU47: #N/A | AV47: #N/A | AW47: #N/A | AX47: #N/A | AY47: #N/A | AZ47: #N/A | BA47: #N/A | BB47: 5848 | BC47: 6696 | BD47: 4521 | BE47: 5543 | BF47: 5414 | BG47: 7553 | BH47: 9149 | BI47: 11034 | BJ47: 12581 | BK47: 12595 | BL47: 13214 | BM47: 14358 | BN47: 12840 | BO47: 13188 | BP47: 13263 | BQ47: 13144 | BR47: 14025 | BS47: 13666 | BT47: 13861 | BU47: 13884 | BV47: 13927 | BW47: 13897 | BX47: 13897 | BY47: 13821 | BZ47: 13978 | CA47: 13951 | CB47: 14073 | CC47: 14168 | CD47: 14168 | CE47: #N/A | CF47: #N/A | CG47: #N/A | CH47: #N/A | CI47: #N/A | CJ47: #N/A | CK47: #N/A | CL47: #N/A | CM47: #N/A | CN47: #N/A | CO47: #N/A | CP47: #N/A | CQ47: #N/A | CR47: #N/A | CS47: 14168
A48: 2017 | B48: 42736 | C48: #N/A | D48: #N/A | E48: #N/A | F48: #N/A | G48: #N/A | H48: #N/A | I48: #N/A | J48: #N/A | K48: #N/A | L48: #N/A | M48: #N/A | N48: #N/A | O48: #N/A | P48: #N/A | Q48: #N/A | R48: #N/A | S48: #N/A | T48: #N/A | U48: #N/A | V48: #N/A | W48: #N/A | X48: #N/A | Y48: #N/A | Z48: #N/A | AA48: #N/A | AB48: #N/A | AC48: #N/A | AD48: #N/A | AE48: #N/A | AF48: #N/A | AG48: #N/A | AH48: #N/A | AI48: #N/A | AJ48: #N/A | AK48: #N/A | AL48: #N/A | AM48: #N/A | AN48: #N/A | AO48: #N/A | AP48: #N/A | AQ48: #N/A | AR48: #N/A | AS48: #N/A | AT48: #N/A | AU48: #N/A | AV48: #N/A | AW48: #N/A | AX48: #N/A | AY48: #N/A | AZ48: #N/A | BA48: #N/A | BB48: #N/A | BC48: #N/A | BD48: 4274 | BE48: 5439 | BF48: 5269 | BG48: 7742 | BH48: 9335 | BI48: 11365 | BJ48: 13174 | BK48: 13133 | BL48: 13885 | BM48: 15064 | BN48: 13169 | BO48: 13509 | BP48: 13560 | BQ48: 13371 | BR48: 14642 | BS48: 14223 | BT48: 14507 | BU48: 14523 | BV48: 14521 | BW48: 14428 | BX48: 14428 | BY48: 14338 | BZ48: 14613 | CA48: 14572 | CB48: 14743 | CC48: 14838 | CD48: 14656 | CE48: 14665 | CF48: #N/A | CG48: #N/A | CH48: #N/A | CI48: #N/A | CJ48: #N/A | CK48: #N/A | CL48: #N/A | CM48: #N/A | CN48: #N/A | CO48: #N/A | CP48: #N/A | CQ48: #N/A | CR48: #N/A | CS48: 14665
A49: 2018 | B49: 43101 | C49: #N/A | D49: #N/A | E49: #N/A | F49: #N/A | G49: #N/A | H49: #N/A | I49: #N/A | J49: #N/A | K49: #N/A | L49: #N/A | M49: #N/A | N49: #N/A | O49: #N/A | P49: #N/A | Q49: #N/A | R49: #N/A | S49: #N/A | T49: #N/A | U49: #N/A | V49: #N/A | W49: #N/A | X49: #N/A | Y49: #N/A | Z49: #N/A | AA49: #N/A | AB49: #N/A | AC49: #N/A | AD49: #N/A | AE49: #N/A | AF49: #N/A | AG49: #N/A | AH49: #N/A | AI49: #N/A | AJ49: #N/A | AK49: #N/A | AL49: #N/A | AM49: #N/A | AN49: #N/A | AO49: #N/A | AP49: #N/A | AQ49: #N/A | AR49: #N/A | AS49: #N/A | AT49: #N/A | AU49: #N/A | AV49: #N/A | AW49: #N/A | AX49: #N/A | AY49: #N/A | AZ49: #N/A | BA49: #N/A | BB49: #N/A | BC49: #N/A | BD49: #N/A | BE49: #N/A | BF49: 5050 | BG49: 7890 | BH49: 9127 | BI49: 11334 | BJ49: 13611 | BK49: 13678 | BL49: 14546 | BM49: 15767 | BN49: 13473 | BO49: 13801 | BP49: 13820 | BQ49: 13536 | BR49: 15316 | BS49: 14827 | BT49: 15218 | BU49: 15202 | BV49: 15135 | BW49: 14983 | BX49: 14983 | BY49: 14864 | BZ49: 15244 | CA49: 15177 | CB49: 15325 | CC49: 15416 | CD49: 15537 | CE49: 15688 | CF49: 15751 | CG49: 15750 | CH49: 15750 | CI49: #N/A | CJ49: #N/A | CK49: #N/A | CL49: #N/A | CM49: #N/A | CN49: #N/A | CO49: #N/A | CP49: #N/A | CQ49: #N/A | CR49: #N/A | CS49: 15750
A50: 2019 | B50: 43466 | C50: #N/A | D50: #N/A | E50: #N/A | F50: #N/A | G50: #N/A | H50: #N/A | I50: #N/A | J50: #N/A | K50: #N/A | L50: #N/A | M50: #N/A | N50: #N/A | O50: #N/A | P50: #N/A | Q50: #N/A | R50: #N/A | S50: #N/A | T50: #N/A | U50: #N/A | V50: #N/A | W50: #N/A | X50: #N/A | Y50: #N/A | Z50: #N/A | AA50: #N/A | AB50: #N/A | AC50: #N/A | AD50: #N/A | AE50: #N/A | AF50: #N/A | AG50: #N/A | AH50: #N/A | AI50: #N/A | AJ50: #N/A | AK50: #N/A | AL50: #N/A | AM50: #N/A | AN50: #N/A | AO50: #N/A | AP50: #N/A | AQ50: #N/A | AR50: #N/A | AS50: #N/A | AT50: #N/A | AU50: #N/A | AV50: #N/A | AW50: #N/A | AX50: #N/A | AY50: #N/A | AZ50: #N/A | BA50: #N/A | BB50: #N/A | BC50: #N/A | BD50: #N/A | BE50: #N/A | BF50: #N/A | BG50: #N/A | BH50: 9344 | BI50: 11753 | BJ50: 14324 | BK50: 14329 | BL50: 15281 | BM50: 16557 | BN50: 13820 | BO50: 14148 | BP50: 14123 | BQ50: 13746 | BR50: 16092 | BS50: 15537 | BT50: 16028 | BU50: 15977 | BV50: 15850 | BW50: 15654 | BX50: 15654 | BY50: 15528 | BZ50: 16033 | CA50: 15934 | CB50: 16001 | CC50: 16092 | CD50: 16282 | CE50: 16762 | CF50: 16636 | CG50: 16621 | CH50: 16685 | CI50: 16803 | CJ50: 16801 | CK50: 16801 | CL50: #N/A | CM50: #N/A | CN50: #N/A | CO50: #N/A | CP50: #N/A | CQ50: #N/A | CR50: #N/A | CS50: 16801
A51: 2020 | B51: 43831 | C51: #N/A | D51: #N/A | E51: #N/A | F51: #N/A | G51: #N/A | H51: #N/A | I51: #N/A | J51: #N/A | K51: #N/A | L51: #N/A | M51: #N/A | N51: #N/A | O51: #N/A | P51: #N/A | Q51: #N/A | R51: #N/A | S51: #N/A | T51: #N/A | U51: #N/A | V51: #N/A | W51: #N/A | X51: #N/A | Y51: #N/A | Z51: #N/A | AA51: #N/A | AB51: #N/A | AC51: #N/A | AD51: #N/A | AE51: #N/A | AF51: #N/A | AG51: #N/A | AH51: #N/A | AI51: #N/A | AJ51: #N/A | AK51: #N/A | AL51: #N/A | AM51: #N/A | AN51: #N/A | AO51: #N/A | AP51: #N/A | AQ51: #N/A | AR51: #N/A | AS51: #N/A | AT51: #N/A | AU51: #N/A | AV51: #N/A | AW51: #N/A | AX51: #N/A | AY51: #N/A | AZ51: #N/A | BA51: #N/A | BB51: #N/A | BC51: #N/A | BD51: #N/A | BE51: #N/A | BF51: #N/A | BG51: #N/A | BH51: #N/A | BI51: #N/A | BJ51: #N/A | BK51: 15027 | BL51: 16073 | BM51: 17392 | BN51: 14181 | BO51: 14512 | BP51: 14432 | BQ51: 13964 | BR51: 16957 | BS51: 16330 | BT51: 16925 | BU51: 16835 | BV51: 16642 | BW51: 16409 | BX51: 16409 | BY51: 16277 | BZ51: 16886 | CA51: 16771 | CB51: 16758 | CC51: 16845 | CD51: 17108 | CE51: 17827 | CF51: 17601 | CG51: 17576 | CH51: 17755 | CI51: 17855 | CJ51: 17835 | CK51: 20270 | CL51: 21019 | CM51: 21017 | CN51: #N/A | CO51: #N/A | CP51: #N/A | CQ51: #N/A | CR51: #N/A | CS51: 21017
A52: 2021 | B52: 44197 | C52: #N/A | D52: #N/A | E52: #N/A | F52: #N/A | G52: #N/A | H52: #N/A | I52: #N/A | J52: #N/A | K52: #N/A | L52: #N/A | M52: #N/A | N52: #N/A | O52: #N/A | P52: #N/A | Q52: #N/A | R52: #N/A | S52: #N/A | T52: #N/A | U52: #N/A | V52: #N/A | W52: #N/A | X52: #N/A | Y52: #N/A | Z52: #N/A | AA52: #N/A | AB52: #N/A | AC52: #N/A | AD52: #N/A | AE52: #N/A | AF52: #N/A | AG52: #N/A | AH52: #N/A | AI52: #N/A | AJ52: #N/A | AK52: #N/A | AL52: #N/A | AM52: #N/A | AN52: #N/A | AO52: #N/A | AP52: #N/A | AQ52: #N/A | AR52: #N/A | AS52: #N/A | AT52: #N/A | AU52: #N/A | AV52: #N/A | AW52: #N/A | AX52: #N/A | AY52: #N/A | AZ52: #N/A | BA52: #N/A | BB52: #N/A | BC52: #N/A | BD52: #N/A | BE52: #N/A | BF52: #N/A | BG52: #N/A | BH52: #N/A | BI52: #N/A | BJ52: #N/A | BK52: #N/A | BL52: #N/A | BM52: 18253 | BN52: 14541 | BO52: 14872 | BP52: 14741 | BQ52: 14181 | BR52: 17876 | BS52: 17168 | BT52: 17899 | BU52: 17769 | BV52: 17518 | BW52: 17226 | BX52: 17226 | BY52: 17102 | BZ52: 17813 | CA52: 17692 | CB52: 17597 | CC52: 17704 | CD52: 18037 | CE52: 18998 | CF52: 18626 | CG52: 18589 | CH52: 18841 | CI52: 18886 | CJ52: 18816 | CK52: 21931 | CL52: 22461 | CM52: 23012 | CN52: 22284 | CO52: #N/A | CP52: #N/A | CQ52: #N/A | CR52: #N/A | CS52: 22283
A53: 2022 | B53: 44562 | C53: #N/A | D53: #N/A | E53: #N/A | F53: #N/A | G53: #N/A | H53: #N/A | I53: #N/A | J53: #N/A | K53: #N/A | L53: #N/A | M53: #N/A | N53: #N/A | O53: #N/A | P53: #N/A | Q53: #N/A | R53: #N/A | S53: #N/A | T53: #N/A | U53: #N/A | V53: #N/A | W53: #N/A | X53: #N/A | Y53: #N/A | Z53: #N/A | AA53: #N/A | AB53: #N/A | AC53: #N/A | AD53: #N/A | AE53: #N/A | AF53: #N/A | AG53: #N/A | AH53: #N/A | AI53: #N/A | AJ53: #N/A | AK53: #N/A | AL53: #N/A | AM53: #N/A | AN53: #N/A | AO53: #N/A | AP53: #N/A | AQ53: #N/A | AR53: #N/A | AS53: #N/A | AT53: #N/A | AU53: #N/A | AV53: #N/A | AW53: #N/A | AX53: #N/A | AY53: #N/A | AZ53: #N/A | BA53: #N/A | BB53: #N/A | BC53: #N/A | BD53: #N/A | BE53: #N/A | BF53: #N/A | BG53: #N/A | BH53: #N/A | BI53: #N/A | BJ53: #N/A | BK53: #N/A | BL53: #N/A | BM53: #N/A | BN53: #N/A | BO53: 15291 | BP53: 15115 | BQ53: 14464 | BR53: 18902 | BS53: 18118 | BT53: 19001 | BU53: 18823 | BV53: 18520 | BW53: 18179 | BX53: 18179 | BY53: 18044 | BZ53: 18891 | CA53: 18766 | CB53: 18584 | CC53: 18721 | CD53: 19109 | CE53: 20319 | CF53: 19795 | CG53: 19748 | CH53: 20042 | CI53: 20066 | CJ53: 19996 | CK53: 23320 | CL53: 23541 | CM53: 24392 | CN53: 24173 | CO53: 24257 | CP53: 24252 | CQ53: #N/A | CR53: #N/A | CS53: 24252
A54: 2023 | B54: 44927 | C54: #N/A | D54: #N/A | E54: #N/A | F54: #N/A | G54: #N/A | H54: #N/A | I54: #N/A | J54: #N/A | K54: #N/A | L54: #N/A | M54: #N/A | N54: #N/A | O54: #N/A | P54: #N/A | Q54: #N/A | R54: #N/A | S54: #N/A | T54: #N/A | U54: #N/A | V54: #N/A | W54: #N/A | X54: #N/A | Y54: #N/A | Z54: #N/A | AA54: #N/A | AB54: #N/A | AC54: #N/A | AD54: #N/A | AE54: #N/A | AF54: #N/A | AG54: #N/A | AH54: #N/A | AI54: #N/A | AJ54: #N/A | AK54: #N/A | AL54: #N/A | AM54: #N/A | AN54: #N/A | AO54: #N/A | AP54: #N/A | AQ54: #N/A | AR54: #N/A | AS54: #N/A | AT54: #N/A | AU54: #N/A | AV54: #N/A | AW54: #N/A | AX54: #N/A | AY54: #N/A | AZ54: #N/A | BA54: #N/A | BB54: #N/A | BC54: #N/A | BD54: #N/A | BE54: #N/A | BF54: #N/A | BG54: #N/A | BH54: #N/A | BI54: #N/A | BJ54: #N/A | BK54: #N/A | BL54: #N/A | BM54: #N/A | BN54: #N/A | BO54: #N/A | BP54: #N/A | BQ54: #N/A | BR54: 19944 | BS54: 19070 | BT54: 20115 | BU54: 19885 | BV54: 19534 | BW54: 19138 | BX54: 19138 | BY54: 18993 | BZ54: 20003 | CA54: 19880 | CB54: 19608 | CC54: 19776 | CD54: 20212 | CE54: 21638 | CF54: 20976 | CG54: 20910 | CH54: 21264 | CI54: 21248 | CJ54: 21144 | CK54: 24520 | CL54: 24547 | CM54: 25156 | CN54: 25193 | CO54: 25716 | CP54: 25767 | CQ54: 26240 | CR54: 26236 | CS54: 26236
A55: 2024 | B55: 45292 | C55: #N/A | D55: #N/A | E55: #N/A | F55: #N/A | G55: #N/A | H55: #N/A | I55: #N/A | J55: #N/A | K55: #N/A | L55: #N/A | M55: #N/A | N55: #N/A | O55: #N/A | P55: #N/A | Q55: #N/A | R55: #N/A | S55: #N/A | T55: #N/A | U55: #N/A | V55: #N/A | W55: #N/A | X55: #N/A | Y55: #N/A | Z55: #N/A | AA55: #N/A | AB55: #N/A | AC55: #N/A | AD55: #N/A | AE55: #N/A | AF55: #N/A | AG55: #N/A | AH55: #N/A | AI55: #N/A | AJ55: #N/A | AK55: #N/A | AL55: #N/A | AM55: #N/A | AN55: #N/A | AO55: #N/A | AP55: #N/A | AQ55: #N/A | AR55: #N/A | AS55: #N/A | AT55: #N/A | AU55: #N/A | AV55: #N/A | AW55: #N/A | AX55: #N/A | AY55: #N/A | AZ55: #N/A | BA55: #N/A | BB55: #N/A | BC55: #N/A | BD55: #N/A | BE55: #N/A | BF55: #N/A | BG55: #N/A | BH55: #N/A | BI55: #N/A | BJ55: #N/A | BK55: #N/A | BL55: #N/A | BM55: #N/A | BN55: #N/A | BO55: #N/A | BP55: #N/A | BQ55: #N/A | BR55: #N/A | BS55: #N/A | BT55: 21260 | BU55: 20947 | BV55: 20554 | BW55: 20089 | BX55: 20089 | BY55: 19933 | BZ55: 21129 | CA55: 21012 | CB55: 20649 | CC55: 20858 | CD55: 21342 | CE55: 22932 | CF55: 22112 | CG55: 22021 | CH55: 22457 | CI55: 22453 | CJ55: 22339 | CK55: 25657 | CL55: 25488 | CM55: 25959 | CN55: 26217 | CO55: 27370 | CP55: 27388 | CQ55: 27897 | CR55: 28178 | CS55: 28199
A56: 2025 | B56: 45658 | C56: #N/A | D56: #N/A | E56: #N/A | F56: #N/A | G56: #N/A | H56: #N/A | I56: #N/A | J56: #N/A | K56: #N/A | L56: #N/A | M56: #N/A | N56: #N/A | O56: #N/A | P56: #N/A | Q56: #N/A | R56: #N/A | S56: #N/A | T56: #N/A | U56: #N/A | V56: #N/A | W56: #N/A | X56: #N/A | Y56: #N/A | Z56: #N/A | AA56: #N/A | AB56: #N/A | AC56: #N/A | AD56: #N/A | AE56: #N/A | AF56: #N/A | AG56: #N/A | AH56: #N/A | AI56: #N/A | AJ56: #N/A | AK56: #N/A | AL56: #N/A | AM56: #N/A | AN56: #N/A | AO56: #N/A | AP56: #N/A | AQ56: #N/A | AR56: #N/A | AS56: #N/A | AT56: #N/A | AU56: #N/A | AV56: #N/A | AW56: #N/A | AX56: #N/A | AY56: #N/A | AZ56: #N/A | BA56: #N/A | BB56: #N/A | BC56: #N/A | BD56: #N/A | BE56: #N/A | BF56: #N/A | BG56: #N/A | BH56: #N/A | BI56: #N/A | BJ56: #N/A | BK56: #N/A | BL56: #N/A | BM56: #N/A | BN56: #N/A | BO56: #N/A | BP56: #N/A | BQ56: #N/A | BR56: #N/A | BS56: #N/A | BT56: #N/A | BU56: #N/A | BV56: #N/A | BW56: 21182 | BX56: 21182 | BY56: 21001 | BZ56: 22399 | CA56: 22280 | CB56: 21824 | CC56: 22078 | CD56: 22613 | CE56: 24338 | CF56: 23372 | CG56: 23253 | CH56: 23784 | CI56: 23827 | CJ56: 23694 | CK56: 26818 | CL56: 26559 | CM56: 26967 | CN56: 27561 | CO56: 29214 | CP56: 29246 | CQ56: 29749 | CR56: 30188 | CS56: 30103
A57: 2026 | B57: 46023 | C57: #N/A | D57: #N/A | E57: #N/A | F57: #N/A | G57: #N/A | H57: #N/A | I57: #N/A | J57: #N/A | K57: #N/A | L57: #N/A | M57: #N/A | N57: #N/A | O57: #N/A | P57: #N/A | Q57: #N/A | R57: #N/A | S57: #N/A | T57: #N/A | U57: #N/A | V57: #N/A | W57: #N/A | X57: #N/A | Y57: #N/A | Z57: #N/A | AA57: #N/A | AB57: #N/A | AC57: #N/A | AD57: #N/A | AE57: #N/A | AF57: #N/A | AG57: #N/A | AH57: #N/A | AI57: #N/A | AJ57: #N/A | AK57: #N/A | AL57: #N/A | AM57: #N/A | AN57: #N/A | AO57: #N/A | AP57: #N/A | AQ57: #N/A | AR57: #N/A | AS57: #N/A | AT57: #N/A | AU57: #N/A | AV57: #N/A | AW57: #N/A | AX57: #N/A | AY57: #N/A | AZ57: #N/A | BA57: #N/A | BB57: #N/A | BC57: #N/A | BD57: #N/A | BE57: #N/A | BF57: #N/A | BG57: #N/A | BH57: #N/A | BI57: #N/A | BJ57: #N/A | BK57: #N/A | BL57: #N/A | BM57: #N/A | BN57: #N/A | BO57: #N/A | BP57: #N/A | BQ57: #N/A | BR57: #N/A | BS57: #N/A | BT57: #N/A | BU57: #N/A | BV57: #N/A | BW57: #N/A | BX57: #N/A | BY57: #N/A | BZ57: 23817 | CA57: 23672 | CB57: 23118 | CC57: 23430 | CD57: 24014 | CE57: 25715 | CF57: 24625 | CG57: 24476 | CH57: 25102 | CI57: 25196 | CJ57: 25053 | CK57: 27888 | CL57: 27596 | CM57: 28062 | CN57: 28925 | CO57: 30927 | CP57: 31054 | CQ57: 31515 | CR57: 32118 | CS57: 31883
A58: 2027 | B58: 46388 | C58: #N/A | D58: #N/A | E58: #N/A | F58: #N/A | G58: #N/A | H58: #N/A | I58: #N/A | J58: #N/A | K58: #N/A | L58: #N/A | M58: #N/A | N58: #N/A | O58: #N/A | P58: #N/A | Q58: #N/A | R58: #N/A | S58: #N/A | T58: #N/A | U58: #N/A | V58: #N/A | W58: #N/A | X58: #N/A | Y58: #N/A | Z58: #N/A | AA58: #N/A | AB58: #N/A | AC58: #N/A | AD58: #N/A | AE58: #N/A | AF58: #N/A | AG58: #N/A | AH58: #N/A | AI58: #N/A | AJ58: #N/A | AK58: #N/A | AL58: #N/A | AM58: #N/A | AN58: #N/A | AO58: #N/A | AP58: #N/A | AQ58: #N/A | AR58: #N/A | AS58: #N/A | AT58: #N/A | AU58: #N/A | AV58: #N/A | AW58: #N/A | AX58: #N/A | AY58: #N/A | AZ58: #N/A | BA58: #N/A | BB58: #N/A | BC58: #N/A | BD58: #N/A | BE58: #N/A | BF58: #N/A | BG58: #N/A | BH58: #N/A | BI58: #N/A | BJ58: #N/A | BK58: #N/A | BL58: #N/A | BM58: #N/A | BN58: #N/A | BO58: #N/A | BP58: #N/A | BQ58: #N/A | BR58: #N/A | BS58: #N/A | BT58: #N/A | BU58: #N/A | BV58: #N/A | BW58: #N/A | BX58: #N/A | BY58: #N/A | BZ58: #N/A | CA58: #N/A | CB58: #N/A | CC58: 24893 | CD58: 25524 | CE58: 27087 | CF58: 25866 | CG58: 25684 | CH58: 26407 | CI58: 26545 | CJ58: 26398 | CK58: 28993 | CL58: 28702 | CM58: 29185 | CN58: 30326 | CO58: 32645 | CP58: 32866 | CQ58: 33233 | CR58: 33949 | CS58: 33636
A59: 2028 | B59: 46753 | C59: #N/A | D59: #N/A | E59: #N/A | F59: #N/A | G59: #N/A | H59: #N/A | I59: #N/A | J59: #N/A | K59: #N/A | L59: #N/A | M59: #N/A | N59: #N/A | O59: #N/A | P59: #N/A | Q59: #N/A | R59: #N/A | S59: #N/A | T59: #N/A | U59: #N/A | V59: #N/A | W59: #N/A | X59: #N/A | Y59: #N/A | Z59: #N/A | AA59: #N/A | AB59: #N/A | AC59: #N/A | AD59: #N/A | AE59: #N/A | AF59: #N/A | AG59: #N/A | AH59: #N/A | AI59: #N/A | AJ59: #N/A | AK59: #N/A | AL59: #N/A | AM59: #N/A | AN59: #N/A | AO59: #N/A | AP59: #N/A | AQ59: #N/A | AR59: #N/A | AS59: #N/A | AT59: #N/A | AU59: #N/A | AV59: #N/A | AW59: #N/A | AX59: #N/A | AY59: #N/A | AZ59: #N/A | BA59: #N/A | BB59: #N/A | BC59: #N/A | BD59: #N/A | BE59: #N/A | BF59: #N/A | BG59: #N/A | BH59: #N/A | BI59: #N/A | BJ59: #N/A | BK59: #N/A | BL59: #N/A | BM59: #N/A | BN59: #N/A | BO59: #N/A | BP59: #N/A | BQ59: #N/A | BR59: #N/A | BS59: #N/A | BT59: #N/A | BU59: #N/A | BV59: #N/A | BW59: #N/A | BX59: #N/A | BY59: #N/A | BZ59: #N/A | CA59: #N/A | CB59: #N/A | CC59: #N/A | CD59: #N/A | CE59: 28671 | CF59: 27338 | CG59: 27116 | CH59: 27917 | CI59: 28152 | CJ59: 27970 | CK59: 30396 | CL59: 30162 | CM59: 30733 | CN59: 32105 | CO59: 34642 | CP59: 34895 | CQ59: 35141 | CR59: 35960 | CS59: 35601
A60: 2029 | B60: 47119 | C60: #N/A | D60: #N/A | E60: #N/A | F60: #N/A | G60: #N/A | H60: #N/A | I60: #N/A | J60: #N/A | K60: #N/A | L60: #N/A | M60: #N/A | N60: #N/A | O60: #N/A | P60: #N/A | Q60: #N/A | R60: #N/A | S60: #N/A | T60: #N/A | U60: #N/A | V60: #N/A | W60: #N/A | X60: #N/A | Y60: #N/A | Z60: #N/A | AA60: #N/A | AB60: #N/A | AC60: #N/A | AD60: #N/A | AE60: #N/A | AF60: #N/A | AG60: #N/A | AH60: #N/A | AI60: #N/A | AJ60: #N/A | AK60: #N/A | AL60: #N/A | AM60: #N/A | AN60: #N/A | AO60: #N/A | AP60: #N/A | AQ60: #N/A | AR60: #N/A | AS60: #N/A | AT60: #N/A | AU60: #N/A | AV60: #N/A | AW60: #N/A | AX60: #N/A | AY60: #N/A | AZ60: #N/A | BA60: #N/A | BB60: #N/A | BC60: #N/A | BD60: #N/A | BE60: #N/A | BF60: #N/A | BG60: #N/A | BH60: #N/A | BI60: #N/A | BJ60: #N/A | BK60: #N/A | BL60: #N/A | BM60: #N/A | BN60: #N/A | BO60: #N/A | BP60: #N/A | BQ60: #N/A | BR60: #N/A | BS60: #N/A | BT60: #N/A | BU60: #N/A | BV60: #N/A | BW60: #N/A | BX60: #N/A | BY60: #N/A | BZ60: #N/A | CA60: #N/A | CB60: #N/A | CC60: #N/A | CD60: #N/A | CE60: #N/A | CF60: 28739 | CG60: 28455 | CH60: 29322 | CI60: 29667 | CJ60: 29479 | CK60: 31773 | CL60: 31593 | CM60: 32119 | CN60: 33760 | CO60: 36406 | CP60: 36830 | CQ60: 36916 | CR60: 37965 | CS60: 37581
A61: 2030 | B61: 47484 | C61: #N/A | D61: #N/A | E61: #N/A | F61: #N/A | G61: #N/A | H61: #N/A | I61: #N/A | J61: #N/A | K61: #N/A | L61: #N/A | M61: #N/A | N61: #N/A | O61: #N/A | P61: #N/A | Q61: #N/A | R61: #N/A | S61: #N/A | T61: #N/A | U61: #N/A | V61: #N/A | W61: #N/A | X61: #N/A | Y61: #N/A | Z61: #N/A | AA61: #N/A | AB61: #N/A | AC61: #N/A | AD61: #N/A | AE61: #N/A | AF61: #N/A | AG61: #N/A | AH61: #N/A | AI61: #N/A | AJ61: #N/A | AK61: #N/A | AL61: #N/A | AM61: #N/A | AN61: #N/A | AO61: #N/A | AP61: #N/A | AQ61: #N/A | AR61: #N/A | AS61: #N/A | AT61: #N/A | AU61: #N/A | AV61: #N/A | AW61: #N/A | AX61: #N/A | AY61: #N/A | AZ61: #N/A | BA61: #N/A | BB61: #N/A | BC61: #N/A | BD61: #N/A | BE61: #N/A | BF61: #N/A | BG61: #N/A | BH61: #N/A | BI61: #N/A | BJ61: #N/A | BK61: #N/A | BL61: #N/A | BM61: #N/A | BN61: #N/A | BO61: #N/A | BP61: #N/A | BQ61: #N/A | BR61: #N/A | BS61: #N/A | BT61: #N/A | BU61: #N/A | BV61: #N/A | BW61: #N/A | BX61: #N/A | BY61: #N/A | BZ61: #N/A | CA61: #N/A | CB61: #N/A | CC61: #N/A | CD61: #N/A | CE61: #N/A | CF61: #N/A | CG61: #N/A | CH61: #N/A | CI61: 31447 | CJ61: 31292 | CK61: 33457 | CL61: 33331 | CM61: 33913 | CN61: 35808 | CO61: 38604 | CP61: 39015 | CQ61: 38868 | CR61: 40198 | CS61: 39748
A62: 2031 | B62: 47849 | C62: #N/A | D62: #N/A | E62: #N/A | F62: #N/A | G62: #N/A | H62: #N/A | I62: #N/A | J62: #N/A | K62: #N/A | L62: #N/A | M62: #N/A | N62: #N/A | O62: #N/A | P62: #N/A | Q62: #N/A | R62: #N/A | S62: #N/A | T62: #N/A | U62: #N/A | V62: #N/A | W62: #N/A | X62: #N/A | Y62: #N/A | Z62: #N/A | AA62: #N/A | AB62: #N/A | AC62: #N/A | AD62: #N/A | AE62: #N/A | AF62: #N/A | AG62: #N/A | AH62: #N/A | AI62: #N/A | AJ62: #N/A | AK62: #N/A | AL62: #N/A | AM62: #N/A | AN62: #N/A | AO62: #N/A | AP62: #N/A | AQ62: #N/A | AR62: #N/A | AS62: #N/A | AT62: #N/A | AU62: #N/A | AV62: #N/A | AW62: #N/A | AX62: #N/A | AY62: #N/A | AZ62: #N/A | BA62: #N/A | BB62: #N/A | BC62: #N/A | BD62: #N/A | BE62: #N/A | BF62: #N/A | BG62: #N/A | BH62: #N/A | BI62: #N/A | BJ62: #N/A | BK62: #N/A | BL62: #N/A | BM62: #N/A | BN62: #N/A | BO62: #N/A | BP62: #N/A | BQ62: #N/A | BR62: #N/A | BS62: #N/A | BT62: #N/A | BU62: #N/A | BV62: #N/A | BW62: #N/A | BX62: #N/A | BY62: #N/A | BZ62: #N/A | CA62: #N/A | CB62: #N/A | CC62: #N/A | CD62: #N/A | CE62: #N/A | CF62: #N/A | CG62: #N/A | CH62: #N/A | CI62: #N/A | CJ62: #N/A | CK62: #N/A | CL62: 35304 | CM62: 35827 | CN62: 37949 | CO62: 40945 | CP62: 41347 | CQ62: 40945 | CR62: 42508 | CS62: 41992
A63: 2032 | B63: 48214 | C63: #N/A | D63: #N/A | E63: #N/A | F63: #N/A | G63: #N/A | H63: #N/A | I63: #N/A | J63: #N/A | K63: #N/A | L63: #N/A | M63: #N/A | N63: #N/A | O63: #N/A | P63: #N/A | Q63: #N/A | R63: #N/A | S63: #N/A | T63: #N/A | U63: #N/A | V63: #N/A | W63: #N/A | X63: #N/A | Y63: #N/A | Z63: #N/A | AA63: #N/A | AB63: #N/A | AC63: #N/A | AD63: #N/A | AE63: #N/A | AF63: #N/A | AG63: #N/A | AH63: #N/A | AI63: #N/A | AJ63: #N/A | AK63: #N/A | AL63: #N/A | AM63: #N/A | AN63: #N/A | AO63: #N/A | AP63: #N/A | AQ63: #N/A | AR63: #N/A | AS63: #N/A | AT63: #N/A | AU63: #N/A | AV63: #N/A | AW63: #N/A | AX63: #N/A | AY63: #N/A | AZ63: #N/A | BA63: #N/A | BB63: #N/A | BC63: #N/A | BD63: #N/A | BE63: #N/A | BF63: #N/A | BG63: #N/A | BH63: #N/A | BI63: #N/A | BJ63: #N/A | BK63: #N/A | BL63: #N/A | BM63: #N/A | BN63: #N/A | BO63: #N/A | BP63: #N/A | BQ63: #N/A | BR63: #N/A | BS63: #N/A | BT63: #N/A | BU63: #N/A | BV63: #N/A | BW63: #N/A | BX63: #N/A | BY63: #N/A | BZ63: #N/A | CA63: #N/A | CB63: #N/A | CC63: #N/A | CD63: #N/A | CE63: #N/A | CF63: #N/A | CG63: #N/A | CH63: #N/A | CI63: #N/A | CJ63: #N/A | CK63: #N/A | CL63: #N/A | CM63: #N/A | CN63: 40213 | CO63: 43482 | CP63: 43861 | CQ63: 43201 | CR63: 45014 | CS63: 44372
A64: 2033 | B64: 48580 | C64: #N/A | D64: #N/A | E64: #N/A | F64: #N/A | G64: #N/A | H64: #N/A | I64: #N/A | J64: #N/A | K64: #N/A | L64: #N/A | M64: #N/A | N64: #N/A | O64: #N/A | P64: #N/A | Q64: #N/A | R64: #N/A | S64: #N/A | T64: #N/A | U64: #N/A | V64: #N/A | W64: #N/A | X64: #N/A | Y64: #N/A | Z64: #N/A | AA64: #N/A | AB64: #N/A | AC64: #N/A | AD64: #N/A | AE64: #N/A | AF64: #N/A | AG64: #N/A | AH64: #N/A | AI64: #N/A | AJ64: #N/A | AK64: #N/A | AL64: #N/A | AM64: #N/A | AN64: #N/A | AO64: #N/A | AP64: #N/A | AQ64: #N/A | AR64: #N/A | AS64: #N/A | AT64: #N/A | AU64: #N/A | AV64: #N/A | AW64: #N/A | AX64: #N/A | AY64: #N/A | AZ64: #N/A | BA64: #N/A | BB64: #N/A | BC64: #N/A | BD64: #N/A | BE64: #N/A | BF64: #N/A | BG64: #N/A | BH64: #N/A | BI64: #N/A | BJ64: #N/A | BK64: #N/A | BL64: #N/A | BM64: #N/A | BN64: #N/A | BO64: #N/A | BP64: #N/A | BQ64: #N/A | BR64: #N/A | BS64: #N/A | BT64: #N/A | BU64: #N/A | BV64: #N/A | BW64: #N/A | BX64: #N/A | BY64: #N/A | BZ64: #N/A | CA64: #N/A | CB64: #N/A | CC64: #N/A | CD64: #N/A | CE64: #N/A | CF64: #N/A | CG64: #N/A | CH64: #N/A | CI64: #N/A | CJ64: #N/A | CK64: #N/A | CL64: #N/A | CM64: #N/A | CN64: #N/A | CO64: 46445 | CP64: 46709 | CQ64: 45739 | CR64: 47819 | CS64: 46985
A65: 2034 | B65: 48945 | C65: #N/A | D65: #N/A | E65: #N/A | F65: #N/A | G65: #N/A | H65: #N/A | I65: #N/A | J65: #N/A | K65: #N/A | L65: #N/A | M65: #N/A | N65: #N/A | O65: #N/A | P65: #N/A | Q65: #N/A | R65: #N/A | S65: #N/A | T65: #N/A | U65: #N/A | V65: #N/A | W65: #N/A | X65: #N/A | Y65: #N/A | Z65: #N/A | AA65: #N/A | AB65: #N/A | AC65: #N/A | AD65: #N/A | AE65: #N/A | AF65: #N/A | AG65: #N/A | AH65: #N/A | AI65: #N/A | AJ65: #N/A | AK65: #N/A | AL65: #N/A | AM65: #N/A | AN65: #N/A | AO65: #N/A | AP65: #N/A | AQ65: #N/A | AR65: #N/A | AS65: #N/A | AT65: #N/A | AU65: #N/A | AV65: #N/A | AW65: #N/A | AX65: #N/A | AY65: #N/A | AZ65: #N/A | BA65: #N/A | BB65: #N/A | BC65: #N/A | BD65: #N/A | BE65: #N/A | BF65: #N/A | BG65: #N/A | BH65: #N/A | BI65: #N/A | BJ65: #N/A | BK65: #N/A | BL65: #N/A | BM65: #N/A | BN65: #N/A | BO65: #N/A | BP65: #N/A | BQ65: #N/A | BR65: #N/A | BS65: #N/A | BT65: #N/A | BU65: #N/A | BV65: #N/A | BW65: #N/A | BX65: #N/A | BY65: #N/A | BZ65: #N/A | CA65: #N/A | CB65: #N/A | CC65: #N/A | CD65: #N/A | CE65: #N/A | CF65: #N/A | CG65: #N/A | CH65: #N/A | CI65: #N/A | CJ65: #N/A | CK65: #N/A | CL65: #N/A | CM65: #N/A | CN65: #N/A | CO65: #N/A | CP65: #N/A | CQ65: 48300 | CR65: 50664 | CS65: 49556
A66: 2035 | B66: 49310 | C66: #N/A | D66: #N/A | E66: #N/A | F66: #N/A | G66: #N/A | H66: #N/A | I66: #N/A | J66: #N/A | K66: #N/A | L66: #N/A | M66: #N/A | N66: #N/A | O66: #N/A | P66: #N/A | Q66: #N/A | R66: #N/A | S66: #N/A | T66: #N/A | U66: #N/A | V66: #N/A | W66: #N/A | X66: #N/A | Y66: #N/A | Z66: #N/A | AA66: #N/A | AB66: #N/A | AC66: #N/A | AD66: #N/A | AE66: #N/A | AF66: #N/A | AG66: #N/A | AH66: #N/A | AI66: #N/A | AJ66: #N/A | AK66: #N/A | AL66: #N/A | AM66: #N/A | AN66: #N/A | AO66: #N/A | AP66: #N/A | AQ66: #N/A | AR66: #N/A | AS66: #N/A | AT66: #N/A | AU66: #N/A | AV66: #N/A | AW66: #N/A | AX66: #N/A | AY66: #N/A | AZ66: #N/A | BA66: #N/A | BB66: #N/A | BC66: #N/A | BD66: #N/A | BE66: #N/A | BF66: #N/A | BG66: #N/A | BH66: #N/A | BI66: #N/A | BJ66: #N/A | BK66: #N/A | BL66: #N/A | BM66: #N/A | BN66: #N/A | BO66: #N/A | BP66: #N/A | BQ66: #N/A | BR66: #N/A | BS66: #N/A | BT66: #N/A | BU66: #N/A | BV66: #N/A | BW66: #N/A | BX66: #N/A | BY66: #N/A | BZ66: #N/A | CA66: #N/A | CB66: #N/A | CC66: #N/A | CD66: #N/A | CE66: #N/A | CF66: #N/A | CG66: #N/A | CH66: #N/A | CI66: #N/A | CJ66: #N/A | CK66: #N/A | CL66: #N/A | CM66: #N/A | CN66: #N/A | CO66: #N/A | CP66: #N/A | CQ66: #N/A | CR66: #N/A | CS66: 52056

Sheet cbo_debt_gdp
C1: 1976A | D1: 1976B | E1: 1977A | F1: 1979A | G1: 1980A | H1: 1981A | I1: 1982A | J1: 1983A | K1: 1984A | L1: 1985A | M1: 1985B | N1: 1986A | O1: 1986B | P1: 1987A | Q1: 1987B | R1: 1988A | S1: 1988B | T1: 1989A | U1: 1989B | V1: 1990A | W1: 1990B | X1: 1991A | Y1: 1991B | Z1: 1992A | AA1: 1992B | AB1: 1993A | AC1: 1993B | AD1: 1994A | AE1: 1994B | AF1: 1995A | AG1: 1995B | AH1: 1995C | AI1: 1996A | AJ1: 1997A | AK1: 1997B | AL1: 1998A | AM1: 1998B | AN1: 1999A | AO1: 1999B | AP1: 2000A | AQ1: 2000B | AR1: 2001A | AS1: 2001B | AT1: 2002A | AU1: 2002B | AV1: 2003A | AW1: 2003B | AX1: 2004A | AY1: 2004B | AZ1: 2005A | BA1: 2005B | BB1: 2006A | BC1: 2006B | BD1: 2007A | BE1: 2007B | BF1: 2008A | BG1: 2008B | BH1: 2009A | BI1: 2009B | BJ1: 2009C | BK1: 2010A | BL1: 2010B | BM1: 2011A | BN1: 2011B | BO1: 2012A | BP1: 2012B | BQ1: 2012C | BR1: 2013A | BS1: 2013B | BT1: 2014A | BU1: 2014B | BV1: 2014C | BW1: 2015A | BX1: 2015B | BY1: 2015C | BZ1: 2016A | CA1: 2016B | CB1: 2016C | CC1: 2017A | CD1: 2017B | CE1: 2018A | CF1: 2019A | CG1: 2019B | CH1: 2019C | CI1: 2020A | CJ1: 2020B | CK1: 2020C | CL1: 2021A | CM1: 2021B | CN1: 2022A | CO1: 2023A | CP1: 2023B | CQ1: 2024A | CR1: 2024B | CS1: 2025A
A2: 1975 2035 !A | B2: .excel_first | AU2: 100*CADAL02B@GOVFIN/CAEAL02B@GOVFIN | AW2: 100*CADAL03B@GOVFIN/CAEAL03B@GOVFIN | AX2: 100*CADAL04A@GOVFIN/CAEAL04A@GOVFIN | AY2: 100*CADAL04B@GOVFIN/CAEAL04B@GOVFIN | AZ2: 100*CADAL05A@GOVFIN/CAEAL05A@GOVFIN | BA2: 100*CADAL05B@GOVFIN/CAEAL05B@GOVFIN | BB2: 100*CADAL06A@GOVFIN/CAEAL06A@GOVFIN | BC2: 100*CADAL06B@GOVFIN/CAEAL06B@GOVFIN | BD2: 100*CADAL07A@GOVFIN/CAEAL07A@GOVFIN | BE2: 100*CADAL07B@GOVFIN/CAEAL07B@GOVFIN | BF2: 100*CADAL08A@GOVFIN/CAEAL08A@GOVFIN | BG2: 100*CADAL08B@GOVFIN/CAEAL08B@GOVFIN | BH2: 100*CADAL09A@GOVFIN/CAEAL09A@GOVFIN | BJ2: 100*CADAL09B@GOVFIN/CAEAL09B@GOVFIN | BK2: 100*CADAL10A@GOVFIN/CAEAL10A@GOVFIN | BL2: 100*CADAL10B@GOVFIN/CAEAL10B@GOVFIN | BM2: 100*CADAL11A@GOVFIN/CAEAL11A@GOVFIN | BN2: 100*CADAL11B@GOVFIN/CAEAL11B@GOVFIN | BO2: 100*CADAL12A@GOVFIN/CAEAL12A@GOVFIN | BP2: 100*CADAL12B@GOVFIN/CAEAL12B@GOVFIN | BQ2: 100*CADAL12C@GOVFIN/CAEAL12C@GOVFIN | BR2: 100*CADAL13A@GOVFIN/CAEAL13A@GOVFIN | BS2: 100*CADAL13B@GOVFIN/CAEAL13B@GOVFIN | BT2: 100*CADAL14A@GOVFIN/CAEAL14A@GOVFIN | BU2: 100*CADAL14B@GOVFIN/CAEAL14B@GOVFIN | BV2: 100*CADAL14C@GOVFIN/CAEAL14C@GOVFIN | BW2: 100*CADAL15A@GOVFIN/CAEAL15A@GOVFIN | BX2: 100*CADAL15B@GOVFIN/CAEAL15B@GOVFIN | BY2: 100*CADAL15C@GOVFIN/CAEAL15C@GOVFIN | BZ2: 100*CADAL16A@GOVFIN/CAEAL16A@GOVFIN | CA2: 100*CADAL16B@GOVFIN/CAEAL16B@GOVFIN | CB2: 100*CADAL16C@GOVFIN/CAEAL16C@GOVFIN | CC2: 100*CADAL17A@GOVFIN/CAEAL17A@GOVFIN | CD2: 100*CADAL17B@GOVFIN/CAEAL17B@GOVFIN | CE2: 100*CADAL18A@GOVFIN/CAEAL18A@GOVFIN | CF2: 100*CADAL19A@GOVFIN/CAEAL19A@GOVFIN | CG2: 100*CADAL19B@GOVFIN/CAEAL19B@GOVFIN | CH2: 100*CADAL19C@GOVFIN/CAEAL19C@GOVFIN | CI2: 100*CADAL20A@GOVFIN/CAEAL20A@GOVFIN | CJ2: 100*CADAL20B@GOVFIN/CAEAL20B@GOVFIN | CK2: 100*CADAL20C@GOVFIN/CAEAL20C@GOVFIN | CL2: 100*CADAL21A@GOVFIN/CAEAL21A@GOVFIN | CM2: 100*CADAL21B@GOVFIN/CAEAL21B@GOVFIN | CN2: 100*CADAL22A@GOVFIN/CAEAL22A@GOVFIN | CO2: 100*CADAL23A@GOVFIN/CAEAL23A@GOVFIN | CP2: 100*CADAL23B@GOVFIN/CAEAL23B@GOVFIN | CQ2: 100*CADAL24A@GOVFIN/CAEAL24A@GOVFIN | CR2: 100*CADAL24B@GOVFIN/CAEAL24B@GOVFIN | CS2: 100*PDPABUD@GOVFIN/GDPFCB@GOVFIN
A3: .DESC | J3: Ratio | AU3: CADAL02B: CBO Baseline Budget, August 2002: Debt Held by the Public (FY, Bil.$) CAEAL02B: CBO Baseline Budget, August 2002: Gross Domestic Product (FY, Bil.$) | AW3: CADAL03B: CBO Baseline Budget, August 2003: Debt Held by the Public (FY, Bil.$) CAEAL03B: CBO Baseline Budget, August 2003: Gross Domestic Product (FY, Bil.$) | AX3: CADAL04A: CBO Baseline Budget, January 2004: Debt Held by the Public (FY, Bil.$) CAEAL04A: CBO Baseline Budget, January 2004: Gross Domestic Product (FY, Bil.$) | AY3: CADAL04B: CBO Baseline Budget, September 2004: Debt Held by the Public (FY, Bil.$) CAEAL04B: CBO Baseline Budget, September 2004: Gross Domestic Product (FY, Bil.$) | AZ3: CADAL05A: CBO Baseline Budget, January 2005: Debt Held by the Public (FY, Bil.$) CAEAL05A: CBO Baseline Budget, January 2005: Gross Domestic Product (FY, Bil.$) | BA3: CADAL05B: CBO Baseline Budget, August 2005: Debt Held by the Public (FY, Bil.$) CAEAL05B: CBO Baseline Budget, August 2005: Gross Domestic Product (FY, Bil.$) | BB3: CADAL06A: CBO Baseline Budget, January 2006: Debt Held by the Public (FY, Bil.$) CAEAL06A: CBO Baseline Budget, January 2006: Gross Domestic Product (FY, Bil.$) | BC3: CADAL06B: CBO Baseline Budget, August 2006: Debt Held by the Public (FY, Bil.$) CAEAL06B: CBO Baseline Budget, August 2006: Gross Domestic Product (FY, Bil.$) | BD3: CADAL07A: CBO Baseline Budget, January 2007: Debt Held by the Public (FY, Bil.$) CAEAL07A: CBO Baseline Budget, January 2007: Gross Domestic Product (FY, Bil.$) | BE3: CADAL07B: CBO Baseline Budget, August 2007: Debt Held by the Public (FY, Bil.$) CAEAL07B: CBO Baseline Budget, August 2007: Gross Domestic Product (FY, Bil.$) | BF3: CADAL08A: CBO Baseline Budget, January 2008: Debt Held by the Public (FY, Bil.$) CAEAL08A: CBO Baseline Budget, January 2008: Gross Domestic Product (FY, Bil.$) | BG3: CADAL08B: CBO Baseline Budget, August 2008: Debt Held by the Public (FY, Bil.$) CAEAL08B: CBO Baseline Budget, August 2008: Gross Domestic Product (FY, Bil.$) | BH3: CADAL09A: CBO Baseline Budget, January 2009: Debt Held by the Public (FY, Bil.$) CAEAL09A: CBO Baseline Budget, January 2009: Gross Domestic Product (FY, Bil.$) | BJ3: CADAL09B: CBO Baseline Budget, August 2009: Debt Held by the Public (FY, Bil.$) CAEAL09B: CBO Baseline Budget, August 2009: Gross Domestic Product (FY, Bil.$) | BK3: CADAL10A: CBO Baseline Budget, January 2010: Debt Held by the Public (FY, Bil.$) CAEAL10A: CBO Baseline Budget, January 2010: Gross Domestic Product (FY, Bil.$) | BL3: CADAL10B: CBO Baseline Budget, August 2010: Debt Held by the Public (FY, Bil.$) CAEAL10B: CBO Baseline Budget, August 2010: Gross Domestic Product (FY, Bil.$) | BM3: CADAL11A: CBO Baseline Budget, January 2011: Debt Held by the Public (FY, Bil.$) CAEAL11A: CBO Baseline Budget, January 2011: Gross Domestic Product (FY, Bil.$) | BN3: CADAL11B: CBO Baseline Budget, August 2011: Debt Held by the Public (FY, Bil.$) CAEAL11B: CBO Baseline Budget, August 2011: Gross Domestic Product (FY, Bil.$) | BO3: CADAL12A: CBO Baseline Budget, January 2012: Debt Held by the Public (FY, Bil.$) CAEAL12A: CBO Baseline Budget, January 2012: Gross Domestic Product (FY, Bil.$) | BP3: CADAL12B: CBO Baseline Budget, March 2012: Debt Held by the Public (FY, Bil.$) CAEAL12B: CBO Baseline Budget, March 2012: Gross Domestic Product (FY, Bil.$) | BQ3: CADAL12C: CBO Baseline Budget, August 2012: Debt Held by the Public (FY, Bil.$) CAEAL12C: CBO Baseline Budget, August 2012: Gross Domestic Product (FY, Bil.$) | BR3: CADAL13A: CBO Baseline Budget, February 2013: Debt Held by the Public (FY, Bil.$) CAEAL13A: CBO Baseline Budget, February 2013: Gross Domestic Product (FY, Bil.$) | BS3: CADAL13B: CBO Baseline Budget, May 2013: Debt Held by the Public (FY, Bil.$) CAEAL13B: CBO Baseline Budget, May 2013: Gross Domestic Product (FY, Bil.$) | BT3: CADAL14A: CBO Baseline Budget, February 2014: Debt Held by the Public (FY, Bil.$) CAEAL14A: CBO Baseline Budget, February 2014: Gross Domestic Product (FY, Bil.$) | BU3: CADAL14B: CBO Baseline Budget, April 2014: Debt Held by the Public (FY, Bil.$) CAEAL14B: CBO Baseline Budget, April 2014: Gross Domestic Product (FY, Bil.$) | BV3: CADAL14C: CBO Baseline Budget, August 2014: Debt Held by the Public (FY, Bil.$) CAEAL14C: CBO Baseline Budget, August 2014: Gross Domestic Product (FY, Bil.$) | BW3: CADAL15A: CBO Baseline Budget, January 2015: Debt Held by the Public (FY, Bil.$) CAEAL15A: CBO Baseline Budget, January 2015: Gross Domestic Product (FY, Bil.$) | BX3: CADAL15B: CBO Baseline Budget, March 2015: Debt Held by the Public (FY, Bil.$) CAEAL15B: CBO Baseline Budget, March 2015: Gross Domestic Product (FY, Bil.$) | BY3: CADAL15C: CBO Baseline Budget, August 2015: Debt Held by the Public (FY, Bil.$) CAEAL15C: CBO Baseline Budget, August 2015: Gross Domestic Product (FY, Bil.$) | BZ3: CADAL16A: CBO Baseline Budget, January 2016: Debt Held by the Public (FY, Bil.$) CAEAL16A: CBO Baseline Budget, January 2016: Gross Domestic Product (FY, Bil.$) | CA3: CADAL16B: CBO Baseline Budget, March 2016: Debt Held by the Public (FY, Bil.$) CAEAL16B: CBO Baseline Budget, March 2016: Gross Domestic Product (FY, Bil.$) | CB3: CADAL16C: CBO Baseline Budget, August 2016: Debt Held by the Public (FY, Bil.$) CAEAL16C: CBO Baseline Budget, August 2016: Gross Domestic Product (FY, Bil.$) | CC3: CADAL17A: CBO Baseline Budget, January 2017: Debt Held by the Public (FY, Bil. US$) CAEAL17A: CBO Baseline Budget, January 2017: Gross Domestic Product (FY, Bil. US$) | CD3: CADAL17B: CBO Baseline Budget, June 2017: Debt Held by the Public (FY, Bil. US$) CAEAL17B: CBO Baseline Budget, June 2017: Gross Domestic Product (FY, Bil. US$) | CE3: CADAL18A: CBO Baseline Budget, April 2018: Debt Held by the Public (FY, Bil. US$) CAEAL18A: CBO Baseline Budget, April 2018: Gross Domestic Product (FY, Bil. US$) | CF3: CADAL19A: CBO Baseline Budget, January 2019: Debt Held by the Public (FY, Bil. US$) CAEAL19A: CBO Baseline Budget, Jan 2019: Gross Domestic Product (FY, Bil. US$) | CG3: CADAL19B: CBO Baseline Budget, May 2019: Debt Held by the Public (FY, Bil. US$) CAEAL19B: CBO Baseline Budget, May 2019: Gross Domestic Product (FY, Bil. US$) | CH3: CADAL19C: CBO Baseline Budget, August 2019: Debt Held by the Public (FY, Bil. US$) CAEAL19C: CBO Baseline Budget, August 2019: Gross Domestic Product (FY, Bil. US$) | CI3: CADAL20A: CBO Baseline Budget, Jan 2020: Debt Held by the Public (FY, Bil. US$) CAEAL20A: CBO Baseline Budget, Jan 2020: Gross Domestic Product (FY, Bil. US$) | CJ3: CADAL20B: CBO Baseline Budget, March 2020: Debt Held by the Public (FY, Bil. US$) CAEAL20B: CBO Baseline Budget, March 2020: Gross Domestic Product (FY, Bil. US$) | CK3: CADAL20C: CBO Baseline Budget, Sept 2020: Debt Held by the Public (FY, Bil. US$) CAEAL20C: CBO Baseline Budget, Sept 2020: Gross Domestic Product (FY, Bil. US$) | CL3: CADAL21A: CBO Baseline Budget, Feb 2021: Debt Held by the Public (FY, Bil. US$) CAEAL21A: CBO Baseline Budget, Feb 2021: Gross Domestic Product (FY, Bil. US$) | CM3: CADAL21B: CBO Baseline Budget, Jul 2021: Debt Held by the Public (FY, Bil. US$) CAEAL21B: CBO Baseline Budget, Jul 2021: Gross Domestic Product (FY, Bil. US$) | CN3: CADAL22A: CBO Baseline Budget, May 2022: Debt Held by the Public (FY, Bil. US$) CAEAL22A: CBO Baseline Budget, May 2022: Gross Domestic Product (FY, Bil. US$) | CO3: CADAL23A: CBO Baseline Budget, Feb 2023: Debt Held by the Public (FY, Bil. US$) CAEAL23A: CBO Baseline Budget, February 2023: Gross Domestic Product (FY, Bil. US$) | CP3: CADAL23B: CBO Baseline Budget, May 2023: Debt Held by the Public (FY, Bil. US$) CAEAL23B: CBO Baseline Budget, May 2023: Gross Domestic Product (FY, Bil. US$) | CQ3: CADAL24A: CBO Baseline Budget, Feb 2024: Debt Held by the Public (FY, Bil. US$) CAEAL24A: CBO Baseline Budget, Feb 2024: Gross Domestic Product (FY, Bil. US$) | CR3: CADAL24B: CBO Baseline Budget, Jun 2024: Debt Held by the Public (FY, Bil. US$) CAEAL24B: CBO Baseline Budget, Jun 2024: Gross Domestic Product (FY, Bil. US$) | CS3: PDPABUD: CBO Baseline Budget Projections, Debt Held by the Public (Fiscal Yr, Bil.$) GDPFCB: CBO's Estimate of President's Budget: GDP (Fiscal Yr,Bil.$)
A4: .DTLM | C4: 27760 | D4: 28095 | E4: 28460 | F4: 28856 | G4: 29252 | H4: 29768 | I4: 29983 | J4: 30348 | K4: 30713 | L4: 31079 | M4: 31260 | N4: 31444 | O4: 31625 | P4: 31778 | Q4: 31990 | R4: 32174 | S4: 32356 | T4: 32509 | U4: 32721 | V4: 32874 | W4: 33055 | X4: 33239 | Y4: 33451 | Z4: 33604 | AA4: 33817 | AB4: 33970 | AC4: 34213 | AD4: 34335 | AE4: 34547 | AF4: 34700 | AG4: 34912 | AH4: 35034 | AI4: 35186 | AJ4: 35431 | AK4: 35674 | AL4: 35796 | AM4: 36008 | AN4: 36161 | AO4: 36342 | AP4: 36526 | AQ4: 36708 | AR4: 36892 | AS4: 37104 | AT4: 37257 | AU4: CADAL02B: Mar-05-2015 13:55 CAEAL02B: Mar-05-2015 13:55 | AV4: 37622 | AW4: CADAL03B: Mar-05-2015 13:55 CAEAL03B: Mar-05-2015 13:55 | AX4: CADAL04A: Mar-05-2015 13:55 CAEAL04A: Mar-05-2015 13:55 | AY4: CADAL04B: Mar-05-2015 13:55 CAEAL04B: Mar-05-2015 13:55 | AZ4: CADAL05A: Mar-05-2015 13:55 CAEAL05A: Mar-05-2015 13:55 | BA4: CADAL05B: Mar-05-2015 13:55 CAEAL05B: Mar-05-2015 13:55 | BB4: CADAL06A: Mar-05-2015 13:55 CAEAL06A: Mar-05-2015 13:55 | BC4: CADAL06B: Mar-05-2015 13:55 CAEAL06B: Mar-05-2015 13:55 | BD4: CADAL07A: Mar-05-2015 13:55 CAEAL07A: Mar-05-2015 13:55 | BE4: CADAL07B: Mar-05-2015 13:55 CAEAL07B: Mar-05-2015 13:55 | BF4: CADAL08A: Mar-05-2015 13:55 CAEAL08A: Mar-05-2015 13:55 | BG4: CADAL08B: Mar-05-2015 13:55 CAEAL08B: Mar-05-2015 13:55 | BH4: CADAL09A: Mar-05-2015 13:55 CAEAL09A: Mar-05-2015 13:55 | BI4: 39873 | BJ4: CADAL09B: Mar-05-2015 13:55 CAEAL09B: Mar-05-2015 13:55 | BK4: CADAL10A: Mar-05-2015 13:55 CAEAL10A: Mar-05-2015 13:55 | BL4: CADAL10B: Mar-05-2015 13:55 CAEAL10B: Mar-05-2015 13:55 | BM4: CADAL11A: Mar-05-2015 13:55 CAEAL11A: Mar-05-2015 13:55 | BN4: CADAL11B: Mar-05-2015 13:55 CAEAL11B: Mar-05-2015 13:55 | BO4: CADAL12A: Mar-05-2015 13:55 CAEAL12A: Mar-05-2015 13:55 | BP4: CADAL12B: Mar-05-2015 13:55 CAEAL12B: Mar-05-2015 13:55 | BQ4: CADAL12C: Mar-05-2015 13:55 CAEAL12C: Mar-05-2015 13:55 | BR4: CADAL13A: Mar-05-2015 13:55 CAEAL13A: Mar-05-2015 13:55 | BS4: CADAL13B: Mar-05-2015 13:55 CAEAL13B: Mar-05-2015 13:55 | BT4: CADAL14A: Mar-05-2015 13:55 CAEAL14A: Mar-05-2015 13:55 | BU4: CADAL14B: Mar-05-2015 13:55 CAEAL14B: Mar-05-2015 13:55 | BV4: CADAL14C: Mar-05-2015 13:55 CAEAL14C: Mar-05-2015 13:55 | BW4: CADAL15A: Mar-10-2015 11:25 CAEAL15A: Mar-10-2015 11:25 | BX4: CADAL15B: Aug-13-2015 16:23 CAEAL15B: Aug-13-2015 16:23 | BY4: CADAL15C: Jan-19-2016 10:25 CAEAL15C: Jan-19-2016 10:25 | BZ4: CADAL16A: Mar-29-2016 14:03 CAEAL16A: Mar-29-2016 14:03 | CA4: CADAL16B: Sep-08-2016 12:44 CAEAL16B: Sep-08-2016 12:44 | CB4: CADAL16C: Jan-24-2017 10:46 CAEAL16C: Jan-24-2017 10:46 | CC4: CADAL17A: Jan-05-2018 16:11 CAEAL17A: Jan-05-2018 16:11 | CD4: CADAL17B: Apr-19-2018 10:36 CAEAL17B: Apr-19-2018 10:36 | CE4: CADAL18A: Nov-01-2018 09:23 CAEAL18A: Nov-01-2018 09:23 | CF4: CADAL19A: Jan-30-2019 09:30 CAEAL19A: Feb-25-2025 08:55 | CG4: CADAL19B: May-02-2019 13:12 CAEAL19B: May-02-2019 13:12 | CH4: CADAL19C: Aug-21-2019 10:39 CAEAL19C: Aug-21-2019 10:39 | CI4: CADAL20A: Sep-02-2020 16:58 CAEAL20A: Sep-02-2020 16:58 | CJ4: CADAL20B: Sep-02-2020 17:01 CAEAL20B: Feb-24-2025 11:55 | CK4: CADAL20C: Sep-02-2020 17:01 CAEAL20C: Sep-02-2020 17:01 | CL4: CADAL21A: Feb-22-2023 16:31 CAEAL21A: Feb-22-2023 16:31 | CM4: CADAL21B: Feb-22-2023 16:31 CAEAL21B: Feb-22-2023 16:31 | CN4: CADAL22A: Feb-22-2023 16:31 CAEAL22A: Feb-22-2023 16:31 | CO4: CADAL23A: Aug-03-2023 09:59 CAEAL23A: Feb-08-2024 14:00 | CP4: CADAL23B: Feb-08-2024 13:22 CAEAL23B: Feb-08-2024 13:22 | CQ4: CADAL24A: Jun-20-2024 11:29 CAEAL24A: Jun-20-2024 11:29 | CR4: CADAL24B: Jan-27-2025 08:42 CAEAL24B: Jan-27-2025 08:42 | CS4: PDPABUD: Jan-17-2025 12:31 GDPFCB: Jan-30-2025 16:49 | DD4: Actual | DF4: Error
A5: .SOURCE | C5: 27760 | D5: 28095 | E5: 28460 | F5: 28856 | G5: 29252 | H5: 29768 | I5: 29983 | J5: 30348 | K5: 30713 | L5: 31079 | M5: 31260 | N5: 31444 | O5: 31625 | P5: 31778 | Q5: 31990 | R5: 32174 | S5: 32356 | T5: 32509 | U5: 32721 | V5: 32874 | W5: 33055 | X5: 33239 | Y5: 33451 | Z5: 33604 | AA5: 33817 | AB5: 33970 | AC5: 34213 | AD5: 34335 | AE5: 34547 | AF5: 34700 | AG5: 34912 | AH5: 35034 | AI5: 35186 | AJ5: 35431 | AK5: 35674 | AL5: 35796 | AM5: 36008 | AN5: 36161 | AO5: 36342 | AP5: 36526 | AQ5: 36708 | AR5: 365610 | AS5: 37104 | AT5: 37257 | AU5: CADAL02B: CBO CAEAL02B: CBO | AV5: 37622 | AW5: CADAL03B: CBO CAEAL03B: CBO | AX5: CADAL04A: CBO CAEAL04A: CBO | AY5: CADAL04B: CBO CAEAL04B: CBO | AZ5: CADAL05A: CBO CAEAL05A: CBO | BA5: CADAL05B: CBO CAEAL05B: CBO | BB5: CADAL06A: CBO CAEAL06A: CBO | BC5: CADAL06B: CBO CAEAL06B: CBO | BD5: CADAL07A: CBO CAEAL07A: CBO | BE5: CADAL07B: CBO CAEAL07B: CBO | BF5: CADAL08A: CBO CAEAL08A: CBO | BG5: CADAL08B: CBO CAEAL08B: CBO | BH5: CADAL09A: CBO CAEAL09A: CBO | BI5: 39873 | BJ5: CADAL09B: CBO CAEAL09B: CBO | BK5: CADAL10A: CBO CAEAL10A: CBO | BL5: CADAL10B: CBO CAEAL10B: CBO | BM5: CADAL11A: CBO CAEAL11A: CBO | BN5: CADAL11B: CBO CAEAL11B: CBO | BO5: CADAL12A: CBO CAEAL12A: CBO | BP5: CADAL12B: CBO CAEAL12B: CBO | BQ5: CADAL12C: CBO CAEAL12C: CBO | BR5: CADAL13A: CBO CAEAL13A: CBO | BS5: CADAL13B: CBO CAEAL13B: CBO | BT5: CADAL14A: CBO CAEAL14A: CBO | BU5: CADAL14B: CBO CAEAL14B: CBO | BV5: CADAL14C: CBO CAEAL14C: CBO | BW5: CADAL15A: CBO CAEAL15A: CBO | BX5: CADAL15B: CBO CAEAL15B: CBO | BY5: CADAL15C: CBO CAEAL15C: CBO | BZ5: CADAL16A: CBO CAEAL16A: CBO | CA5: CADAL16B: CBO CAEAL16B: CBO | CB5: CADAL16C: CBO CAEAL16C: CBO | CC5: CADAL17A: CBO CAEAL17A: CBO | CD5: CADAL17B: CBO CAEAL17B: CBO | CE5: CADAL18A: CBO CAEAL18A: CBO | CF5: CADAL19A: CBO CAEAL19A: CBO | CG5: CADAL19B: CBO CAEAL19B: CBO | CH5: CADAL19C: CBO CAEAL19C: CBO | CI5: CADAL20A: CBO CAEAL20A: CBO | CJ5: CADAL20B: CBO CAEAL20B: CBO | CK5: CADAL20C: CBO CAEAL20C: CBO | CL5: CADAL21A: CBO CAEAL21A: CBO | CM5: CADAL21B: CBO CAEAL21B: CBO | CN5: CADAL22A: CBO CAEAL22A: CBO | CO5: CADAL23A: CBO CAEAL23A: CBO | CP5: CADAL23B: CBO CAEAL23B: CBO | CQ5: CADAL24A: CBO CAEAL24A: CBO | CR5: CADAL24B: CBO CAEAL24B: CBO | CS5: PDPABUD: CBO GDPFCB: CBO | CV5: Forecast horizon | CW5: 0 | CY5: 5 | DA5: 10 | DD5: 0 | DE5: 5 | DF5: 0 | DG5: 5
A6: 1975 | B6: 27395 | C6: =100*cbo_debt!C6/cbo_ngdp!C6 -> #N/A | D6: =100*cbo_debt!D6/cbo_ngdp!D6 -> #N/A | E6: =100*cbo_debt!E6/cbo_ngdp!E6 -> #N/A | F6: =100*cbo_debt!F6/cbo_ngdp!F6 -> #N/A | G6: =100*cbo_debt!G6/cbo_ngdp!G6 -> #N/A | H6: =100*cbo_debt!H6/cbo_ngdp!H6 -> #N/A | I6: =100*cbo_debt!I6/cbo_ngdp!I6 -> #N/A | J6: =100*cbo_debt!J6/cbo_ngdp!B6 -> #N/A | K6: =100*cbo_debt!K6/cbo_ngdp!K6 -> #N/A | L6: =100*cbo_debt!L6/cbo_ngdp!L6 -> #N/A | M6: =100*cbo_debt!M6/cbo_ngdp!M6 -> #N/A | N6: =100*cbo_debt!N6/cbo_ngdp!N6 -> #N/A | O6: =100*cbo_debt!O6/cbo_ngdp!O6 -> #N/A | P6: =100*cbo_debt!P6/cbo_ngdp!P6 -> #N/A | Q6: =100*cbo_debt!Q6/cbo_ngdp!Q6 -> #N/A | R6: =100*cbo_debt!R6/cbo_ngdp!R6 -> #N/A | ... AT6: =100*cbo_debt!AT6/cbo_ngdp!AT6 -> #N/A | AU6: #N/A | AV6: =100*cbo_debt!AV6/cbo_ngdp!AV6 -> #N/A | AW6: #N/A | AX6: #N/A | AY6: #N/A | AZ6: #N/A | BA6: #N/A | BB6: #N/A | BC6: #N/A | BD6: #N/A | BE6: #N/A | BF6: #N/A | BG6: #N/A | BH6: #N/A | BI6: #N/A | BJ6: #N/A | BK6: #N/A | BL6: #N/A | BM6: #N/A | BN6: #N/A | BO6: #N/A | BP6: #N/A | BQ6: #N/A | BR6: #N/A | BS6: #N/A | BT6: #N/A | BU6: #N/A | BV6: #N/A | BW6: #N/A | BX6: #N/A | BY6: #N/A | BZ6: #N/A | CA6: #N/A | CB6: #N/A | CC6: #N/A | CD6: #N/A | CE6: #N/A | CF6: #N/A | CG6: #N/A | CH6: #N/A | CI6: #N/A | CJ6: #N/A | CK6: #N/A | CL6: #N/A | CM6: #N/A | CN6: #N/A | CO6: #N/A | CP6: #N/A | CQ6: #N/A | CR6: #N/A | CS6: 24.579963 | CV6: Date of forecast (column) | CW6: Forecasted period (row) | CX6: Value | CY6: Forecasted period (row) | CZ6: Value | DA6: Forecasted period (row) | DB6: Value
A7: 1976 | B7: 27760 | C7: =100*cbo_debt!C7/cbo_ngdp!C7 -> 27.669617 | D7: =100*cbo_debt!D7/cbo_ngdp!D7 -> #N/A | E7: =100*cbo_debt!E7/cbo_ngdp!E7 -> #N/A | F7: =100*cbo_debt!F7/cbo_ngdp!F7 -> #N/A | G7: =100*cbo_debt!G7/cbo_ngdp!G7 -> #N/A | H7: =100*cbo_debt!H7/cbo_ngdp!H7 -> #N/A | I7: =100*cbo_debt!I7/cbo_ngdp!I7 -> #N/A | J7: =100*cbo_debt!J7/cbo_ngdp!B7 -> #N/A | K7: =100*cbo_debt!K7/cbo_ngdp!K7 -> #N/A | L7: =100*cbo_debt!L7/cbo_ngdp!L7 -> #N/A | M7: =100*cbo_debt!M7/cbo_ngdp!M7 -> #N/A | N7: =100*cbo_debt!N7/cbo_ngdp!N7 -> #N/A | O7: =100*cbo_debt!O7/cbo_ngdp!O7 -> #N/A | P7: =100*cbo_debt!P7/cbo_ngdp!P7 -> #N/A | Q7: =100*cbo_debt!Q7/cbo_ngdp!Q7 -> #N/A | R7: =100*cbo_debt!R7/cbo_ngdp!R7 -> #N/A | ... AT7: =100*cbo_debt!AT7/cbo_ngdp!AT7 -> #N/A | AU7: #N/A | AV7: =100*cbo_debt!AV7/cbo_ngdp!AV7 -> #N/A | AW7: #N/A | AX7: #N/A | AY7: #N/A | AZ7: #N/A | BA7: #N/A | BB7: #N/A | BC7: #N/A | BD7: #N/A | BE7: #N/A | BF7: #N/A | BG7: #N/A | BH7: #N/A | BI7: #N/A | BJ7: #N/A | BK7: #N/A | BL7: #N/A | BM7: #N/A | BN7: #N/A | BO7: #N/A | BP7: #N/A | BQ7: #N/A | BR7: #N/A | BS7: #N/A | BT7: #N/A | BU7: #N/A | BV7: #N/A | BW7: #N/A | BX7: #N/A | BY7: #N/A | BZ7: #N/A | CA7: #N/A | CB7: #N/A | CC7: #N/A | CD7: #N/A | CE7: #N/A | CF7: #N/A | CG7: #N/A | CH7: #N/A | CI7: #N/A | CJ7: #N/A | CK7: #N/A | CL7: #N/A | CM7: #N/A | CN7: #N/A | CO7: #N/A | CP7: #N/A | CQ7: #N/A | CR7: #N/A | CS7: 26.707727 | CU7: 27760 | CV7: =OFFSET(C$1,0,ROWS($1:1)-1) -> 1976A | CW7: =LEFT(CV7,4)+$CW$5 -> 1976 | CX7: {=INDEX($C$6:$CS$100,MATCH(CW7,YEAR($B$6:$B$100),0),MATCH(CV7,$C$1:$CS$1,0))} -> 27.669617 | CY7: =LEFT(CV7,4)+$CY$5 -> 1981 | CZ7: {=INDEX($C$6:$CS$100,MATCH(CY7,YEAR($B$6:$B$100),0),MATCH(CV7,$C$1:$CS$1,0))} -> 10.731707 | DA7: =LEFT(CV7,4)+$DA$5 -> 1986 | DB7: {=INDEX($C$6:$CS$100,MATCH(DA7,YEAR($B$6:$B$100),0),MATCH(CV7,$C$1:$CS$1,0))} -> #N/A | DD7: =VLOOKUP(DATE(CW7,1,1),$B$6:$CS$66,96,FALSE) -> 26.707727 | DE7: =VLOOKUP(DATE(CY7,1,1),$B$6:$CS$66,96,FALSE) -> 25.18353
A8: 1977 | B8: 28126 | C8: =100*cbo_debt!C8/cbo_ngdp!C8 -> 26.176927 | D8: =100*cbo_debt!D8/cbo_ngdp!D8 -> 28.75817 | E8: =100*cbo_debt!E8/cbo_ngdp!E8 -> #N/A | F8: =100*cbo_debt!F8/cbo_ngdp!F8 -> #N/A | G8: =100*cbo_debt!G8/cbo_ngdp!G8 -> #N/A | H8: =100*cbo_debt!H8/cbo_ngdp!H8 -> #N/A | I8: =100*cbo_debt!I8/cbo_ngdp!I8 -> #N/A | J8: =100*cbo_debt!J8/cbo_ngdp!B8 -> #N/A | K8: =100*cbo_debt!K8/cbo_ngdp!K8 -> #N/A | L8: =100*cbo_debt!L8/cbo_ngdp!L8 -> #N/A | M8: =100*cbo_debt!M8/cbo_ngdp!M8 -> #N/A | N8: =100*cbo_debt!N8/cbo_ngdp!N8 -> #N/A | O8: =100*cbo_debt!O8/cbo_ngdp!O8 -> #N/A | P8: =100*cbo_debt!P8/cbo_ngdp!P8 -> #N/A | Q8: =100*cbo_debt!Q8/cbo_ngdp!Q8 -> #N/A | R8: =100*cbo_debt!R8/cbo_ngdp!R8 -> #N/A | ... AT8: =100*cbo_debt!AT8/cbo_ngdp!AT8 -> #N/A | AU8: #N/A | AV8: =100*cbo_debt!AV8/cbo_ngdp!AV8 -> #N/A | AW8: #N/A | AX8: #N/A | AY8: #N/A | AZ8: #N/A | BA8: #N/A | BB8: #N/A | BC8: #N/A | BD8: #N/A | BE8: #N/A | BF8: #N/A | BG8: #N/A | BH8: #N/A | BI8: #N/A | BJ8: #N/A | BK8: #N/A | BL8: #N/A | BM8: #N/A | BN8: #N/A | BO8: #N/A | BP8: #N/A | BQ8: #N/A | BR8: #N/A | BS8: #N/A | BT8: #N/A | BU8: #N/A | BV8: #N/A | BW8: #N/A | BX8: #N/A | BY8: #N/A | BZ8: #N/A | CA8: #N/A | CB8: #N/A | CC8: #N/A | CD8: #N/A | CE8: #N/A | CF8: #N/A | CG8: #N/A | CH8: #N/A | CI8: #N/A | CJ8: #N/A | CK8: #N/A | CL8: #N/A | CM8: #N/A | CN8: #N/A | CO8: #N/A | CP8: #N/A | CQ8: #N/A | CR8: #N/A | CS8: 27.124506 | CU8: 28095 | CV8: =OFFSET(C$1,0,ROWS($1:2)-1) -> 1976B | CW8: =LEFT(CV8,4)+$CW$5+1 -> 1977 | CX8: {=INDEX($C$6:$CS$100,MATCH(CW8,YEAR($B$6:$B$100),0),MATCH(CV8,$C$1:$CS$1,0))} -> 28.75817 | CY8: =LEFT(CV8,4)+$CY$5 -> 1981 | CZ8: {=INDEX($C$6:$CS$100,MATCH(CY8,YEAR($B$6:$B$100),0),MATCH(CV8,$C$1:$CS$1,0))} -> 19.343066 | DA8: =LEFT(CV8,4)+$DA$5 -> 1986 | DB8: {=INDEX($C$6:$CS$100,MATCH(DA8,YEAR($B$6:$B$100),0),MATCH(CV8,$C$1:$CS$1,0))} -> #N/A | DD8: =VLOOKUP(DATE(CW8,1,1),$B$6:$CS$66,96,FALSE) -> 27.124506 | DE8: =VLOOKUP(DATE(CY8,1,1),$B$6:$CS$66,96,FALSE) -> 25.18353
A9: 1978 | B9: 28491 | C9: =100*cbo_debt!C9/cbo_ngdp!C9 -> 23.0839 | D9: =100*cbo_debt!D9/cbo_ngdp!D9 -> 28.121927 | E9: =100*cbo_debt!E9/cbo_ngdp!E9 -> 29.654837 | F9: =100*cbo_debt!F9/cbo_ngdp!F9 -> #N/A | G9: =100*cbo_debt!G9/cbo_ngdp!G9 -> #N/A | H9: =100*cbo_debt!H9/cbo_ngdp!H9 -> #N/A | I9: =100*cbo_debt!I9/cbo_ngdp!I9 -> #N/A | J9: =100*cbo_debt!J9/cbo_ngdp!B9 -> #N/A | K9: =100*cbo_debt!K9/cbo_ngdp!K9 -> #N/A | L9: =100*cbo_debt!L9/cbo_ngdp!L9 -> #N/A | M9: =100*cbo_debt!M9/cbo_ngdp!M9 -> #N/A | N9: =100*cbo_debt!N9/cbo_ngdp!N9 -> #N/A | O9: =100*cbo_debt!O9/cbo_ngdp!O9 -> #N/A | P9: =100*cbo_debt!P9/cbo_ngdp!P9 -> #N/A | Q9: =100*cbo_debt!Q9/cbo_ngdp!Q9 -> #N/A | R9: =100*cbo_debt!R9/cbo_ngdp!R9 -> #N/A | ... AT9: =100*cbo_debt!AT9/cbo_ngdp!AT9 -> #N/A | AU9: #N/A | AV9: =100*cbo_debt!AV9/cbo_ngdp!AV9 -> #N/A | AW9: #N/A | AX9: #N/A | AY9: #N/A | AZ9: #N/A | BA9: #N/A | BB9: #N/A | BC9: #N/A | BD9: #N/A | BE9: #N/A | BF9: #N/A | BG9: #N/A | BH9: #N/A | BI9: #N/A | BJ9: #N/A | BK9: #N/A | BL9: #N/A | BM9: #N/A | BN9: #N/A | BO9: #N/A | BP9: #N/A | BQ9: #N/A | BR9: #N/A | BS9: #N/A | BT9: #N/A | BU9: #N/A | BV9: #N/A | BW9: #N/A | BX9: #N/A | BY9: #N/A | BZ9: #N/A | CA9: #N/A | CB9: #N/A | CC9: #N/A | CD9: #N/A | CE9: #N/A | CF9: #N/A | CG9: #N/A | CH9: #N/A | CI9: #N/A | CJ9: #N/A | CK9: #N/A | CL9: #N/A | CM9: #N/A | CN9: #N/A | CO9: #N/A | CP9: #N/A | CQ9: #N/A | CR9: #N/A | CS9: 26.704795 | CU9: 28460 | CV9: =OFFSET(C$1,0,ROWS($1:3)-1) -> 1977A | CW9: =LEFT(CV9,4)+$CW$5+1 -> 1978 | CX9: {=INDEX($C$6:$CS$100,MATCH(CW9,YEAR($B$6:$B$100),0),MATCH(CV9,$C$1:$CS$1,0))} -> 29.654837 | CY9: =LEFT(CV9,4)+$CY$5 -> 1982 | CZ9: {=INDEX($C$6:$CS$100,MATCH(CY9,YEAR($B$6:$B$100),0),MATCH(CV9,$C$1:$CS$1,0))} -> 18.544982 | DA9: =LEFT(CV9,4)+$DA$5 -> 1987 | DB9: {=INDEX($C$6:$CS$100,MATCH(DA9,YEAR($B$6:$B$100),0),MATCH(CV9,$C$1:$CS$1,0))} -> #N/A | DD9: =VLOOKUP(DATE(CW9,1,1),$B$6:$CS$66,96,FALSE) -> 26.704795 | DE9: =VLOOKUP(DATE(CY9,1,1),$B$6:$CS$66,96,FALSE) -> 27.920314
A10: 1979 | B10: 28856 | C10: =100*cbo_debt!C10/cbo_ngdp!C10 -> 19.315895 | D10: =100*cbo_debt!D10/cbo_ngdp!D10 -> 26.168224 | E10: =100*cbo_debt!E10/cbo_ngdp!E10 -> 28.496042 | F10: =100*cbo_debt!F10/cbo_ngdp!F10 -> 28.173913 | G10: =100*cbo_debt!G10/cbo_ngdp!G10 -> #N/A | H10: =100*cbo_debt!H10/cbo_ngdp!H10 -> #N/A | I10: =100*cbo_debt!I10/cbo_ngdp!I10 -> #N/A | J10: =100*cbo_debt!J10/cbo_ngdp!B10 -> #N/A | K10: =100*cbo_debt!K10/cbo_ngdp!K10 -> #N/A | L10: =100*cbo_debt!L10/cbo_ngdp!L10 -> #N/A | M10: =100*cbo_debt!M10/cbo_ngdp!M10 -> #N/A | N10: =100*cbo_debt!N10/cbo_ngdp!N10 -> #N/A | O10: =100*cbo_debt!O10/cbo_ngdp!O10 -> #N/A | P10: =100*cbo_debt!P10/cbo_ngdp!P10 -> #N/A | Q10: =100*cbo_debt!Q10/cbo_ngdp!Q10 -> #N/A | R10: =100*cbo_debt!R10/cbo_ngdp!R10 -> #N/A | ... AT10: =100*cbo_debt!AT10/cbo_ngdp!AT10 -> #N/A | AU10: #N/A | AV10: =100*cbo_debt!AV10/cbo_ngdp!AV10 -> #N/A | AW10: #N/A | AX10: #N/A | AY10: #N/A | AZ10: #N/A | BA10: #N/A | BB10: #N/A | BC10: #N/A | BD10: #N/A | BE10: #N/A | BF10: #N/A | BG10: #N/A | BH10: #N/A | BI10: #N/A | BJ10: #N/A | BK10: #N/A | BL10: #N/A | BM10: #N/A | BN10: #N/A | BO10: #N/A | BP10: #N/A | BQ10: #N/A | BR10: #N/A | BS10: #N/A | BT10: #N/A | BU10: #N/A | BV10: #N/A | BW10: #N/A | BX10: #N/A | BY10: #N/A | BZ10: #N/A | CA10: #N/A | CB10: #N/A | CC10: #N/A | CD10: #N/A | CE10: #N/A | CF10: #N/A | CG10: #N/A | CH10: #N/A | CI10: #N/A | CJ10: #N/A | CK10: #N/A | CL10: #N/A | CM10: #N/A | CN10: #N/A | CO10: #N/A | CP10: #N/A | CQ10: #N/A | CR10: #N/A | CS10: 24.941543 | CU10: 28856 | CV10: =OFFSET(C$1,0,ROWS($1:4)-1) -> 1979A | CW10: =LEFT(CV10,4)+$CW$5 -> 1979 | CX10: {=INDEX($C$6:$CS$100,MATCH(CW10,YEAR($B$6:$B$100),0),MATCH(CV10,$C$1:$CS$1,0))} -> 28.173913 | CY10: =LEFT(CV10,4)+$CY$5 -> 1984 | CZ10: {=INDEX($C$6:$CS$100,MATCH(CY10,YEAR($B$6:$B$100),0),MATCH(CV10,$C$1:$CS$1,0))} -> 15.02444 | DA10: =LEFT(CV10,4)+$DA$5 -> 1989 | DB10: {=INDEX($C$6:$CS$100,MATCH(DA10,YEAR($B$6:$B$100),0),MATCH(CV10,$C$1:$CS$1,0))} -> #N/A | DD10: =VLOOKUP(DATE(CW10,1,1),$B$6:$CS$66,96,FALSE) -> 24.941543 | DE10: =VLOOKUP(DATE(CY10,1,1),$B$6:$CS$66,96,FALSE) -> 33.096987
A11: 1980 | B11: 29221 | C11: =100*cbo_debt!C11/cbo_ngdp!C11 -> 15.179856 | D11: =100*cbo_debt!D11/cbo_ngdp!D11 -> 23.188406 | E11: =100*cbo_debt!E11/cbo_ngdp!E11 -> 26.121477 | F11: =100*cbo_debt!F11/cbo_ngdp!F11 -> 27.60396 | G11: =100*cbo_debt!G11/cbo_ngdp!G11 -> 27.306977 | H11: =100*cbo_debt!H11/cbo_ngdp!H11 -> #N/A | I11: =100*cbo_debt!I11/cbo_ngdp!I11 -> #N/A | J11: =100*cbo_debt!J11/cbo_ngdp!B11 -> #N/A | K11: =100*cbo_debt!K11/cbo_ngdp!K11 -> #N/A | L11: =100*cbo_debt!L11/cbo_ngdp!L11 -> #N/A | M11: =100*cbo_debt!M11/cbo_ngdp!M11 -> #N/A | N11: =100*cbo_debt!N11/cbo_ngdp!N11 -> #N/A | O11: =100*cbo_debt!O11/cbo_ngdp!O11 -> #N/A | P11: =100*cbo_debt!P11/cbo_ngdp!P11 -> #N/A | Q11: =100*cbo_debt!Q11/cbo_ngdp!Q11 -> #N/A | R11: =100*cbo_debt!R11/cbo_ngdp!R11 -> #N/A | ... AT11: =100*cbo_debt!AT11/cbo_ngdp!AT11 -> #N/A | AU11: #N/A | AV11: =100*cbo_debt!AV11/cbo_ngdp!AV11 -> #N/A | AW11: #N/A | AX11: #N/A | AY11: #N/A | AZ11: #N/A | BA11: #N/A | BB11: #N/A | BC11: #N/A | BD11: #N/A | BE11: #N/A | BF11: #N/A | BG11: #N/A | BH11: #N/A | BI11: #N/A | BJ11: #N/A | BK11: #N/A | BL11: #N/A | BM11: #N/A | BN11: #N/A | BO11: #N/A | BP11: #N/A | BQ11: #N/A | BR11: #N/A | BS11: #N/A | BT11: #N/A | BU11: #N/A | BV11: #N/A | BW11: #N/A | BX11: #N/A | BY11: #N/A | BZ11: #N/A | CA11: #N/A | CB11: #N/A | CC11: #N/A | CD11: #N/A | CE11: #N/A | CF11: #N/A | CG11: #N/A | CH11: #N/A | CI11: #N/A | CJ11: #N/A | CK11: #N/A | CL11: #N/A | CM11: #N/A | CN11: #N/A | CO11: #N/A | CP11: #N/A | CQ11: #N/A | CR11: #N/A | CS11: 25.501433 | CU11: 29252 | CV11: =OFFSET(C$1,0,ROWS($1:5)-1) -> 1980A | CW11: =LEFT(CV11,4)+$CW$5 -> 1980 | CX11: {=INDEX($C$6:$CS$100,MATCH(CW11,YEAR($B$6:$B$100),0),MATCH(CV11,$C$1:$CS$1,0))} -> 27.306977 | CY11: =LEFT(CV11,4)+$CY$5 -> 1985 | CZ11: {=INDEX($C$6:$CS$100,MATCH(CY11,YEAR($B$6:$B$100),0),MATCH(CV11,$C$1:$CS$1,0))} -> 15.871658 | DA11: =LEFT(CV11,4)+$DA$5 -> 1990 | DB11: {=INDEX($C$6:$CS$100,MATCH(DA11,YEAR($B$6:$B$100),0),MATCH(CV11,$C$1:$CS$1,0))} -> #N/A | DD11: =VLOOKUP(DATE(CW11,1,1),$B$6:$CS$66,96,FALSE) -> 25.501433 | DE11: =VLOOKUP(DATE(CY11,1,1),$B$6:$CS$66,96,FALSE) -> 35.334115
A12: 1981 | B12: 29587 | C12: =100*cbo_debt!C12/cbo_ngdp!C12 -> 10.731707 | D12: =100*cbo_debt!D12/cbo_ngdp!D12 -> 19.343066 | E12: =100*cbo_debt!E12/cbo_ngdp!E12 -> 22.745239 | F12: =100*cbo_debt!F12/cbo_ngdp!F12 -> 25.83511 | G12: =100*cbo_debt!G12/cbo_ngdp!G12 -> 26.454021 | H12: =100*cbo_debt!H12/cbo_ngdp!H12 -> 26.916667 | I12: =100*cbo_debt!I12/cbo_ngdp!I12 -> #N/A | J12: =100*cbo_debt!J12/cbo_ngdp!B12 -> #N/A | K12: =100*cbo_debt!K12/cbo_ngdp!K12 -> #N/A | L12: =100*cbo_debt!L12/cbo_ngdp!L12 -> #N/A | M12: =100*cbo_debt!M12/cbo_ngdp!M12 -> #N/A | N12: =100*cbo_debt!N12/cbo_ngdp!N12 -> #N/A | O12: =100*cbo_debt!O12/cbo_ngdp!O12 -> #N/A | P12: =100*cbo_debt!P12/cbo_ngdp!P12 -> #N/A | Q12: =100*cbo_debt!Q12/cbo_ngdp!Q12 -> #N/A | R12: =100*cbo_debt!R12/cbo_ngdp!R12 -> #N/A | ... AT12: =100*cbo_debt!AT12/cbo_ngdp!AT12 -> #N/A | AU12: #N/A | AV12: =100*cbo_debt!AV12/cbo_ngdp!AV12 -> #N/A | AW12: #N/A | AX12: #N/A | AY12: #N/A | AZ12: #N/A | BA12: #N/A | BB12: #N/A | BC12: #N/A | BD12: #N/A | BE12: #N/A | BF12: #N/A | BG12: #N/A | BH12: #N/A | BI12: #N/A | BJ12: #N/A | BK12: #N/A | BL12: #N/A | BM12: #N/A | BN12: #N/A | BO12: #N/A | BP12: #N/A | BQ12: #N/A | BR12: #N/A | BS12: #N/A | BT12: #N/A | BU12: #N/A | BV12: #N/A | BW12: #N/A | BX12: #N/A | BY12: #N/A | BZ12: #N/A | CA12: #N/A | CB12: #N/A | CC12: #N/A | CD12: #N/A | CE12: #N/A | CF12: #N/A | CG12: #N/A | CH12: #N/A | CI12: #N/A | CJ12: #N/A | CK12: #N/A | CL12: #N/A | CM12: #N/A | CN12: #N/A | CO12: #N/A | CP12: #N/A | CQ12: #N/A | CR12: #N/A | CS12: 25.18353 | CU12: 29768 | CV12: =OFFSET(C$1,0,ROWS($1:6)-1) -> 1981A | CW12: =LEFT(CV12,4)+$CW$5 -> 1981 | CX12: {=INDEX($C$6:$CS$100,MATCH(CW12,YEAR($B$6:$B$100),0),MATCH(CV12,$C$1:$CS$1,0))} -> 26.916667 | CY12: =LEFT(CV12,4)+$CY$5 -> 1986 | CZ12: {=INDEX($C$6:$CS$100,MATCH(CY12,YEAR($B$6:$B$100),0),MATCH(CV12,$C$1:$CS$1,0))} -> 7.1803828 | DA12: =LEFT(CV12,4)+$DA$5 -> 1991 | DB12: {=INDEX($C$6:$CS$100,MATCH(DA12,YEAR($B$6:$B$100),0),MATCH(CV12,$C$1:$CS$1,0))} -> #N/A | DD12: =VLOOKUP(DATE(CW12,1,1),$B$6:$CS$66,96,FALSE) -> 25.18353 | DE12: =VLOOKUP(DATE(CY12,1,1),$B$6:$CS$66,96,FALSE) -> 38.466637 | DF12: =(DD12-CX12)^2 -> 3.0037621 | DG12: =(DE12-CZ12)^2 -> 978.82972
A13: 1982 | B13: 29952 | C13: =100*cbo_debt!C13/cbo_ngdp!C13 -> #N/A | D13: =100*cbo_debt!D13/cbo_ngdp!D13 -> 14.805023 | E13: =100*cbo_debt!E13/cbo_ngdp!E13 -> 18.544982 | F13: =100*cbo_debt!F13/cbo_ngdp!F13 -> 22.954473 | G13: =100*cbo_debt!G13/cbo_ngdp!G13 -> 24.5 | H13: =100*cbo_debt!H13/cbo_ngdp!H13 -> 23.7 | I13: =100*cbo_debt!I13/cbo_ngdp!I13 -> 29.888372 | J13: =100*cbo_debt!J13/cbo_ngdp!B13 -> #N/A | K13: =100*cbo_debt!K13/cbo_ngdp!K13 -> #N/A | L13: =100*cbo_debt!L13/cbo_ngdp!L13 -> #N/A | M13: =100*cbo_debt!M13/cbo_ngdp!M13 -> #N/A | N13: =100*cbo_debt!N13/cbo_ngdp!N13 -> #N/A | O13: =100*cbo_debt!O13/cbo_ngdp!O13 -> #N/A | P13: =100*cbo_debt!P13/cbo_ngdp!P13 -> #N/A | Q13: =100*cbo_debt!Q13/cbo_ngdp!Q13 -> #N/A | R13: =100*cbo_debt!R13/cbo_ngdp!R13 -> #N/A | ... AT13: =100*cbo_debt!AT13/cbo_ngdp!AT13 -> #N/A | AU13: #N/A | AV13: =100*cbo_debt!AV13/cbo_ngdp!AV13 -> #N/A | AW13: #N/A | AX13: #N/A | AY13: #N/A | AZ13: #N/A | BA13: #N/A | BB13: #N/A | BC13: #N/A | BD13: #N/A | BE13: #N/A | BF13: #N/A | BG13: #N/A | BH13: #N/A | BI13: #N/A | BJ13: #N/A | BK13: #N/A | BL13: #N/A | BM13: #N/A | BN13: #N/A | BO13: #N/A | BP13: #N/A | BQ13: #N/A | BR13: #N/A | BS13: #N/A | BT13: #N/A | BU13: #N/A | BV13: #N/A | BW13: #N/A | BX13: #N/A | BY13: #N/A | BZ13: #N/A | CA13: #N/A | CB13: #N/A | CC13: #N/A | CD13: #N/A | CE13: #N/A | CF13: #N/A | CG13: #N/A | CH13: #N/A | CI13: #N/A | CJ13: #N/A | CK13: #N/A | CL13: #N/A | CM13: #N/A | CN13: #N/A | CO13: #N/A | CP13: #N/A | CQ13: #N/A | CR13: #N/A | CS13: 27.920314 | CU13: 29983 | CV13: =OFFSET(C$1,0,ROWS($1:7)-1) -> 1982A | CW13: =LEFT(CV13,4)+$CW$5 -> 1982 | CX13: {=INDEX($C$6:$CS$100,MATCH(CW13,YEAR($B$6:$B$100),0),MATCH(CV13,$C$1:$CS$1,0))} -> 29.888372 | CY13: =LEFT(CV13,4)+$CY$5 -> 1987 | CZ13: {=INDEX($C$6:$CS$100,MATCH(CY13,YEAR($B$6:$B$100),0),MATCH(CV13,$C$1:$CS$1,0))} -> 41 | DA13: =LEFT(CV13,4)+$DA$5 -> 1992 | DB13: {=INDEX($C$6:$CS$100,MATCH(DA13,YEAR($B$6:$B$100),0),MATCH(CV13,$C$1:$CS$1,0))} -> #N/A | DD13: =VLOOKUP(DATE(CW13,1,1),$B$6:$CS$66,96,FALSE) -> 27.920314 | DE13: =VLOOKUP(DATE(CY13,1,1),$B$6:$CS$66,96,FALSE) -> 39.639262 | DF13: =(DD13-CX13)^2 -> 3.873253 | DG13: =(DE13-CZ13)^2 -> 1.8516086
A14: 1983 | B14: 30317 | C14: =100*cbo_debt!C14/cbo_ngdp!C14 -> #N/A | D14: =100*cbo_debt!D14/cbo_ngdp!D14 -> #N/A | E14: =100*cbo_debt!E14/cbo_ngdp!E14 -> 14.02421 | F14: =100*cbo_debt!F14/cbo_ngdp!F14 -> 19.376965 | G14: =100*cbo_debt!G14/cbo_ngdp!G14 -> 22.213388 | H14: =100*cbo_debt!H14/cbo_ngdp!H14 -> 21.444444 | I14: =100*cbo_debt!I14/cbo_ngdp!I14 -> 31.701136 | J14: 35.6 | K14: =100*cbo_debt!K14/cbo_ngdp!K14 -> #N/A | L14: =100*cbo_debt!L14/cbo_ngdp!L14 -> #N/A | M14: =100*cbo_debt!M14/cbo_ngdp!M14 -> #N/A | N14: =100*cbo_debt!N14/cbo_ngdp!N14 -> #N/A | O14: =100*cbo_debt!O14/cbo_ngdp!O14 -> #N/A | P14: =100*cbo_debt!P14/cbo_ngdp!P14 -> #N/A | Q14: =100*cbo_debt!Q14/cbo_ngdp!Q14 -> #N/A | R14: =100*cbo_debt!R14/cbo_ngdp!R14 -> #N/A | ... AT14: =100*cbo_debt!AT14/cbo_ngdp!AT14 -> #N/A | AU14: #N/A | AV14: =100*cbo_debt!AV14/cbo_ngdp!AV14 -> #N/A | AW14: #N/A | AX14: #N/A | AY14: #N/A | AZ14: #N/A | BA14: #N/A | BB14: #N/A | BC14: #N/A | BD14: #N/A | BE14: #N/A | BF14: #N/A | BG14: #N/A | BH14: #N/A | BI14: #N/A | BJ14: #N/A | BK14: #N/A | BL14: #N/A | BM14: #N/A | BN14: #N/A | BO14: #N/A | BP14: #N/A | BQ14: #N/A | BR14: #N/A | BS14: #N/A | BT14: #N/A | BU14: #N/A | BV14: #N/A | BW14: #N/A | BX14: #N/A | BY14: #N/A | BZ14: #N/A | CA14: #N/A | CB14: #N/A | CC14: #N/A | CD14: #N/A | CE14: #N/A | CF14: #N/A | CG14: #N/A | CH14: #N/A | CI14: #N/A | CJ14: #N/A | CK14: #N/A | CL14: #N/A | CM14: #N/A | CN14: #N/A | CO14: #N/A | CP14: #N/A | CQ14: #N/A | CR14: #N/A | CS14: 32.154977 | CU14: 30348 | CV14: =OFFSET(C$1,0,ROWS($1:8)-1) -> 1983A | CW14: =LEFT(CV14,4)+$CW$5 -> 1983 | CX14: {=INDEX($C$6:$CS$100,MATCH(CW14,YEAR($B$6:$B$100),0),MATCH(CV14,$C$1:$CS$1,0))} -> 35.6 | CY14: =LEFT(CV14,4)+$CY$5 -> 1988 | CZ14: {=INDEX($C$6:$CS$100,MATCH(CY14,YEAR($B$6:$B$100),0),MATCH(CV14,$C$1:$CS$1,0))} -> 49.5 | DA14: =LEFT(CV14,4)+$DA$5 -> 1993 | DB14: {=INDEX($C$6:$CS$100,MATCH(DA14,YEAR($B$6:$B$100),0),MATCH(CV14,$C$1:$CS$1,0))} -> #N/A | DD14: =VLOOKUP(DATE(CW14,1,1),$B$6:$CS$66,96,FALSE) -> 32.154977 | DE14: =VLOOKUP(DATE(CY14,1,1),$B$6:$CS$66,96,FALSE) -> 39.929947 | DF14: =(DD14-CX14)^2 -> 11.868181 | DG14: =(DE14-CZ14)^2 -> 91.585906
A15: 1984 | B15: 30682 | C15: =100*cbo_debt!C15/cbo_ngdp!C15 -> #N/A | D15: =100*cbo_debt!D15/cbo_ngdp!D15 -> #N/A | E15: =100*cbo_debt!E15/cbo_ngdp!E15 -> #N/A | F15: =100*cbo_debt!F15/cbo_ngdp!F15 -> 15.02444 | G15: =100*cbo_debt!G15/cbo_ngdp!G15 -> 19.345455 | H15: =100*cbo_debt!H15/cbo_ngdp!H15 -> 17.4 | I15: =100*cbo_debt!I15/cbo_ngdp!I15 -> 34.07767 | J15: 38.3 | K15: =100*cbo_debt!K15/cbo_ngdp!K15 -> 37.243896 | L15: =100*cbo_debt!L15/cbo_ngdp!L15 -> #N/A | M15: =100*cbo_debt!M15/cbo_ngdp!M15 -> #N/A | N15: =100*cbo_debt!N15/cbo_ngdp!N15 -> #N/A | O15: =100*cbo_debt!O15/cbo_ngdp!O15 -> #N/A | P15: =100*cbo_debt!P15/cbo_ngdp!P15 -> #N/A | Q15: =100*cbo_debt!Q15/cbo_ngdp!Q15 -> #N/A | R15: =100*cbo_debt!R15/cbo_ngdp!R15 -> #N/A | ... AT15: =100*cbo_debt!AT15/cbo_ngdp!AT15 -> #N/A | AU15: #N/A | AV15: =100*cbo_debt!AV15/cbo_ngdp!AV15 -> #N/A | AW15: #N/A | AX15: #N/A | AY15: #N/A | AZ15: #N/A | BA15: #N/A | BB15: #N/A | BC15: #N/A | BD15: #N/A | BE15: #N/A | BF15: #N/A | BG15: #N/A | BH15: #N/A | BI15: #N/A | BJ15: #N/A | BK15: #N/A | BL15: #N/A | BM15: #N/A | BN15: #N/A | BO15: #N/A | BP15: #N/A | BQ15: #N/A | BR15: #N/A | BS15: #N/A | BT15: #N/A | BU15: #N/A | BV15: #N/A | BW15: #N/A | BX15: #N/A | BY15: #N/A | BZ15: #N/A | CA15: #N/A | CB15: #N/A | CC15: #N/A | CD15: #N/A | CE15: #N/A | CF15: #N/A | CG15: #N/A | CH15: #N/A | CI15: #N/A | CJ15: #N/A | CK15: #N/A | CL15: #N/A | CM15: #N/A | CN15: #N/A | CO15: #N/A | CP15: #N/A | CQ15: #N/A | CR15: #N/A | CS15: 33.096987 | CU15: 30713 | CV15: =OFFSET(C$1,0,ROWS($1:9)-1) -> 1984A | CW15: =LEFT(CV15,4)+$CW$5 -> 1984 | CX15: {=INDEX($C$6:$CS$100,MATCH(CW15,YEAR($B$6:$B$100),0),MATCH(CV15,$C$1:$CS$1,0))} -> 37.243896 | CY15: =LEFT(CV15,4)+$CY$5 -> 1989 | CZ15: {=INDEX($C$6:$CS$100,MATCH(CY15,YEAR($B$6:$B$100),0),MATCH(CV15,$C$1:$CS$1,0))} -> 49.377208 | DA15: =LEFT(CV15,4)+$DA$5 -> 1994 | DB15: {=INDEX($C$6:$CS$100,MATCH(DA15,YEAR($B$6:$B$100),0),MATCH(CV15,$C$1:$CS$1,0))} -> #N/A | DD15: =VLOOKUP(DATE(CW15,1,1),$B$6:$CS$66,96,FALSE) -> 33.096987 | DE15: =VLOOKUP(DATE(CY15,1,1),$B$6:$CS$66,96,FALSE) -> 39.441944 | DF15: =(DD15-CX15)^2 -> 17.196854 | DG15: =(DE15-CZ15)^2 -> 98.70946
A16: 1985 | B16: 31048 | C16: =100*cbo_debt!C16/cbo_ngdp!C16 -> #N/A | D16: =100*cbo_debt!D16/cbo_ngdp!D16 -> #N/A | E16: =100*cbo_debt!E16/cbo_ngdp!E16 -> #N/A | F16: =100*cbo_debt!F16/cbo_ngdp!F16 -> #N/A | G16: =100*cbo_debt!G16/cbo_ngdp!G16 -> 15.871658 | H16: =100*cbo_debt!H16/cbo_ngdp!H16 -> 12.534783 | I16: =100*cbo_debt!I16/cbo_ngdp!I16 -> 36.461947 | J16: 41.1 | K16: =100*cbo_debt!K16/cbo_ngdp!K16 -> 39.232737 | L16: =100*cbo_debt!L16/cbo_ngdp!L16 -> 39.584955 | M16: =100*cbo_debt!M16/cbo_ngdp!M16 -> 39.635417 | N16: =100*cbo_debt!N16/cbo_ngdp!N16 -> #N/A | O16: =100*cbo_debt!O16/cbo_ngdp!O16 -> #N/A | P16: =100*cbo_debt!P16/cbo_ngdp!P16 -> #N/A | Q16: =100*cbo_debt!Q16/cbo_ngdp!Q16 -> #N/A | R16: =100*cbo_debt!R16/cbo_ngdp!R16 -> #N/A | ... AT16: =100*cbo_debt!AT16/cbo_ngdp!AT16 -> #N/A | AU16: #N/A | AV16: =100*cbo_debt!AV16/cbo_ngdp!AV16 -> #N/A | AW16: #N/A | AX16: #N/A | AY16: #N/A | AZ16: #N/A | BA16: #N/A | BB16: #N/A | BC16: #N/A | BD16: #N/A | BE16: #N/A | BF16: #N/A | BG16: #N/A | BH16: #N/A | BI16: #N/A | BJ16: #N/A | BK16: #N/A | BL16: #N/A | BM16: #N/A | BN16: #N/A | BO16: #N/A | BP16: #N/A | BQ16: #N/A | BR16: #N/A | BS16: #N/A | BT16: #N/A | BU16: #N/A | BV16: #N/A | BW16: #N/A | BX16: #N/A | BY16: #N/A | BZ16: #N/A | CA16: #N/A | CB16: #N/A | CC16: #N/A | CD16: #N/A | CE16: #N/A | CF16: #N/A | CG16: #N/A | CH16: #N/A | CI16: #N/A | CJ16: #N/A | CK16: #N/A | CL16: #N/A | CM16: #N/A | CN16: #N/A | CO16: #N/A | CP16: #N/A | CQ16: #N/A | CR16: #N/A | CS16: 35.334115 | CU16: 31079 | CV16: =OFFSET(C$1,0,ROWS($1:10)-1) -> 1985A | CW16: =LEFT(CV16,4)+$CW$5 -> 1985 | CX16: {=INDEX($C$6:$CS$100,MATCH(CW16,YEAR($B$6:$B$100),0),MATCH(CV16,$C$1:$CS$1,0))} -> 39.584955 | CY16: =LEFT(CV16,4)+$CY$5 -> 1990 | CZ16: {=INDEX($C$6:$CS$100,MATCH(CY16,YEAR($B$6:$B$100),0),MATCH(CV16,$C$1:$CS$1,0))} -> 49.696753 | DA16: =LEFT(CV16,4)+$DA$5 -> 1995 | DB16: {=INDEX($C$6:$CS$100,MATCH(DA16,YEAR($B$6:$B$100),0),MATCH(CV16,$C$1:$CS$1,0))} -> #N/A | DD16: =VLOOKUP(DATE(CW16,1,1),$B$6:$CS$66,96,FALSE) -> 35.334115 | DE16: =VLOOKUP(DATE(CY16,1,1),$B$6:$CS$66,96,FALSE) -> 40.888286 | DF16: =(DD16-CX16)^2 -> 18.069638 | DG16: =(DE16-CZ16)^2 -> 77.589097
A17: 1986 | B17: 31413 | C17: =100*cbo_debt!C17/cbo_ngdp!C17 -> #N/A | D17: =100*cbo_debt!D17/cbo_ngdp!D17 -> #N/A | E17: =100*cbo_debt!E17/cbo_ngdp!E17 -> #N/A | F17: =100*cbo_debt!F17/cbo_ngdp!F17 -> #N/A | G17: =100*cbo_debt!G17/cbo_ngdp!G17 -> #N/A | H17: =100*cbo_debt!H17/cbo_ngdp!H17 -> 7.1803828 | I17: =100*cbo_debt!I17/cbo_ngdp!I17 -> 39.244094 | J17: 43.9 | K17: =100*cbo_debt!K17/cbo_ngdp!K17 -> 41.472595 | L17: =100*cbo_debt!L17/cbo_ngdp!L17 -> 41.847042 | M17: =100*cbo_debt!M17/cbo_ngdp!M17 -> 41.106815 | N17: =100*cbo_debt!N17/cbo_ngdp!N17 -> 41.030534 | O17: =100*cbo_debt!O17/cbo_ngdp!O17 -> 41.762728 | P17: =100*cbo_debt!P17/cbo_ngdp!P17 -> #N/A | Q17: =100*cbo_debt!Q17/cbo_ngdp!Q17 -> #N/A | R17: =100*cbo_debt!R17/cbo_ngdp!R17 -> #N/A | ... AT17: =100*cbo_debt!AT17/cbo_ngdp!AT17 -> #N/A | AU17: #N/A | AV17: =100*cbo_debt!AV17/cbo_ngdp!AV17 -> #N/A | AW17: #N/A | AX17: #N/A | AY17: #N/A | AZ17: #N/A | BA17: #N/A | BB17: #N/A | BC17: #N/A | BD17: #N/A | BE17: #N/A | BF17: #N/A | BG17: #N/A | BH17: #N/A | BI17: #N/A | BJ17: #N/A | BK17: #N/A | BL17: #N/A | BM17: #N/A | BN17: #N/A | BO17: #N/A | BP17: #N/A | BQ17: #N/A | BR17: #N/A | BS17: #N/A | BT17: #N/A | BU17: #N/A | BV17: #N/A | BW17: #N/A | BX17: #N/A | BY17: #N/A | BZ17: #N/A | CA17: #N/A | CB17: #N/A | CC17: #N/A | CD17: #N/A | CE17: #N/A | CF17: #N/A | CG17: #N/A | CH17: #N/A | CI17: #N/A | CJ17: #N/A | CK17: #N/A | CL17: #N/A | CM17: #N/A | CN17: #N/A | CO17: #N/A | CP17: #N/A | CQ17: #N/A | CR17: #N/A | CS17: 38.466637 | CU17: 31260 | CV17: =OFFSET(C$1,0,ROWS($1:11)-1) -> 1985B | CW17: =LEFT(CV17,4)+$CW$5 -> 1985 | CX17: {=INDEX($C$6:$CS$100,MATCH(CW17,YEAR($B$6:$B$100),0),MATCH(CV17,$C$1:$CS$1,0))} -> 39.635417 | CY17: =LEFT(CV17,4)+$CY$5 -> 1990 | CZ17: {=INDEX($C$6:$CS$100,MATCH(CY17,YEAR($B$6:$B$100),0),MATCH(CV17,$C$1:$CS$1,0))} -> 40.235841 | DA17: =LEFT(CV17,4)+$DA$5 -> 1995 | DB17: {=INDEX($C$6:$CS$100,MATCH(DA17,YEAR($B$6:$B$100),0),MATCH(CV17,$C$1:$CS$1,0))} -> #N/A | DD17: =VLOOKUP(DATE(CW17,1,1),$B$6:$CS$66,96,FALSE) -> 35.334115 | DE17: =VLOOKUP(DATE(CY17,1,1),$B$6:$CS$66,96,FALSE) -> 40.888286 | DF17: =(DD17-CX17)^2 -> 18.501197 | DG17: =(DE17-CZ17)^2 -> 0.42568516
A18: 1987 | B18: 31778 | C18: =100*cbo_debt!C18/cbo_ngdp!C18 -> #N/A | D18: =100*cbo_debt!D18/cbo_ngdp!D18 -> #N/A | E18: =100*cbo_debt!E18/cbo_ngdp!E18 -> #N/A | F18: =100*cbo_debt!F18/cbo_ngdp!F18 -> #N/A | G18: =100*cbo_debt!G18/cbo_ngdp!G18 -> #N/A | H18: =100*cbo_debt!H18/cbo_ngdp!H18 -> #N/A | I18: =100*cbo_debt!I18/cbo_ngdp!I18 -> 41 | J18: 46.8 | K18: =100*cbo_debt!K18/cbo_ngdp!K18 -> 43.885516 | L18: =100*cbo_debt!L18/cbo_ngdp!L18 -> 43.988401 | M18: =100*cbo_debt!M18/cbo_ngdp!M18 -> 41.707754 | N18: =100*cbo_debt!N18/cbo_ngdp!N18 -> 42.184725 | O18: =100*cbo_debt!O18/cbo_ngdp!O18 -> 43.499887 | P18: =100*cbo_debt!P18/cbo_ngdp!P18 -> 43.418959 | Q18: =100*cbo_debt!Q18/cbo_ngdp!Q18 -> 43.116353 | R18: =100*cbo_debt!R18/cbo_ngdp!R18 -> #N/A | ... AT18: =100*cbo_debt!AT18/cbo_ngdp!AT18 -> #N/A | AU18: #N/A | AV18: =100*cbo_debt!AV18/cbo_ngdp!AV18 -> #N/A | AW18: #N/A | AX18: #N/A | AY18: #N/A | AZ18: #N/A | BA18: #N/A | BB18: #N/A | BC18: #N/A | BD18: #N/A | BE18: #N/A | BF18: #N/A | BG18: #N/A | BH18: #N/A | BI18: #N/A | BJ18: #N/A | BK18: #N/A | BL18: #N/A | BM18: #N/A | BN18: #N/A | BO18: #N/A | BP18: #N/A | BQ18: #N/A | BR18: #N/A | BS18: #N/A | BT18: #N/A | BU18: #N/A | BV18: #N/A | BW18: #N/A | BX18: #N/A | BY18: #N/A | BZ18: #N/A | CA18: #N/A | CB18: #N/A | CC18: #N/A | CD18: #N/A | CE18: #N/A | CF18: #N/A | CG18: #N/A | CH18: #N/A | CI18: #N/A | CJ18: #N/A | CK18: #N/A | CL18: #N/A | CM18: #N/A | CN18: #N/A | CO18: #N/A | CP18: #N/A | CQ18: #N/A | CR18: #N/A | CS18: 39.639262 | CU18: 31444 | CV18: =OFFSET(C$1,0,ROWS($1:12)-1) -> 1986A | CW18: =LEFT(CV18,4)+$CW$5 -> 1986 | CX18: {=INDEX($C$6:$CS$100,MATCH(CW18,YEAR($B$6:$B$100),0),MATCH(CV18,$C$1:$CS$1,0))} -> 41.030534 | CY18: =LEFT(CV18,4)+$CY$5 -> 1991 | CZ18: {=INDEX($C$6:$CS$100,MATCH(CY18,YEAR($B$6:$B$100),0),MATCH(CV18,$C$1:$CS$1,0))} -> 40.168679 | DA18: =LEFT(CV18,4)+$DA$5 -> 1996 | DB18: {=INDEX($C$6:$CS$100,MATCH(DA18,YEAR($B$6:$B$100),0),MATCH(CV18,$C$1:$CS$1,0))} -> #N/A | DD18: =VLOOKUP(DATE(CW18,1,1),$B$6:$CS$66,96,FALSE) -> 38.466637 | DE18: =VLOOKUP(DATE(CY18,1,1),$B$6:$CS$66,96,FALSE) -> 44.132611 | DF18: =(DD18-CX18)^2 -> 6.5735686 | DG18: =(DE18-CZ18)^2 -> 15.712761
A19: 1988 | B19: 32143 | C19: =100*cbo_debt!C19/cbo_ngdp!C19 -> #N/A | D19: =100*cbo_debt!D19/cbo_ngdp!D19 -> #N/A | E19: =100*cbo_debt!E19/cbo_ngdp!E19 -> #N/A | F19: =100*cbo_debt!F19/cbo_ngdp!F19 -> #N/A | G19: =100*cbo_debt!G19/cbo_ngdp!G19 -> #N/A | H19: =100*cbo_debt!H19/cbo_ngdp!H19 -> #N/A | I19: =100*cbo_debt!I19/cbo_ngdp!I19 -> #N/A | J19: 49.5 | K19: =100*cbo_debt!K19/cbo_ngdp!K19 -> 46.48085 | L19: =100*cbo_debt!L19/cbo_ngdp!L19 -> 45.962733 | M19: =100*cbo_debt!M19/cbo_ngdp!M19 -> 41.595678 | N19: =100*cbo_debt!N19/cbo_ngdp!N19 -> 42.662257 | O19: =100*cbo_debt!O19/cbo_ngdp!O19 -> 43.572481 | P19: =100*cbo_debt!P19/cbo_ngdp!P19 -> 44.210302 | Q19: =100*cbo_debt!Q19/cbo_ngdp!Q19 -> 44.022891 | R19: =100*cbo_debt!R19/cbo_ngdp!R19 -> 43.629756 | ... AT19: =100*cbo_debt!AT19/cbo_ngdp!AT19 -> #N/A | AU19: #N/A | AV19: =100*cbo_debt!AV19/cbo_ngdp!AV19 -> #N/A | AW19: #N/A | AX19: #N/A | AY19: #N/A | AZ19: #N/A | BA19: #N/A | BB19: #N/A | BC19: #N/A | BD19: #N/A | BE19: #N/A | BF19: #N/A | BG19: #N/A | BH19: #N/A | BI19: #N/A | BJ19: #N/A | BK19: #N/A | BL19: #N/A | BM19: #N/A | BN19: #N/A | BO19: #N/A | BP19: #N/A | BQ19: #N/A | BR19: #N/A | BS19: #N/A | BT19: #N/A | BU19: #N/A | BV19: #N/A | BW19: #N/A | BX19: #N/A | BY19: #N/A | BZ19: #N/A | CA19: #N/A | CB19: #N/A | CC19: #N/A | CD19: #N/A | CE19: #N/A | CF19: #N/A | CG19: #N/A | CH19: #N/A | CI19: #N/A | CJ19: #N/A | CK19: #N/A | CL19: #N/A | CM19: #N/A | CN19: #N/A | CO19: #N/A | CP19: #N/A | CQ19: #N/A | CR19: #N/A | CS19: 39.929947 | CU19: 31625 | CV19: =OFFSET(C$1,0,ROWS($1:13)-1) -> 1986B | CW19: =LEFT(CV19,4)+$CW$5 -> 1986 | CX19: {=INDEX($C$6:$CS$100,MATCH(CW19,YEAR($B$6:$B$100),0),MATCH(CV19,$C$1:$CS$1,0))} -> 41.762728 | CY19: =LEFT(CV19,4)+$CY$5 -> 1991 | CZ19: {=INDEX($C$6:$CS$100,MATCH(CY19,YEAR($B$6:$B$100),0),MATCH(CV19,$C$1:$CS$1,0))} -> 40.12934 | DA19: =LEFT(CV19,4)+$DA$5 -> 1996 | DB19: {=INDEX($C$6:$CS$100,MATCH(DA19,YEAR($B$6:$B$100),0),MATCH(CV19,$C$1:$CS$1,0))} -> #N/A | DD19: =VLOOKUP(DATE(CW19,1,1),$B$6:$CS$66,96,FALSE) -> 38.466637 | DE19: =VLOOKUP(DATE(CY19,1,1),$B$6:$CS$66,96,FALSE) -> 44.132611 | DF19: =(DD19-CX19)^2 -> 10.864215 | DG19: =(DE19-CZ19)^2 -> 16.026183
A20: 1989 | B20: 32509 | C20: =100*cbo_debt!C20/cbo_ngdp!C20 -> #N/A | D20: =100*cbo_debt!D20/cbo_ngdp!D20 -> #N/A | E20: =100*cbo_debt!E20/cbo_ngdp!E20 -> #N/A | F20: =100*cbo_debt!F20/cbo_ngdp!F20 -> #N/A | G20: =100*cbo_debt!G20/cbo_ngdp!G20 -> #N/A | H20: =100*cbo_debt!H20/cbo_ngdp!H20 -> #N/A | I20: =100*cbo_debt!I20/cbo_ngdp!I20 -> #N/A | J20: =100*cbo_debt!J20/cbo_ngdp!B20 -> #N/A | K20: =100*cbo_debt!K20/cbo_ngdp!K20 -> 49.377208 | L20: =100*cbo_debt!L20/cbo_ngdp!L20 -> 47.847809 | M20: =100*cbo_debt!M20/cbo_ngdp!M20 -> 41.098266 | N20: =100*cbo_debt!N20/cbo_ngdp!N20 -> 42.328347 | O20: =100*cbo_debt!O20/cbo_ngdp!O20 -> 43.022344 | P20: =100*cbo_debt!P20/cbo_ngdp!P20 -> 44.426783 | Q20: =100*cbo_debt!Q20/cbo_ngdp!Q20 -> 45.004965 | R20: =100*cbo_debt!R20/cbo_ngdp!R20 -> 44.462279 | ... AT20: =100*cbo_debt!AT20/cbo_ngdp!AT20 -> #N/A | AU20: #N/A | AV20: =100*cbo_debt!AV20/cbo_ngdp!AV20 -> #N/A | AW20: #N/A | AX20: #N/A | AY20: #N/A | AZ20: #N/A | BA20: #N/A | BB20: #N/A | BC20: #N/A | BD20: #N/A | BE20: #N/A | BF20: #N/A | BG20: #N/A | BH20: #N/A | BI20: #N/A | BJ20: #N/A | BK20: #N/A | BL20: #N/A | BM20: #N/A | BN20: #N/A | BO20: #N/A | BP20: #N/A | BQ20: #N/A | BR20: #N/A | BS20: #N/A | BT20: #N/A | BU20: #N/A | BV20: #N/A | BW20: #N/A | BX20: #N/A | BY20: #N/A | BZ20: #N/A | CA20: #N/A | CB20: #N/A | CC20: #N/A | CD20: #N/A | CE20: #N/A | CF20: #N/A | CG20: #N/A | CH20: #N/A | CI20: #N/A | CJ20: #N/A | CK20: #N/A | CL20: #N/A | CM20: #N/A | CN20: #N/A | CO20: #N/A | CP20: #N/A | CQ20: #N/A | CR20: #N/A | CS20: 39.441944 | CU20: 31778 | CV20: =OFFSET(C$1,0,ROWS($1:14)-1) -> 1987A | CW20: =LEFT(CV20,4)+$CW$5 -> 1987 | CX20: {=INDEX($C$6:$CS$100,MATCH(CW20,YEAR($B$6:$B$100),0),MATCH(CV20,$C$1:$CS$1,0))} -> 43.418959 | CY20: =LEFT(CV20,4)+$CY$5 -> 1992 | CZ20: {=INDEX($C$6:$CS$100,MATCH(CY20,YEAR($B$6:$B$100),0),MATCH(CV20,$C$1:$CS$1,0))} -> 41.319108 | DA20: =LEFT(CV20,4)+$DA$5 -> 1997 | DB20: {=INDEX($C$6:$CS$100,MATCH(DA20,YEAR($B$6:$B$100),0),MATCH(CV20,$C$1:$CS$1,0))} -> #N/A | DD20: =VLOOKUP(DATE(CW20,1,1),$B$6:$CS$66,96,FALSE) -> 39.639262 | DE20: =VLOOKUP(DATE(CY20,1,1),$B$6:$CS$66,96,FALSE) -> 46.758105 | DF20: =(DD20-CX20)^2 -> 14.28611 | DG20: =(DE20-CZ20)^2 -> 29.582689
A21: 1990 | B21: 32874 | C21: =100*cbo_debt!C21/cbo_ngdp!C21 -> #N/A | D21: =100*cbo_debt!D21/cbo_ngdp!D21 -> #N/A | E21: =100*cbo_debt!E21/cbo_ngdp!E21 -> #N/A | F21: =100*cbo_debt!F21/cbo_ngdp!F21 -> #N/A | G21: =100*cbo_debt!G21/cbo_ngdp!G21 -> #N/A | H21: =100*cbo_debt!H21/cbo_ngdp!H21 -> #N/A | I21: =100*cbo_debt!I21/cbo_ngdp!I21 -> #N/A | J21: =100*cbo_debt!J21/cbo_ngdp!B21 -> #N/A | K21: =100*cbo_debt!K21/cbo_ngdp!K21 -> #N/A | L21: =100*cbo_debt!L21/cbo_ngdp!L21 -> 49.696753 | M21: =100*cbo_debt!M21/cbo_ngdp!M21 -> 40.235841 | N21: =100*cbo_debt!N21/cbo_ngdp!N21 -> 41.395266 | O21: =100*cbo_debt!O21/cbo_ngdp!O21 -> 41.811211 | P21: =100*cbo_debt!P21/cbo_ngdp!P21 -> 43.784684 | Q21: =100*cbo_debt!Q21/cbo_ngdp!Q21 -> 45.35316 | R21: =100*cbo_debt!R21/cbo_ngdp!R21 -> 44.723995 | ... AT21: =100*cbo_debt!AT21/cbo_ngdp!AT21 -> #N/A | AU21: #N/A | AV21: =100*cbo_debt!AV21/cbo_ngdp!AV21 -> #N/A | AW21: #N/A | AX21: #N/A | AY21: #N/A | AZ21: #N/A | BA21: #N/A | BB21: #N/A | BC21: #N/A | BD21: #N/A | BE21: #N/A | BF21: #N/A | BG21: #N/A | BH21: #N/A | BI21: #N/A | BJ21: #N/A | BK21: #N/A | BL21: #N/A | BM21: #N/A | BN21: #N/A | BO21: #N/A | BP21: #N/A | BQ21: #N/A | BR21: #N/A | BS21: #N/A | BT21: #N/A | BU21: #N/A | BV21: #N/A | BW21: #N/A | BX21: #N/A | BY21: #N/A | BZ21: #N/A | CA21: #N/A | CB21: #N/A | CC21: #N/A | CD21: #N/A | CE21: #N/A | CF21: #N/A | CG21: #N/A | CH21: #N/A | CI21: #N/A | CJ21: #N/A | CK21: #N/A | CL21: #N/A | CM21: #N/A | CN21: #N/A | CO21: #N/A | CP21: #N/A | CQ21: #N/A | CR21: #N/A | CS21: 40.888286 | CU21: 31990 | CV21: =OFFSET(C$1,0,ROWS($1:15)-1) -> 1987B | CW21: =LEFT(CV21,4)+$CW$5 -> 1987 | CX21: {=INDEX($C$6:$CS$100,MATCH(CW21,YEAR($B$6:$B$100),0),MATCH(CV21,$C$1:$CS$1,0))} -> 43.116353 | CY21: =LEFT(CV21,4)+$CY$5 -> 1992 | CZ21: {=INDEX($C$6:$CS$100,MATCH(CY21,YEAR($B$6:$B$100),0),MATCH(CV21,$C$1:$CS$1,0))} -> 44.78098 | DA21: =LEFT(CV21,4)+$DA$5 -> 1997 | DB21: {=INDEX($C$6:$CS$100,MATCH(DA21,YEAR($B$6:$B$100),0),MATCH(CV21,$C$1:$CS$1,0))} -> #N/A | DD21: =VLOOKUP(DATE(CW21,1,1),$B$6:$CS$66,96,FALSE) -> 39.639262 | DE21: =VLOOKUP(DATE(CY21,1,1),$B$6:$CS$66,96,FALSE) -> 46.758105 | DF21: =(DD21-CX21)^2 -> 12.090163 | DG21: =(DE21-CZ21)^2 -> 3.9090211
A22: 1991 | B22: 33239 | C22: =100*cbo_debt!C22/cbo_ngdp!C22 -> #N/A | D22: =100*cbo_debt!D22/cbo_ngdp!D22 -> #N/A | E22: =100*cbo_debt!E22/cbo_ngdp!E22 -> #N/A | F22: =100*cbo_debt!F22/cbo_ngdp!F22 -> #N/A | G22: =100*cbo_debt!G22/cbo_ngdp!G22 -> #N/A | H22: =100*cbo_debt!H22/cbo_ngdp!H22 -> #N/A | I22: =100*cbo_debt!I22/cbo_ngdp!I22 -> #N/A | J22: =100*cbo_debt!J22/cbo_ngdp!B22 -> #N/A | K22: =100*cbo_debt!K22/cbo_ngdp!K22 -> #N/A | L22: =100*cbo_debt!L22/cbo_ngdp!L22 -> #N/A | M22: =100*cbo_debt!M22/cbo_ngdp!M22 -> #N/A | N22: =100*cbo_debt!N22/cbo_ngdp!N22 -> 40.168679 | O22: =100*cbo_debt!O22/cbo_ngdp!O22 -> 40.12934 | P22: =100*cbo_debt!P22/cbo_ngdp!P22 -> 42.696823 | Q22: =100*cbo_debt!Q22/cbo_ngdp!Q22 -> 45.258396 | R22: =100*cbo_debt!R22/cbo_ngdp!R22 -> 44.610515 | ... AT22: =100*cbo_debt!AT22/cbo_ngdp!AT22 -> #N/A | AU22: #N/A | AV22: =100*cbo_debt!AV22/cbo_ngdp!AV22 -> #N/A | AW22: #N/A | AX22: #N/A | AY22: #N/A | AZ22: #N/A | BA22: #N/A | BB22: #N/A | BC22: #N/A | BD22: #N/A | BE22: #N/A | BF22: #N/A | BG22: #N/A | BH22: #N/A | BI22: #N/A | BJ22: #N/A | BK22: #N/A | BL22: #N/A | BM22: #N/A | BN22: #N/A | BO22: #N/A | BP22: #N/A | BQ22: #N/A | BR22: #N/A | BS22: #N/A | BT22: #N/A | BU22: #N/A | BV22: #N/A | BW22: #N/A | BX22: #N/A | BY22: #N/A | BZ22: #N/A | CA22: #N/A | CB22: #N/A | CC22: #N/A | CD22: #N/A | CE22: #N/A | CF22: #N/A | CG22: #N/A | CH22: #N/A | CI22: #N/A | CJ22: #N/A | CK22: #N/A | CL22: #N/A | CM22: #N/A | CN22: #N/A | CO22: #N/A | CP22: #N/A | CQ22: #N/A | CR22: #N/A | CS22: 44.132611 | CU22: 32174 | CV22: =OFFSET(C$1,0,ROWS($1:16)-1) -> 1988A | CW22: =LEFT(CV22,4)+$CW$5 -> 1988 | CX22: {=INDEX($C$6:$CS$100,MATCH(CW22,YEAR($B$6:$B$100),0),MATCH(CV22,$C$1:$CS$1,0))} -> 43.629756 | CY22: =LEFT(CV22,4)+$CY$5 -> 1993 | CZ22: {=INDEX($C$6:$CS$100,MATCH(CY22,YEAR($B$6:$B$100),0),MATCH(CV22,$C$1:$CS$1,0))} -> 43.404648 | DA22: =LEFT(CV22,4)+$DA$5 -> 1998 | DB22: {=INDEX($C$6:$CS$100,MATCH(DA22,YEAR($B$6:$B$100),0),MATCH(CV22,$C$1:$CS$1,0))} -> #N/A | DD22: =VLOOKUP(DATE(CW22,1,1),$B$6:$CS$66,96,FALSE) -> 39.929947 | DE22: =VLOOKUP(DATE(CY22,1,1),$B$6:$CS$66,96,FALSE) -> 47.940959 | DF22: =(DD22-CX22)^2 -> 13.688585 | DG22: =(DE22-CZ22)^2 -> 20.578118
A23: 1992 | B23: 33604 | C23: =100*cbo_debt!C23/cbo_ngdp!C23 -> #N/A | D23: =100*cbo_debt!D23/cbo_ngdp!D23 -> #N/A | E23: =100*cbo_debt!E23/cbo_ngdp!E23 -> #N/A | F23: =100*cbo_debt!F23/cbo_ngdp!F23 -> #N/A | G23: =100*cbo_debt!G23/cbo_ngdp!G23 -> #N/A | H23: =100*cbo_debt!H23/cbo_ngdp!H23 -> #N/A | I23: =100*cbo_debt!I23/cbo_ngdp!I23 -> #N/A | J23: =100*cbo_debt!J23/cbo_ngdp!B23 -> #N/A | K23: =100*cbo_debt!K23/cbo_ngdp!K23 -> #N/A | L23: =100*cbo_debt!L23/cbo_ngdp!L23 -> #N/A | M23: =100*cbo_debt!M23/cbo_ngdp!M23 -> #N/A | N23: =100*cbo_debt!N23/cbo_ngdp!N23 -> #N/A | O23: =100*cbo_debt!O23/cbo_ngdp!O23 -> #N/A | P23: =100*cbo_debt!P23/cbo_ngdp!P23 -> 41.319108 | Q23: =100*cbo_debt!Q23/cbo_ngdp!Q23 -> 44.78098 | R23: =100*cbo_debt!R23/cbo_ngdp!R23 -> 44.215896 | ... AT23: =100*cbo_debt!AT23/cbo_ngdp!AT23 -> #N/A | AU23: #N/A | AV23: =100*cbo_debt!AV23/cbo_ngdp!AV23 -> #N/A | AW23: #N/A | AX23: #N/A | AY23: #N/A | AZ23: #N/A | BA23: #N/A | BB23: #N/A | BC23: #N/A | BD23: #N/A | BE23: #N/A | BF23: #N/A | BG23: #N/A | BH23: #N/A | BI23: #N/A | BJ23: #N/A | BK23: #N/A | BL23: #N/A | BM23: #N/A | BN23: #N/A | BO23: #N/A | BP23: #N/A | BQ23: #N/A | BR23: #N/A | BS23: #N/A | BT23: #N/A | BU23: #N/A | BV23: #N/A | BW23: #N/A | BX23: #N/A | BY23: #N/A | BZ23: #N/A | CA23: #N/A | CB23: #N/A | CC23: #N/A | CD23: #N/A | CE23: #N/A | CF23: #N/A | CG23: #N/A | CH23: #N/A | CI23: #N/A | CJ23: #N/A | CK23: #N/A | CL23: #N/A | CM23: #N/A | CN23: #N/A | CO23: #N/A | CP23: #N/A | CQ23: #N/A | CR23: #N/A | CS23: 46.758105 | CU23: 32356 | CV23: =OFFSET(C$1,0,ROWS($1:17)-1) -> 1988B | CW23: =LEFT(CV23,4)+$CW$5 -> 1988 | CX23: {=INDEX($C$6:$CS$100,MATCH(CW23,YEAR($B$6:$B$100),0),MATCH(CV23,$C$1:$CS$1,0))} -> 42.587545 | CY23: =LEFT(CV23,4)+$CY$5 -> 1993 | CZ23: {=INDEX($C$6:$CS$100,MATCH(CY23,YEAR($B$6:$B$100),0),MATCH(CV23,$C$1:$CS$1,0))} -> 40.913938 | DA23: =LEFT(CV23,4)+$DA$5 -> 1998 | DB23: {=INDEX($C$6:$CS$100,MATCH(DA23,YEAR($B$6:$B$100),0),MATCH(CV23,$C$1:$CS$1,0))} -> #N/A | DD23: =VLOOKUP(DATE(CW23,1,1),$B$6:$CS$66,96,FALSE) -> 39.929947 | DE23: =VLOOKUP(DATE(CY23,1,1),$B$6:$CS$66,96,FALSE) -> 47.940959 | DF23: =(DD23-CX23)^2 -> 7.0628223 | DG23: =(DE23-CZ23)^2 -> 49.379036
A24: 1993 | B24: 33970 | C24: =100*cbo_debt!C24/cbo_ngdp!C24 -> #N/A | D24: =100*cbo_debt!D24/cbo_ngdp!D24 -> #N/A | E24: =100*cbo_debt!E24/cbo_ngdp!E24 -> #N/A | F24: =100*cbo_debt!F24/cbo_ngdp!F24 -> #N/A | G24: =100*cbo_debt!G24/cbo_ngdp!G24 -> #N/A | H24: =100*cbo_debt!H24/cbo_ngdp!H24 -> #N/A | I24: =100*cbo_debt!I24/cbo_ngdp!I24 -> #N/A | J24: =100*cbo_debt!J24/cbo_ngdp!B24 -> #N/A | K24: =100*cbo_debt!K24/cbo_ngdp!K24 -> #N/A | L24: =100*cbo_debt!L24/cbo_ngdp!L24 -> #N/A | M24: =100*cbo_debt!M24/cbo_ngdp!M24 -> #N/A | N24: =100*cbo_debt!N24/cbo_ngdp!N24 -> #N/A | O24: =100*cbo_debt!O24/cbo_ngdp!O24 -> #N/A | P24: =100*cbo_debt!P24/cbo_ngdp!P24 -> #N/A | Q24: =100*cbo_debt!Q24/cbo_ngdp!Q24 -> #N/A | R24: =100*cbo_debt!R24/cbo_ngdp!R24 -> 43.404648 | ... AT24: =100*cbo_debt!AT24/cbo_ngdp!AT24 -> #N/A | AU24: #N/A | AV24: =100*cbo_debt!AV24/cbo_ngdp!AV24 -> #N/A | AW24: #N/A | AX24: #N/A | AY24: #N/A | AZ24: #N/A | BA24: #N/A | BB24: #N/A | BC24: #N/A | BD24: #N/A | BE24: #N/A | BF24: #N/A | BG24: #N/A | BH24: #N/A | BI24: #N/A | BJ24: #N/A | BK24: #N/A | BL24: #N/A | BM24: #N/A | BN24: #N/A | BO24: #N/A | BP24: #N/A | BQ24: #N/A | BR24: #N/A | BS24: #N/A | BT24: #N/A | BU24: #N/A | BV24: #N/A | BW24: #N/A | BX24: #N/A | BY24: #N/A | BZ24: #N/A | CA24: #N/A | CB24: #N/A | CC24: #N/A | CD24: #N/A | CE24: #N/A | CF24: #N/A | CG24: #N/A | CH24: #N/A | CI24: #N/A | CJ24: #N/A | CK24: #N/A | CL24: #N/A | CM24: #N/A | CN24: #N/A | CO24: #N/A | CP24: #N/A | CQ24: #N/A | CR24: #N/A | CS24: 47.940959 | CU24: 32509 | CV24: =OFFSET(C$1,0,ROWS($1:18)-1) -> 1989A | CW24: =LEFT(CV24,4)+$CW$5 -> 1989 | CX24: {=INDEX($C$6:$CS$100,MATCH(CW24,YEAR($B$6:$B$100),0),MATCH(CV24,$C$1:$CS$1,0))} -> 42.756736 | CY24: =LEFT(CV24,4)+$CY$5 -> 1994 | CZ24: {=INDEX($C$6:$CS$100,MATCH(CY24,YEAR($B$6:$B$100),0),MATCH(CV24,$C$1:$CS$1,0))} -> 40.722238 | DA24: =LEFT(CV24,4)+$DA$5 -> 1999 | DB24: {=INDEX($C$6:$CS$100,MATCH(DA24,YEAR($B$6:$B$100),0),MATCH(CV24,$C$1:$CS$1,0))} -> #N/A | DD24: =VLOOKUP(DATE(CW24,1,1),$B$6:$CS$66,96,FALSE) -> 39.441944 | DE24: =VLOOKUP(DATE(CY24,1,1),$B$6:$CS$66,96,FALSE) -> 47.833357 | DF24: =(DD24-CX24)^2 -> 10.987842 | DG24: =(DE24-CZ24)^2 -> 50.568006
A25: 1994 | B25: 34335 | C25: =100*cbo_debt!C25/cbo_ngdp!C25 -> #N/A | D25: =100*cbo_debt!D25/cbo_ngdp!D25 -> #N/A | E25: =100*cbo_debt!E25/cbo_ngdp!E25 -> #N/A | F25: =100*cbo_debt!F25/cbo_ngdp!F25 -> #N/A | G25: =100*cbo_debt!G25/cbo_ngdp!G25 -> #N/A | H25: =100*cbo_debt!H25/cbo_ngdp!H25 -> #N/A | I25: =100*cbo_debt!I25/cbo_ngdp!I25 -> #N/A | J25: =100*cbo_debt!J25/cbo_ngdp!B25 -> #N/A | K25: =100*cbo_debt!K25/cbo_ngdp!K25 -> #N/A | L25: =100*cbo_debt!L25/cbo_ngdp!L25 -> #N/A | M25: =100*cbo_debt!M25/cbo_ngdp!M25 -> #N/A | N25: =100*cbo_debt!N25/cbo_ngdp!N25 -> #N/A | O25: =100*cbo_debt!O25/cbo_ngdp!O25 -> #N/A | P25: =100*cbo_debt!P25/cbo_ngdp!P25 -> #N/A | Q25: =100*cbo_debt!Q25/cbo_ngdp!Q25 -> #N/A | R25: =100*cbo_debt!R25/cbo_ngdp!R25 -> #N/A | ... AT25: =100*cbo_debt!AT25/cbo_ngdp!AT25 -> #N/A | AU25: #N/A | AV25: =100*cbo_debt!AV25/cbo_ngdp!AV25 -> #N/A | AW25: #N/A | AX25: #N/A | AY25: #N/A | AZ25: #N/A | BA25: #N/A | BB25: #N/A | BC25: #N/A | BD25: #N/A | BE25: #N/A | BF25: #N/A | BG25: #N/A | BH25: #N/A | BI25: #N/A | BJ25: #N/A | BK25: #N/A | BL25: #N/A | BM25: #N/A | BN25: #N/A | BO25: #N/A | BP25: #N/A | BQ25: #N/A | BR25: #N/A | BS25: #N/A | BT25: #N/A | BU25: #N/A | BV25: #N/A | BW25: #N/A | BX25: #N/A | BY25: #N/A | BZ25: #N/A | CA25: #N/A | CB25: #N/A | CC25: #N/A | CD25: #N/A | CE25: #N/A | CF25: #N/A | CG25: #N/A | CH25: #N/A | CI25: #N/A | CJ25: #N/A | CK25: #N/A | CL25: #N/A | CM25: #N/A | CN25: #N/A | CO25: #N/A | CP25: #N/A | CQ25: #N/A | CR25: #N/A | CS25: 47.833357 | CU25: 32721 | CV25: =OFFSET(C$1,0,ROWS($1:19)-1) -> 1989B | CW25: =LEFT(CV25,4)+$CW$5 -> 1989 | CX25: {=INDEX($C$6:$CS$100,MATCH(CW25,YEAR($B$6:$B$100),0),MATCH(CV25,$C$1:$CS$1,0))} -> 42.740366 | CY25: =LEFT(CV25,4)+$CY$5 -> 1994 | CZ25: {=INDEX($C$6:$CS$100,MATCH(CY25,YEAR($B$6:$B$100),0),MATCH(CV25,$C$1:$CS$1,0))} -> 40.658413 | DA25: =LEFT(CV25,4)+$DA$5 -> 1999 | DB25: {=INDEX($C$6:$CS$100,MATCH(DA25,YEAR($B$6:$B$100),0),MATCH(CV25,$C$1:$CS$1,0))} -> #N/A | DD25: =VLOOKUP(DATE(CW25,1,1),$B$6:$CS$66,96,FALSE) -> 39.441944 | DE25: =VLOOKUP(DATE(CY25,1,1),$B$6:$CS$66,96,FALSE) -> 47.833357 | DF25: =(DD25-CX25)^2 -> 10.879586 | DG25: =(DE25-CZ25)^2 -> 51.479814
